[{"author": "oflg", "core-version": ">=5.2.1", "dependents": "$:/plugins/oflg/fishing-cannedfish", "description": "记忆包", "list": "readme", "name": "北师大版一年级起点三年级下", "parent-plugin": "$:/plugins/oflg/fishing-cannedfish", "plugin-type": "plugin", "source": "https://github.com/oflg/fishing-cannedfish", "title": "$:/plugins/oflg/fishing-cannedfish/北师大版一年级起点三年级下", "version": "0.0.2", "type": "application/json", "text": "{\"tiddlers\": {\"$:/plugins/oflg/fishing-cannedfish/北师大版一年级起点三年级下/readme\": {\"title\": \"$:/plugins/oflg/fishing-cannedfish/北师大版一年级起点三年级下/readme\", \"text\": \"Installation and usage tutorial is available at [[Fishing Manual|https://oflg.github.io/fishing/]].\\n\\n可在 [[钓鱼手册|https://oflg.github.io/fishing/]] 查看安装使用教程。\"}, \"$:/plugins/oflg/fishing/fishingrod/[all[shadows+tiddlers]tag[?]prefix[北师大版一年级起点三年级下/]]\": {\"title\": \"$:/plugins/oflg/fishing/fishingrod/[all[shadows+tiddlers]tag[?]prefix[北师大版一年级起点三年级下/]]\", \"caption\": \"北师大版一年级起点三年级下\"}, \"$:/plugins/oflg/fishing-cannedfish/北师大版一年级起点三年级下/SearchWord\": {\"title\": \"$:/plugins/oflg/fishing-cannedfish/北师大版一年级起点三年级下/SearchWord\", \"tags\": \"$:/tags/QuestionTemplate\", \"word\": \"fishing\", \"text\": \"<$reveal\\n            state=<<folded-state>>\\n            type=\\\"match\\\"\\n            text=\\\"hide\\\"\\n            animate=\\\"yes\\\"\\n        >\\n            {{!!word}}\\n        </$reveal>\\n\\n    <span\\n        class=\\\"tc-fish-title\\\"\\n    >\\n        <$reveal\\n            state=<<folded-state>>\\n            type=\\\"nomatch\\\"\\n            text=\\\"hide\\\"\\n            animate=\\\"yes\\\"\\n        >\\n            <main style=\\\"width:100%;overflow:hidden;\\\"> \\n                <iframe id={{!!word}}\\n                    title={{!!word}}\\n                    height=\\\"700px\\\"\\n                    width=\\\"100%\\\"\\n                    src={{{[{!!word}encodeuricomponent[]addprefix[https://quark.sm.cn/api/rest?method=quark_fanyi.dlpage&format=html&schema=v2&entry=top#en/zh/]]}}}\\n                    frameborder=0\\n                    seamless=\\\"seamless\\\"\\n                    style=\\\"margin:-200px 0 -110px 0;\\\"\\n                    marginheight=\\\"0\\\"\\n                    marginwidth=\\\"0\\\"\\n                />\\n            </main>\\n        </$reveal>\\n    </span>\"}, \"北师大版一年级起点三年级下/20220119011922801462\": {\"title\": \"北师大版一年级起点三年级下/20220119011922801462\", \"tags\": \"[[Unit 7]] ?\", \"word\": \"restaurant\", \"created\": \"20220119011922801462\", \"caption\": \"{{||$:/plugins/oflg/fishing-cannedfish/北师大版一年级起点三年级下/SearchWord}}\"}, \"北师大版一年级起点三年级下/20220119011922801479\": {\"title\": \"北师大版一年级起点三年级下/20220119011922801479\", \"tags\": \"[[Unit 7]] ?\", \"word\": \"menu\", \"created\": \"20220119011922801479\", \"caption\": \"{{||$:/plugins/oflg/fishing-cannedfish/北师大版一年级起点三年级下/SearchWord}}\"}, \"北师大版一年级起点三年级下/20220119011922801484\": {\"title\": \"北师大版一年级起点三年级下/20220119011922801484\", \"tags\": \"[[Unit 7]] ?\", \"word\": \"like\", \"created\": \"20220119011922801484\", \"caption\": \"{{||$:/plugins/oflg/fishing-cannedfish/北师大版一年级起点三年级下/SearchWord}}\"}, \"北师大版一年级起点三年级下/20220119011922801489\": {\"title\": \"北师大版一年级起点三年级下/20220119011922801489\", \"tags\": \"[[Unit 7]] ?\", \"word\": \"chicken\", \"created\": \"20220119011922801489\", \"caption\": \"{{||$:/plugins/oflg/fishing-cannedfish/北师大版一年级起点三年级下/SearchWord}}\"}, \"北师大版一年级起点三年级下/20220119011922801493\": {\"title\": \"北师大版一年级起点三年级下/20220119011922801493\", \"tags\": \"[[Unit 7]] ?\", \"word\": \"noodles\", \"created\": \"20220119011922801493\", \"caption\": \"{{||$:/plugins/oflg/fishing-cannedfish/北师大版一年级起点三年级下/SearchWord}}\"}, \"北师大版一年级起点三年级下/20220119011922801496\": {\"title\": \"北师大版一年级起点三年级下/20220119011922801496\", \"tags\": \"[[Unit 7]] ?\", \"word\": \"bread\", \"created\": \"20220119011922801496\", \"caption\": \"{{||$:/plugins/oflg/fishing-cannedfish/北师大版一年级起点三年级下/SearchWord}}\"}, \"北师大版一年级起点三年级下/20220119011922801500\": {\"title\": \"北师大版一年级起点三年级下/20220119011922801500\", \"tags\": \"[[Unit 7]] ?\", \"word\": \"fruit\", \"created\": \"20220119011922801500\", \"caption\": \"{{||$:/plugins/oflg/fishing-cannedfish/北师大版一年级起点三年级下/SearchWord}}\"}, \"北师大版一年级起点三年级下/20220119011922801504\": {\"title\": \"北师大版一年级起点三年级下/20220119011922801504\", \"tags\": \"[[Unit 7]] ?\", \"word\": \"meat\", \"created\": \"20220119011922801504\", \"caption\": \"{{||$:/plugins/oflg/fishing-cannedfish/北师大版一年级起点三年级下/SearchWord}}\"}, \"北师大版一年级起点三年级下/20220119011922801508\": {\"title\": \"北师大版一年级起点三年级下/20220119011922801508\", \"tags\": \"[[Unit 7]] ?\", \"word\": \"vegetables\", \"created\": \"20220119011922801508\", \"caption\": \"{{||$:/plugins/oflg/fishing-cannedfish/北师大版一年级起点三年级下/SearchWord}}\"}, \"北师大版一年级起点三年级下/20220119011922801511\": {\"title\": \"北师大版一年级起点三年级下/20220119011922801511\", \"tags\": \"[[Unit 7]] ?\", \"word\": \"dumplings\", \"created\": \"20220119011922801511\", \"caption\": \"{{||$:/plugins/oflg/fishing-cannedfish/北师大版一年级起点三年级下/SearchWord}}\"}, \"北师大版一年级起点三年级下/20220119011922801515\": {\"title\": \"北师大版一年级起点三年级下/20220119011922801515\", \"tags\": \"[[Unit 7]] ?\", \"word\": \"hamburgers\", \"created\": \"20220119011922801515\", \"caption\": \"{{||$:/plugins/oflg/fishing-cannedfish/北师大版一年级起点三年级下/SearchWord}}\"}, \"北师大版一年级起点三年级下/20220119011922801519\": {\"title\": \"北师大版一年级起点三年级下/20220119011922801519\", \"tags\": \"[[Unit 8]] ?\", \"word\": \"big\", \"created\": \"20220119011922801519\", \"caption\": \"{{||$:/plugins/oflg/fishing-cannedfish/北师大版一年级起点三年级下/SearchWord}}\"}, \"北师大版一年级起点三年级下/20220119011922801523\": {\"title\": \"北师大版一年级起点三年级下/20220119011922801523\", \"tags\": \"[[Unit 8]] ?\", \"word\": \"beautiful\", \"created\": \"20220119011922801523\", \"caption\": \"{{||$:/plugins/oflg/fishing-cannedfish/北师大版一年级起点三年级下/SearchWord}}\"}, \"北师大版一年级起点三年级下/20220119011922801526\": {\"title\": \"北师大版一年级起点三年级下/20220119011922801526\", \"tags\": \"[[Unit 8]] ?\", \"word\": \"tall\", \"created\": \"20220119011922801526\", \"caption\": \"{{||$:/plugins/oflg/fishing-cannedfish/北师大版一年级起点三年级下/SearchWord}}\"}, \"北师大版一年级起点三年级下/20220119011922801530\": {\"title\": \"北师大版一年级起点三年级下/20220119011922801530\", \"tags\": \"[[Unit 8]] ?\", \"word\": \"small\", \"created\": \"20220119011922801530\", \"caption\": \"{{||$:/plugins/oflg/fishing-cannedfish/北师大版一年级起点三年级下/SearchWord}}\"}, \"北师大版一年级起点三年级下/20220119011922801533\": {\"title\": \"北师大版一年级起点三年级下/20220119011922801533\", \"tags\": \"[[Unit 8]] ?\", \"word\": \"peacock\", \"created\": \"20220119011922801533\", \"caption\": \"{{||$:/plugins/oflg/fishing-cannedfish/北师大版一年级起点三年级下/SearchWord}}\"}, \"北师大版一年级起点三年级下/20220119011922801537\": {\"title\": \"北师大版一年级起点三年级下/20220119011922801537\", \"tags\": \"[[Unit 8]] ?\", \"word\": \"old\", \"created\": \"20220119011922801537\", \"caption\": \"{{||$:/plugins/oflg/fishing-cannedfish/北师大版一年级起点三年级下/SearchWord}}\"}, \"北师大版一年级起点三年级下/20220119011922801540\": {\"title\": \"北师大版一年级起点三年级下/20220119011922801540\", \"tags\": \"[[Unit 8]] ?\", \"word\": \"turtle\", \"created\": \"20220119011922801540\", \"caption\": \"{{||$:/plugins/oflg/fishing-cannedfish/北师大版一年级起点三年级下/SearchWord}}\"}, \"北师大版一年级起点三年级下/20220119011922801544\": {\"title\": \"北师大版一年级起点三年级下/20220119011922801544\", \"tags\": \"[[Unit 8]] ?\", \"word\": \"young\", \"created\": \"20220119011922801544\", \"caption\": \"{{||$:/plugins/oflg/fishing-cannedfish/北师大版一年级起点三年级下/SearchWord}}\"}, \"北师大版一年级起点三年级下/20220119011922801548\": {\"title\": \"北师大版一年级起点三年级下/20220119011922801548\", \"tags\": \"[[Unit 8]] ?\", \"word\": \"bad\", \"created\": \"20220119011922801548\", \"caption\": \"{{||$:/plugins/oflg/fishing-cannedfish/北师大版一年级起点三年级下/SearchWord}}\"}, \"北师大版一年级起点三年级下/20220119011922801552\": {\"title\": \"北师大版一年级起点三年级下/20220119011922801552\", \"tags\": \"[[Unit 8]] ?\", \"word\": \"good\", \"created\": \"20220119011922801552\", \"caption\": \"{{||$:/plugins/oflg/fishing-cannedfish/北师大版一年级起点三年级下/SearchWord}}\"}, \"北师大版一年级起点三年级下/20220119011922801556\": {\"title\": \"北师大版一年级起点三年级下/20220119011922801556\", \"tags\": \"[[Unit 8]] ?\", \"word\": \"happy\", \"created\": \"20220119011922801556\", \"caption\": \"{{||$:/plugins/oflg/fishing-cannedfish/北师大版一年级起点三年级下/SearchWord}}\"}, \"北师大版一年级起点三年级下/20220119011922801559\": {\"title\": \"北师大版一年级起点三年级下/20220119011922801559\", \"tags\": \"[[Unit 8]] ?\", \"word\": \"short\", \"created\": \"20220119011922801559\", \"caption\": \"{{||$:/plugins/oflg/fishing-cannedfish/北师大版一年级起点三年级下/SearchWord}}\"}, \"北师大版一年级起点三年级下/20220119011922801563\": {\"title\": \"北师大版一年级起点三年级下/20220119011922801563\", \"tags\": \"[[Unit 8]] ?\", \"word\": \"fast\", \"created\": \"20220119011922801563\", \"caption\": \"{{||$:/plugins/oflg/fishing-cannedfish/北师大版一年级起点三年级下/SearchWord}}\"}, \"北师大版一年级起点三年级下/20220119011922801566\": {\"title\": \"北师大版一年级起点三年级下/20220119011922801566\", \"tags\": \"[[Unit 8]] ?\", \"word\": \"slow\", \"created\": \"20220119011922801566\", \"caption\": \"{{||$:/plugins/oflg/fishing-cannedfish/北师大版一年级起点三年级下/SearchWord}}\"}, \"北师大版一年级起点三年级下/20220119011922801570\": {\"title\": \"北师大版一年级起点三年级下/20220119011922801570\", \"tags\": \"[[Unit 8]] ?\", \"word\": \"fat\", \"created\": \"20220119011922801570\", \"caption\": \"{{||$:/plugins/oflg/fishing-cannedfish/北师大版一年级起点三年级下/SearchWord}}\"}, \"北师大版一年级起点三年级下/20220119011922801573\": {\"title\": \"北师大版一年级起点三年级下/20220119011922801573\", \"tags\": \"[[Unit 8]] ?\", \"word\": \"thin\", \"created\": \"20220119011922801573\", \"caption\": \"{{||$:/plugins/oflg/fishing-cannedfish/北师大版一年级起点三年级下/SearchWord}}\"}, \"北师大版一年级起点三年级下/20220119011922801576\": {\"title\": \"北师大版一年级起点三年级下/20220119011922801576\", \"tags\": \"[[Unit 8]] ?\", \"word\": \"long\", \"created\": \"20220119011922801576\", \"caption\": \"{{||$:/plugins/oflg/fishing-cannedfish/北师大版一年级起点三年级下/SearchWord}}\"}, \"北师大版一年级起点三年级下/20220119011922801581\": {\"title\": \"北师大版一年级起点三年级下/20220119011922801581\", \"tags\": \"[[Unit 9]] ?\", \"word\": \"hot\", \"created\": \"20220119011922801581\", \"caption\": \"{{||$:/plugins/oflg/fishing-cannedfish/北师大版一年级起点三年级下/SearchWord}}\"}, \"北师大版一年级起点三年级下/20220119011922801584\": {\"title\": \"北师大版一年级起点三年级下/20220119011922801584\", \"tags\": \"[[Unit 9]] ?\", \"word\": \"soup\", \"created\": \"20220119011922801584\", \"caption\": \"{{||$:/plugins/oflg/fishing-cannedfish/北师大版一年级起点三年级下/SearchWord}}\"}, \"北师大版一年级起点三年级下/20220119011922801588\": {\"title\": \"北师大版一年级起点三年级下/20220119011922801588\", \"tags\": \"[[Unit 9]] ?\", \"word\": \"thirsty\", \"created\": \"20220119011922801588\", \"caption\": \"{{||$:/plugins/oflg/fishing-cannedfish/北师大版一年级起点三年级下/SearchWord}}\"}, \"北师大版一年级起点三年级下/20220119011922801592\": {\"title\": \"北师大版一年级起点三年级下/20220119011922801592\", \"tags\": \"[[Unit 9]] ?\", \"word\": \"some\", \"created\": \"20220119011922801592\", \"caption\": \"{{||$:/plugins/oflg/fishing-cannedfish/北师大版一年级起点三年级下/SearchWord}}\"}, \"北师大版一年级起点三年级下/20220119011922801595\": {\"title\": \"北师大版一年级起点三年级下/20220119011922801595\", \"tags\": \"[[Unit 9]] ?\", \"word\": \"cola\", \"created\": \"20220119011922801595\", \"caption\": \"{{||$:/plugins/oflg/fishing-cannedfish/北师大版一年级起点三年级下/SearchWord}}\"}, \"北师大版一年级起点三年级下/20220119011922801599\": {\"title\": \"北师大版一年级起点三年级下/20220119011922801599\", \"tags\": \"[[Unit 9]] ?\", \"word\": \"hungry\", \"created\": \"20220119011922801599\", \"caption\": \"{{||$:/plugins/oflg/fishing-cannedfish/北师大版一年级起点三年级下/SearchWord}}\"}, \"北师大版一年级起点三年级下/20220119011922801602\": {\"title\": \"北师大版一年级起点三年级下/20220119011922801602\", \"tags\": \"[[Unit 9]] ?\", \"word\": \"milk\", \"created\": \"20220119011922801602\", \"caption\": \"{{||$:/plugins/oflg/fishing-cannedfish/北师大版一年级起点三年级下/SearchWord}}\"}, \"北师大版一年级起点三年级下/20220119011922801606\": {\"title\": \"北师大版一年级起点三年级下/20220119011922801606\", \"tags\": \"[[Unit 9]] ?\", \"word\": \"cold\", \"created\": \"20220119011922801606\", \"caption\": \"{{||$:/plugins/oflg/fishing-cannedfish/北师大版一年级起点三年级下/SearchWord}}\"}, \"北师大版一年级起点三年级下/20220119011922801610\": {\"title\": \"北师大版一年级起点三年级下/20220119011922801610\", \"tags\": \"[[Unit 9]] ?\", \"word\": \"fresh\", \"created\": \"20220119011922801610\", \"caption\": \"{{||$:/plugins/oflg/fishing-cannedfish/北师大版一年级起点三年级下/SearchWord}}\"}, \"北师大版一年级起点三年级下/20220119011922801613\": {\"title\": \"北师大版一年级起点三年级下/20220119011922801613\", \"tags\": \"[[Unit 9]] ?\", \"word\": \"favorite\", \"created\": \"20220119011922801613\", \"caption\": \"{{||$:/plugins/oflg/fishing-cannedfish/北师大版一年级起点三年级下/SearchWord}}\"}, \"北师大版一年级起点三年级下/20220119011922801617\": {\"title\": \"北师大版一年级起点三年级下/20220119011922801617\", \"tags\": \"[[Unit 9]] ?\", \"word\": \"coffee\", \"created\": \"20220119011922801617\", \"caption\": \"{{||$:/plugins/oflg/fishing-cannedfish/北师大版一年级起点三年级下/SearchWord}}\"}, \"北师大版一年级起点三年级下/20220119011922801620\": {\"title\": \"北师大版一年级起点三年级下/20220119011922801620\", \"tags\": \"[[Unit 9]] ?\", \"word\": \"water\", \"created\": \"20220119011922801620\", \"caption\": \"{{||$:/plugins/oflg/fishing-cannedfish/北师大版一年级起点三年级下/SearchWord}}\"}, \"北师大版一年级起点三年级下/20220119011922801624\": {\"title\": \"北师大版一年级起点三年级下/20220119011922801624\", \"tags\": \"[[Unit 9]] ?\", \"word\": \"iced tea\", \"created\": \"20220119011922801624\", \"caption\": \"{{||$:/plugins/oflg/fishing-cannedfish/北师大版一年级起点三年级下/SearchWord}}\"}, \"北师大版一年级起点三年级下/20220119011922801629\": {\"title\": \"北师大版一年级起点三年级下/20220119011922801629\", \"tags\": \"[[Unit 10]] ?\", \"word\": \"store\", \"created\": \"20220119011922801629\", \"caption\": \"{{||$:/plugins/oflg/fishing-cannedfish/北师大版一年级起点三年级下/SearchWord}}\"}, \"北师大版一年级起点三年级下/20220119011922801632\": {\"title\": \"北师大版一年级起点三年级下/20220119011922801632\", \"tags\": \"[[Unit 10]] ?\", \"word\": \"hat\", \"created\": \"20220119011922801632\", \"caption\": \"{{||$:/plugins/oflg/fishing-cannedfish/北师大版一年级起点三年级下/SearchWord}}\"}, \"北师大版一年级起点三年级下/20220119011922801635\": {\"title\": \"北师大版一年级起点三年级下/20220119011922801635\", \"tags\": \"[[Unit 10]] ?\", \"word\": \"new\", \"created\": \"20220119011922801635\", \"caption\": \"{{||$:/plugins/oflg/fishing-cannedfish/北师大版一年级起点三年级下/SearchWord}}\"}, \"北师大版一年级起点三年级下/20220119011922801639\": {\"title\": \"北师大版一年级起点三年级下/20220119011922801639\", \"tags\": \"[[Unit 10]] ?\", \"word\": \"clock\", \"created\": \"20220119011922801639\", \"caption\": \"{{||$:/plugins/oflg/fishing-cannedfish/北师大版一年级起点三年级下/SearchWord}}\"}, \"北师大版一年级起点三年级下/20220119011922801642\": {\"title\": \"北师大版一年级起点三年级下/20220119011922801642\", \"tags\": \"[[Unit 10]] ?\", \"word\": \"storybook\", \"created\": \"20220119011922801642\", \"caption\": \"{{||$:/plugins/oflg/fishing-cannedfish/北师大版一年级起点三年级下/SearchWord}}\"}, \"北师大版一年级起点三年级下/20220119011922801646\": {\"title\": \"北师大版一年级起点三年级下/20220119011922801646\", \"tags\": \"[[Unit 10]] ?\", \"word\": \"sell\", \"created\": \"20220119011922801646\", \"caption\": \"{{||$:/plugins/oflg/fishing-cannedfish/北师大版一年级起点三年级下/SearchWord}}\"}, \"北师大版一年级起点三年级下/20220119011922801650\": {\"title\": \"北师大版一年级起点三年级下/20220119011922801650\", \"tags\": \"[[Unit 10]] ?\", \"word\": \"newspaper\", \"created\": \"20220119011922801650\", \"caption\": \"{{||$:/plugins/oflg/fishing-cannedfish/北师大版一年级起点三年级下/SearchWord}}\"}, \"北师大版一年级起点三年级下/20220119011922801653\": {\"title\": \"北师大版一年级起点三年级下/20220119011922801653\", \"tags\": \"[[Unit 10]] ?\", \"word\": \"magazine\", \"created\": \"20220119011922801653\", \"caption\": \"{{||$:/plugins/oflg/fishing-cannedfish/北师大版一年级起点三年级下/SearchWord}}\"}, \"北师大版一年级起点三年级下/20220119011922801657\": {\"title\": \"北师大版一年级起点三年级下/20220119011922801657\", \"tags\": \"[[Unit 10]] ?\", \"word\": \"watch\", \"created\": \"20220119011922801657\", \"caption\": \"{{||$:/plugins/oflg/fishing-cannedfish/北师大版一年级起点三年级下/SearchWord}}\"}, \"北师大版一年级起点三年级下/20220119011922801660\": {\"title\": \"北师大版一年级起点三年级下/20220119011922801660\", \"tags\": \"[[Unit 10]] ?\", \"word\": \"umbrella\", \"created\": \"20220119011922801660\", \"caption\": \"{{||$:/plugins/oflg/fishing-cannedfish/北师大版一年级起点三年级下/SearchWord}}\"}, \"北师大版一年级起点三年级下/20220119011922801664\": {\"title\": \"北师大版一年级起点三年级下/20220119011922801664\", \"tags\": \"[[Unit 10]] ?\", \"word\": \"toys\", \"created\": \"20220119011922801664\", \"caption\": \"{{||$:/plugins/oflg/fishing-cannedfish/北师大版一年级起点三年级下/SearchWord}}\"}, \"北师大版一年级起点三年级下/20220119011922801668\": {\"title\": \"北师大版一年级起点三年级下/20220119011922801668\", \"tags\": \"[[Unit 11]] ?\", \"word\": \"well\", \"created\": \"20220119011922801668\", \"caption\": \"{{||$:/plugins/oflg/fishing-cannedfish/北师大版一年级起点三年级下/SearchWord}}\"}, \"北师大版一年级起点三年级下/20220119011922801671\": {\"title\": \"北师大版一年级起点三年级下/20220119011922801671\", \"tags\": \"[[Unit 11]] ?\", \"word\": \"stomach\", \"created\": \"20220119011922801671\", \"caption\": \"{{||$:/plugins/oflg/fishing-cannedfish/北师大版一年级起点三年级下/SearchWord}}\"}, \"北师大版一年级起点三年级下/20220119011922801675\": {\"title\": \"北师大版一年级起点三年级下/20220119011922801675\", \"tags\": \"[[Unit 11]] ?\", \"word\": \"hurt\", \"created\": \"20220119011922801675\", \"caption\": \"{{||$:/plugins/oflg/fishing-cannedfish/北师大版一年级起点三年级下/SearchWord}}\"}, \"北师大版一年级起点三年级下/20220119011922801678\": {\"title\": \"北师大版一年级起点三年级下/20220119011922801678\", \"tags\": \"[[Unit 11]] ?\", \"word\": \"mouth\", \"created\": \"20220119011922801678\", \"caption\": \"{{||$:/plugins/oflg/fishing-cannedfish/北师大版一年级起点三年级下/SearchWord}}\"}, \"北师大版一年级起点三年级下/20220119011922801681\": {\"title\": \"北师大版一年级起点三年级下/20220119011922801681\", \"tags\": \"[[Unit 11]] ?\", \"word\": \"hair\", \"created\": \"20220119011922801681\", \"caption\": \"{{||$:/plugins/oflg/fishing-cannedfish/北师大版一年级起点三年级下/SearchWord}}\"}, \"北师大版一年级起点三年级下/20220119011922801685\": {\"title\": \"北师大版一年级起点三年级下/20220119011922801685\", \"tags\": \"[[Unit 11]] ?\", \"word\": \"face\", \"created\": \"20220119011922801685\", \"caption\": \"{{||$:/plugins/oflg/fishing-cannedfish/北师大版一年级起点三年级下/SearchWord}}\"}, \"北师大版一年级起点三年级下/20220119011922801689\": {\"title\": \"北师大版一年级起点三年级下/20220119011922801689\", \"tags\": \"[[Unit 11]] ?\", \"word\": \"head\", \"created\": \"20220119011922801689\", \"caption\": \"{{||$:/plugins/oflg/fishing-cannedfish/北师大版一年级起点三年级下/SearchWord}}\"}, \"北师大版一年级起点三年级下/20220119011922801692\": {\"title\": \"北师大版一年级起点三年级下/20220119011922801692\", \"tags\": \"[[Unit 11]] ?\", \"word\": \"arm\", \"created\": \"20220119011922801692\", \"caption\": \"{{||$:/plugins/oflg/fishing-cannedfish/北师大版一年级起点三年级下/SearchWord}}\"}, \"北师大版一年级起点三年级下/20220119011922801696\": {\"title\": \"北师大版一年级起点三年级下/20220119011922801696\", \"tags\": \"[[Unit 11]] ?\", \"word\": \"hand\", \"created\": \"20220119011922801696\", \"caption\": \"{{||$:/plugins/oflg/fishing-cannedfish/北师大版一年级起点三年级下/SearchWord}}\"}, \"北师大版一年级起点三年级下/20220119011922801700\": {\"title\": \"北师大版一年级起点三年级下/20220119011922801700\", \"tags\": \"[[Unit 11]] ?\", \"word\": \"leg\", \"created\": \"20220119011922801700\", \"caption\": \"{{||$:/plugins/oflg/fishing-cannedfish/北师大版一年级起点三年级下/SearchWord}}\"}, \"北师大版一年级起点三年级下/20220119011922801703\": {\"title\": \"北师大版一年级起点三年级下/20220119011922801703\", \"tags\": \"[[Unit 11]] ?\", \"word\": \"foot\", \"created\": \"20220119011922801703\", \"caption\": \"{{||$:/plugins/oflg/fishing-cannedfish/北师大版一年级起点三年级下/SearchWord}}\"}, \"北师大版一年级起点三年级下/20220119011922801707\": {\"title\": \"北师大版一年级起点三年级下/20220119011922801707\", \"tags\": \"[[Unit 12]] ?\", \"word\": \"ticket\", \"created\": \"20220119011922801707\", \"caption\": \"{{||$:/plugins/oflg/fishing-cannedfish/北师大版一年级起点三年级下/SearchWord}}\"}, \"北师大版一年级起点三年级下/20220119011922801710\": {\"title\": \"北师大版一年级起点三年级下/20220119011922801710\", \"tags\": \"[[Unit 12]] ?\", \"word\": \"train\", \"created\": \"20220119011922801710\", \"caption\": \"{{||$:/plugins/oflg/fishing-cannedfish/北师大版一年级起点三年级下/SearchWord}}\"}, \"北师大版一年级起点三年级下/20220119011922801714\": {\"title\": \"北师大版一年级起点三年级下/20220119011922801714\", \"tags\": \"[[Unit 12]] ?\", \"word\": \"window\", \"created\": \"20220119011922801714\", \"caption\": \"{{||$:/plugins/oflg/fishing-cannedfish/北师大版一年级起点三年级下/SearchWord}}\"}}}"}]