[{"author": "oflg", "core-version": ">=5.2.1", "dependents": "$:/plugins/oflg/fishing-cannedfish", "description": "记忆包", "list": "readme", "name": "北师大版高中英语选修模块7", "parent-plugin": "$:/plugins/oflg/fishing-cannedfish", "plugin-type": "plugin", "source": "https://github.com/oflg/fishing-cannedfish", "title": "$:/plugins/oflg/fishing-cannedfish/北师大版高中英语选修模块7", "version": "0.0.5", "type": "application/json", "text": "{\"tiddlers\": {\"$:/plugins/oflg/fishing-cannedfish/北师大版高中英语选修模块7/readme\": {\"title\": \"$:/plugins/oflg/fishing-cannedfish/北师大版高中英语选修模块7/readme\", \"text\": \"Installation and usage tutorial is available at [[Fishing Manual|https://oflg.github.io/fishing/]].\\n\\n可在 [[钓鱼手册|https://oflg.github.io/fishing/]] 查看安装使用教程。\"}, \"$:/plugins/oflg/fishing/fishingrod/[[$:/plugins/oflg/fishing-cannedfish/北师大版高中英语选修模块7]plugintiddlers[]tag[?]]\": {\"title\": \"$:/plugins/oflg/fishing/fishingrod/[[$:/plugins/oflg/fishing-cannedfish/北师大版高中英语选修模块7]plugintiddlers[]tag[?]]\", \"type\": \"application/json\", \"caption\": \"北师大版高中英语选修模块7\"}, \"$:/plugins/oflg/fishing-cannedfish/北师大版高中英语选修模块7/Question\": {\"title\": \"$:/plugins/oflg/fishing-cannedfish/北师大版高中英语选修模块7/Question\", \"tags\": \"$:/tags/QuestionTemplate\", \"word\": \"fishing\", \"text\": \"\\n<$reveal\\n    state=<<folded-state>>\\n    type=\\\"match\\\"\\n    text=\\\"hide\\\"\\n    animate=\\\"yes\\\"\\n>\\n    {{!!word}}\\n</$reveal>\\n\\n<$reveal\\n    state=<<folded-state>>\\n    type=\\\"nomatch\\\"\\n    text=\\\"hide\\\"\\n    animate=\\\"yes\\\"\\n>\\n    <span\\n        class=\\\"tc-fish-title\\\"\\n    >\\n        <main style=\\\"width:100%;overflow:hidden;\\\"> \\n            <iframe\\n                height=\\\"700px\\\"\\n                width=\\\"100%\\\"\\n                src={{{[{!!word}encodeuricomponent[]addprefix[https://quark.sm.cn/api/rest?method=quark_fanyi.dlpage&format=html&schema=v2&entry=top#en/zh/]]}}}\\n                frameborder=0\\n                seamless=\\\"seamless\\\"\\n                style=\\\"margin:-200px 0 -110px 0;\\\"\\n                marginheight=\\\"0\\\"\\n                marginwidth=\\\"0\\\"\\n            />\\n        </main>\\n    </span>\\n</$reveal>\\n\"}, \"北师大版高中英语选修模块7/20220226134401887371\": {\"title\": \"北师大版高中英语选修模块7/20220226134401887371\", \"tags\": \"[[Unit 19 Warm-up]] ?\", \"word\": \"mother tongue\", \"created\": \"20220226134401887371\", \"caption\": \"{{||$:/plugins/oflg/fishing-cannedfish/北师大版高中英语选修模块7/Question}}\"}, \"北师大版高中英语选修模块7/20220226134401887388\": {\"title\": \"北师大版高中英语选修模块7/20220226134401887388\", \"tags\": \"[[Unit 19 Warm-up]] ?\", \"word\": \"input\", \"created\": \"20220226134401887388\", \"caption\": \"{{||$:/plugins/oflg/fishing-cannedfish/北师大版高中英语选修模块7/Question}}\"}, \"北师大版高中英语选修模块7/20220226134401887393\": {\"title\": \"北师大版高中英语选修模块7/20220226134401887393\", \"tags\": \"[[Unit 19 Warm-up]] ?\", \"word\": \"output\", \"created\": \"20220226134401887393\", \"caption\": \"{{||$:/plugins/oflg/fishing-cannedfish/北师大版高中英语选修模块7/Question}}\"}, \"北师大版高中英语选修模块7/20220226134401887397\": {\"title\": \"北师大版高中英语选修模块7/20220226134401887397\", \"tags\": \"[[Unit 19 Warm-up]] ?\", \"word\": \"fluency\", \"created\": \"20220226134401887397\", \"caption\": \"{{||$:/plugins/oflg/fishing-cannedfish/北师大版高中英语选修模块7/Question}}\"}, \"北师大版高中英语选修模块7/20220226134401887400\": {\"title\": \"北师大版高中英语选修模块7/20220226134401887400\", \"tags\": \"[[Unit 19 Warm-up]] ?\", \"word\": \"accuracy\", \"created\": \"20220226134401887400\", \"caption\": \"{{||$:/plugins/oflg/fishing-cannedfish/北师大版高中英语选修模块7/Question}}\"}, \"北师大版高中英语选修模块7/20220226134401887403\": {\"title\": \"北师大版高中英语选修模块7/20220226134401887403\", \"tags\": \"[[Unit 19 Warm-up]] ?\", \"word\": \"punctuation\", \"created\": \"20220226134401887403\", \"caption\": \"{{||$:/plugins/oflg/fishing-cannedfish/北师大版高中英语选修模块7/Question}}\"}, \"北师大版高中英语选修模块7/20220226134401887406\": {\"title\": \"北师大版高中英语选修模块7/20220226134401887406\", \"tags\": \"[[Unit 19 Warm-up]] ?\", \"word\": \"royal\", \"created\": \"20220226134401887406\", \"caption\": \"{{||$:/plugins/oflg/fishing-cannedfish/北师大版高中英语选修模块7/Question}}\"}, \"北师大版高中英语选修模块7/20220226134401887410\": {\"title\": \"北师大版高中英语选修模块7/20220226134401887410\", \"tags\": \"[[Unit 19 Warm-up]] ?\", \"word\": \"nationwide\", \"created\": \"20220226134401887410\", \"caption\": \"{{||$:/plugins/oflg/fishing-cannedfish/北师大版高中英语选修模块7/Question}}\"}, \"北师大版高中英语选修模块7/20220226134401887414\": {\"title\": \"北师大版高中英语选修模块7/20220226134401887414\", \"tags\": \"[[Unit 19 Warm-up]] ?\", \"word\": \"thankful\", \"created\": \"20220226134401887414\", \"caption\": \"{{||$:/plugins/oflg/fishing-cannedfish/北师大版高中英语选修模块7/Question}}\"}, \"北师大版高中英语选修模块7/20220226134401887417\": {\"title\": \"北师大版高中英语选修模块7/20220226134401887417\", \"tags\": \"[[Unit 19 Warm-up]] ?\", \"word\": \"constitution\", \"created\": \"20220226134401887417\", \"caption\": \"{{||$:/plugins/oflg/fishing-cannedfish/北师大版高中英语选修模块7/Question}}\"}, \"北师大版高中英语选修模块7/20220226134401887420\": {\"title\": \"北师大版高中英语选修模块7/20220226134401887420\", \"tags\": \"[[Unit 19 Warm-up]] ?\", \"word\": \"liberty\", \"created\": \"20220226134401887420\", \"caption\": \"{{||$:/plugins/oflg/fishing-cannedfish/北师大版高中英语选修模块7/Question}}\"}, \"北师大版高中英语选修模块7/20220226134401887423\": {\"title\": \"北师大版高中英语选修模块7/20220226134401887423\", \"tags\": \"[[Unit 19 Warm-up]] ?\", \"word\": \"the Statue of Liberty\", \"created\": \"20220226134401887423\", \"caption\": \"{{||$:/plugins/oflg/fishing-cannedfish/北师大版高中英语选修模块7/Question}}\"}, \"北师大版高中英语选修模块7/20220226134401887426\": {\"title\": \"北师大版高中英语选修模块7/20220226134401887426\", \"tags\": \"[[Unit 19 Warm-up]] ?\", \"word\": \"jungle\", \"created\": \"20220226134401887426\", \"caption\": \"{{||$:/plugins/oflg/fishing-cannedfish/北师大版高中英语选修模块7/Question}}\"}, \"北师大版高中英语选修模块7/20220226134401887430\": {\"title\": \"北师大版高中英语选修模块7/20220226134401887430\", \"tags\": \"[[Unit 19 Warm-up]] ?\", \"word\": \"cafeteria\", \"created\": \"20220226134401887430\", \"caption\": \"{{||$:/plugins/oflg/fishing-cannedfish/北师大版高中英语选修模块7/Question}}\"}, \"北师大版高中英语选修模块7/20220226134401887433\": {\"title\": \"北师大版高中英语选修模块7/20220226134401887433\", \"tags\": \"[[Unit 19 Warm-up]] ?\", \"word\": \"fold\", \"created\": \"20220226134401887433\", \"caption\": \"{{||$:/plugins/oflg/fishing-cannedfish/北师大版高中英语选修模块7/Question}}\"}, \"北师大版高中英语选修模块7/20220226134401887437\": {\"title\": \"北师大版高中英语选修模块7/20220226134401887437\", \"tags\": \"[[Unit 19 Lesson 1]] ?\", \"word\": \"global\", \"created\": \"20220226134401887437\", \"caption\": \"{{||$:/plugins/oflg/fishing-cannedfish/北师大版高中英语选修模块7/Question}}\"}, \"北师大版高中英语选修模块7/20220226134401887440\": {\"title\": \"北师大版高中英语选修模块7/20220226134401887440\", \"tags\": \"[[Unit 19 Lesson 1]] ?\", \"word\": \"decade\", \"created\": \"20220226134401887440\", \"caption\": \"{{||$:/plugins/oflg/fishing-cannedfish/北师大版高中英语选修模块7/Question}}\"}, \"北师大版高中英语选修模块7/20220226134401887443\": {\"title\": \"北师大版高中英语选修模块7/20220226134401887443\", \"tags\": \"[[Unit 19 Lesson 1]] ?\", \"word\": \"trend\", \"created\": \"20220226134401887443\", \"caption\": \"{{||$:/plugins/oflg/fishing-cannedfish/北师大版高中英语选修模块7/Question}}\"}, \"北师大版高中英语选修模块7/20220226134401887446\": {\"title\": \"北师大版高中英语选修模块7/20220226134401887446\", \"tags\": \"[[Unit 19 Lesson 1]] ?\", \"word\": \"absence\", \"created\": \"20220226134401887446\", \"caption\": \"{{||$:/plugins/oflg/fishing-cannedfish/北师大版高中英语选修模块7/Question}}\"}, \"北师大版高中英语选修模块7/20220226134401887450\": {\"title\": \"北师大版高中英语选修模块7/20220226134401887450\", \"tags\": \"[[Unit 19 Lesson 1]] ?\", \"word\": \"theory\", \"created\": \"20220226134401887450\", \"caption\": \"{{||$:/plugins/oflg/fishing-cannedfish/北师大版高中英语选修模块7/Question}}\"}, \"北师大版高中英语选修模块7/20220226134401887454\": {\"title\": \"北师大版高中英语选修模块7/20220226134401887454\", \"tags\": \"[[Unit 19 Lesson 1]] ?\", \"word\": \"acquisition\", \"created\": \"20220226134401887454\", \"caption\": \"{{||$:/plugins/oflg/fishing-cannedfish/北师大版高中英语选修模块7/Question}}\"}, \"北师大版高中英语选修模块7/20220226134401887457\": {\"title\": \"北师大版高中英语选修模块7/20220226134401887457\", \"tags\": \"[[Unit 19 Lesson 1]] ?\", \"word\": \"attain\", \"created\": \"20220226134401887457\", \"caption\": \"{{||$:/plugins/oflg/fishing-cannedfish/北师大版高中英语选修模块7/Question}}\"}, \"北师大版高中英语选修模块7/20220226134401887460\": {\"title\": \"北师大版高中英语选修模块7/20220226134401887460\", \"tags\": \"[[Unit 19 Lesson 1]] ?\", \"word\": \"surround\", \"created\": \"20220226134401887460\", \"caption\": \"{{||$:/plugins/oflg/fishing-cannedfish/北师大版高中英语选修模块7/Question}}\"}, \"北师大版高中英语选修模块7/20220226134401887463\": {\"title\": \"北师大版高中英语选修模块7/20220226134401887463\", \"tags\": \"[[Unit 19 Lesson 1]] ?\", \"word\": \"curriculum\", \"created\": \"20220226134401887463\", \"caption\": \"{{||$:/plugins/oflg/fishing-cannedfish/北师大版高中英语选修模块7/Question}}\"}, \"北师大版高中英语选修模块7/20220226134401887466\": {\"title\": \"北师大版高中英语选修模块7/20220226134401887466\", \"tags\": \"[[Unit 19 Lesson 1]] ?\", \"word\": \"adequate\", \"created\": \"20220226134401887466\", \"caption\": \"{{||$:/plugins/oflg/fishing-cannedfish/北师大版高中英语选修模块7/Question}}\"}, \"北师大版高中英语选修模块7/20220226134401887469\": {\"title\": \"北师大版高中英语选修模块7/20220226134401887469\", \"tags\": \"[[Unit 19 Lesson 1]] ?\", \"word\": \"medium\", \"created\": \"20220226134401887469\", \"caption\": \"{{||$:/plugins/oflg/fishing-cannedfish/北师大版高中英语选修模块7/Question}}\"}, \"北师大版高中英语选修模块7/20220226134401887472\": {\"title\": \"北师大版高中英语选修模块7/20220226134401887472\", \"tags\": \"[[Unit 19 Lesson 1]] ?\", \"word\": \"ensure\", \"created\": \"20220226134401887472\", \"caption\": \"{{||$:/plugins/oflg/fishing-cannedfish/北师大版高中英语选修模块7/Question}}\"}, \"北师大版高中英语选修模块7/20220226134401887475\": {\"title\": \"北师大版高中英语选修模块7/20220226134401887475\", \"tags\": \"[[Unit 19 Lesson 1]] ?\", \"word\": \"accelerate\", \"created\": \"20220226134401887475\", \"caption\": \"{{||$:/plugins/oflg/fishing-cannedfish/北师大版高中英语选修模块7/Question}}\"}, \"北师大版高中英语选修模块7/20220226134401887478\": {\"title\": \"北师大版高中英语选修模块7/20220226134401887478\", \"tags\": \"[[Unit 19 Lesson 1]] ?\", \"word\": \"target\", \"created\": \"20220226134401887478\", \"caption\": \"{{||$:/plugins/oflg/fishing-cannedfish/北师大版高中英语选修模块7/Question}}\"}, \"北师大版高中英语选修模块7/20220226134401887481\": {\"title\": \"北师大版高中英语选修模块7/20220226134401887481\", \"tags\": \"[[Unit 19 Lesson 1]] ?\", \"word\": \"enlarge\", \"created\": \"20220226134401887481\", \"caption\": \"{{||$:/plugins/oflg/fishing-cannedfish/北师大版高中英语选修模块7/Question}}\"}, \"北师大版高中英语选修模块7/20220226134401887484\": {\"title\": \"北师大版高中英语选修模块7/20220226134401887484\", \"tags\": \"[[Unit 19 Lesson 1]] ?\", \"word\": \"guarantee\", \"created\": \"20220226134401887484\", \"caption\": \"{{||$:/plugins/oflg/fishing-cannedfish/北师大版高中英语选修模块7/Question}}\"}, \"北师大版高中英语选修模块7/20220226134401887487\": {\"title\": \"北师大版高中英语选修模块7/20220226134401887487\", \"tags\": \"[[Unit 19 Lesson 1]] ?\", \"word\": \"adjust\", \"created\": \"20220226134401887487\", \"caption\": \"{{||$:/plugins/oflg/fishing-cannedfish/北师大版高中英语选修模块7/Question}}\"}, \"北师大版高中英语选修模块7/20220226134401887491\": {\"title\": \"北师大版高中英语选修模块7/20220226134401887491\", \"tags\": \"[[Unit 19 Lesson 1]] ?\", \"word\": \"inform\", \"created\": \"20220226134401887491\", \"caption\": \"{{||$:/plugins/oflg/fishing-cannedfish/北师大版高中英语选修模块7/Question}}\"}, \"北师大版高中英语选修模块7/20220226134401887494\": {\"title\": \"北师大版高中英语选修模块7/20220226134401887494\", \"tags\": \"[[Unit 19 Lesson 1]] ?\", \"word\": \"dedication\", \"created\": \"20220226134401887494\", \"caption\": \"{{||$:/plugins/oflg/fishing-cannedfish/北师大版高中英语选修模块7/Question}}\"}, \"北师大版高中英语选修模块7/20220226134401887497\": {\"title\": \"北师大版高中英语选修模块7/20220226134401887497\", \"tags\": \"[[Unit 19 Lesson 1]] ?\", \"word\": \"dedicated\", \"created\": \"20220226134401887497\", \"caption\": \"{{||$:/plugins/oflg/fishing-cannedfish/北师大版高中英语选修模块7/Question}}\"}, \"北师大版高中英语选修模块7/20220226134401887500\": {\"title\": \"北师大版高中英语选修模块7/20220226134401887500\", \"tags\": \"[[Unit 19 Lesson 1]] ?\", \"word\": \"manual\", \"created\": \"20220226134401887500\", \"caption\": \"{{||$:/plugins/oflg/fishing-cannedfish/北师大版高中英语选修模块7/Question}}\"}, \"北师大版高中英语选修模块7/20220226134401887503\": {\"title\": \"北师大版高中英语选修模块7/20220226134401887503\", \"tags\": \"[[Unit 19 Lesson 1]] ?\", \"word\": \"theft\", \"created\": \"20220226134401887503\", \"caption\": \"{{||$:/plugins/oflg/fishing-cannedfish/北师大版高中英语选修模块7/Question}}\"}, \"北师大版高中英语选修模块7/20220226134401887506\": {\"title\": \"北师大版高中英语选修模块7/20220226134401887506\", \"tags\": \"[[Unit 19 Lesson 1]] ?\", \"word\": \"announcement\", \"created\": \"20220226134401887506\", \"caption\": \"{{||$:/plugins/oflg/fishing-cannedfish/北师大版高中英语选修模块7/Question}}\"}, \"北师大版高中英语选修模块7/20220226134401887510\": {\"title\": \"北师大版高中英语选修模块7/20220226134401887510\", \"tags\": \"[[Unit 19 Lesson 2]] ?\", \"word\": \"mate\", \"created\": \"20220226134401887510\", \"caption\": \"{{||$:/plugins/oflg/fishing-cannedfish/北师大版高中英语选修模块7/Question}}\"}, \"北师大版高中英语选修模块7/20220226134401887513\": {\"title\": \"北师大版高中英语选修模块7/20220226134401887513\", \"tags\": \"[[Unit 19 Lesson 2]] ?\", \"word\": \"cream\", \"created\": \"20220226134401887513\", \"caption\": \"{{||$:/plugins/oflg/fishing-cannedfish/北师大版高中英语选修模块7/Question}}\"}, \"北师大版高中英语选修模块7/20220226134401887517\": {\"title\": \"北师大版高中英语选修模块7/20220226134401887517\", \"tags\": \"[[Unit 19 Lesson 2]] ?\", \"word\": \"razor\", \"created\": \"20220226134401887517\", \"caption\": \"{{||$:/plugins/oflg/fishing-cannedfish/北师大版高中英语选修模块7/Question}}\"}, \"北师大版高中英语选修模块7/20220226134401887520\": {\"title\": \"北师大版高中英语选修模块7/20220226134401887520\", \"tags\": \"[[Unit 19 Lesson 2]] ?\", \"word\": \"catch on\", \"created\": \"20220226134401887520\", \"caption\": \"{{||$:/plugins/oflg/fishing-cannedfish/北师大版高中英语选修模块7/Question}}\"}, \"北师大版高中英语选修模块7/20220226134401887523\": {\"title\": \"北师大版高中英语选修模块7/20220226134401887523\", \"tags\": \"[[Unit 19 Lesson 2]] ?\", \"word\": \"for ages\", \"created\": \"20220226134401887523\", \"caption\": \"{{||$:/plugins/oflg/fishing-cannedfish/北师大版高中英语选修模块7/Question}}\"}, \"北师大版高中英语选修模块7/20220226134401887526\": {\"title\": \"北师大版高中英语选修模块7/20220226134401887526\", \"tags\": \"[[Unit 19 Lesson 2]] ?\", \"word\": \"brochure\", \"created\": \"20220226134401887526\", \"caption\": \"{{||$:/plugins/oflg/fishing-cannedfish/北师大版高中英语选修模块7/Question}}\"}, \"北师大版高中英语选修模块7/20220226134401887529\": {\"title\": \"北师大版高中英语选修模块7/20220226134401887529\", \"tags\": \"[[Unit 19 Lesson 2]] ?\", \"word\": \"cab\", \"created\": \"20220226134401887529\", \"caption\": \"{{||$:/plugins/oflg/fishing-cannedfish/北师大版高中英语选修模块7/Question}}\"}, \"北师大版高中英语选修模块7/20220226134401887532\": {\"title\": \"北师大版高中英语选修模块7/20220226134401887532\", \"tags\": \"[[Unit 19 Lesson 2]] ?\", \"word\": \"relative\", \"created\": \"20220226134401887532\", \"caption\": \"{{||$:/plugins/oflg/fishing-cannedfish/北师大版高中英语选修模块7/Question}}\"}, \"北师大版高中英语选修模块7/20220226134401887535\": {\"title\": \"北师大版高中英语选修模块7/20220226134401887535\", \"tags\": \"[[Unit 19 Lesson 3]] ?\", \"word\": \"pat\", \"created\": \"20220226134401887535\", \"caption\": \"{{||$:/plugins/oflg/fishing-cannedfish/北师大版高中英语选修模块7/Question}}\"}, \"北师大版高中英语选修模块7/20220226134401887538\": {\"title\": \"北师大版高中英语选修模块7/20220226134401887538\", \"tags\": \"[[Unit 19 Lesson 3]] ?\", \"word\": \"congratulate\", \"created\": \"20220226134401887538\", \"caption\": \"{{||$:/plugins/oflg/fishing-cannedfish/北师大版高中英语选修模块7/Question}}\"}, \"北师大版高中英语选修模块7/20220226134401887541\": {\"title\": \"北师大版高中英语选修模块7/20220226134401887541\", \"tags\": \"[[Unit 19 Lesson 3]] ?\", \"word\": \"explicit\", \"created\": \"20220226134401887541\", \"caption\": \"{{||$:/plugins/oflg/fishing-cannedfish/北师大版高中英语选修模块7/Question}}\"}, \"北师大版高中英语选修模块7/20220226134401887544\": {\"title\": \"北师大版高中英语选修模块7/20220226134401887544\", \"tags\": \"[[Unit 19 Lesson 3]] ?\", \"word\": \"eyebrow\", \"created\": \"20220226134401887544\", \"caption\": \"{{||$:/plugins/oflg/fishing-cannedfish/北师大版高中英语选修模块7/Question}}\"}, \"北师大版高中英语选修模块7/20220226134401887547\": {\"title\": \"北师大版高中英语选修模块7/20220226134401887547\", \"tags\": \"[[Unit 19 Lesson 3]] ?\", \"word\": \"on purpose\", \"created\": \"20220226134401887547\", \"caption\": \"{{||$:/plugins/oflg/fishing-cannedfish/北师大版高中英语选修模块7/Question}}\"}, \"北师大版高中英语选修模块7/20220226134401887550\": {\"title\": \"北师大版高中英语选修模块7/20220226134401887550\", \"tags\": \"[[Unit 19 Lesson 3]] ?\", \"word\": \"upwards\", \"created\": \"20220226134401887550\", \"caption\": \"{{||$:/plugins/oflg/fishing-cannedfish/北师大版高中英语选修模块7/Question}}\"}, \"北师大版高中英语选修模块7/20220226134401887553\": {\"title\": \"北师大版高中英语选修模块7/20220226134401887553\", \"tags\": \"[[Unit 19 Lesson 3]] ?\", \"word\": \"upper\", \"created\": \"20220226134401887553\", \"caption\": \"{{||$:/plugins/oflg/fishing-cannedfish/北师大版高中英语选修模块7/Question}}\"}, \"北师大版高中英语选修模块7/20220226134401887556\": {\"title\": \"北师大版高中英语选修模块7/20220226134401887556\", \"tags\": \"[[Unit 19 Lesson 3]] ?\", \"word\": \"unconscious\", \"created\": \"20220226134401887556\", \"caption\": \"{{||$:/plugins/oflg/fishing-cannedfish/北师大版高中英语选修模块7/Question}}\"}, \"北师大版高中英语选修模块7/20220226134401887559\": {\"title\": \"北师大版高中英语选修模块7/20220226134401887559\", \"tags\": \"[[Unit 19 Lesson 3]] ?\", \"word\": \"rigid\", \"created\": \"20220226134401887559\", \"caption\": \"{{||$:/plugins/oflg/fishing-cannedfish/北师大版高中英语选修模块7/Question}}\"}, \"北师大版高中英语选修模块7/20220226134401887562\": {\"title\": \"北师大版高中英语选修模块7/20220226134401887562\", \"tags\": \"[[Unit 19 Lesson 3]] ?\", \"word\": \"tight\", \"created\": \"20220226134401887562\", \"caption\": \"{{||$:/plugins/oflg/fishing-cannedfish/北师大版高中英语选修模块7/Question}}\"}, \"北师大版高中英语选修模块7/20220226134401887565\": {\"title\": \"北师大版高中英语选修模块7/20220226134401887565\", \"tags\": \"[[Unit 19 Lesson 3]] ?\", \"word\": \"resemble\", \"created\": \"20220226134401887565\", \"caption\": \"{{||$:/plugins/oflg/fishing-cannedfish/北师大版高中英语选修模块7/Question}}\"}, \"北师大版高中英语选修模块7/20220226134401887567\": {\"title\": \"北师大版高中英语选修模块7/20220226134401887567\", \"tags\": \"[[Unit 19 Lesson 3]] ?\", \"word\": \"transparent\", \"created\": \"20220226134401887567\", \"caption\": \"{{||$:/plugins/oflg/fishing-cannedfish/北师大版高中英语选修模块7/Question}}\"}, \"北师大版高中英语选修模块7/20220226134401887570\": {\"title\": \"北师大版高中英语选修模块7/20220226134401887570\", \"tags\": \"[[Unit 19 Lesson 3]] ?\", \"word\": \"unrest\", \"created\": \"20220226134401887570\", \"caption\": \"{{||$:/plugins/oflg/fishing-cannedfish/北师大版高中英语选修模块7/Question}}\"}, \"北师大版高中英语选修模块7/20220226134401887574\": {\"title\": \"北师大版高中英语选修模块7/20220226134401887574\", \"tags\": \"[[Unit 19 Lesson 3]] ?\", \"word\": \"merely\", \"created\": \"20220226134401887574\", \"caption\": \"{{||$:/plugins/oflg/fishing-cannedfish/北师大版高中英语选修模块7/Question}}\"}, \"北师大版高中英语选修模块7/20220226134401887577\": {\"title\": \"北师大版高中英语选修模块7/20220226134401887577\", \"tags\": \"[[Unit 19 Lesson 3]] ?\", \"word\": \"purchase\", \"created\": \"20220226134401887577\", \"caption\": \"{{||$:/plugins/oflg/fishing-cannedfish/北师大版高中英语选修模块7/Question}}\"}, \"北师大版高中英语选修模块7/20220226134401887580\": {\"title\": \"北师大版高中英语选修模块7/20220226134401887580\", \"tags\": \"[[Unit 19 Lesson 3]] ?\", \"word\": \"on the other hand\", \"created\": \"20220226134401887580\", \"caption\": \"{{||$:/plugins/oflg/fishing-cannedfish/北师大版高中英语选修模块7/Question}}\"}, \"北师大版高中英语选修模块7/20220226134401887583\": {\"title\": \"北师大版高中英语选修模块7/20220226134401887583\", \"tags\": \"[[Unit 19 Lesson 3]] ?\", \"word\": \"negotiate\", \"created\": \"20220226134401887583\", \"caption\": \"{{||$:/plugins/oflg/fishing-cannedfish/北师大版高中英语选修模块7/Question}}\"}, \"北师大版高中英语选修模块7/20220226134401887586\": {\"title\": \"北师大版高中英语选修模块7/20220226134401887586\", \"tags\": \"[[Unit 19 Lesson 3]] ?\", \"word\": \"outline\", \"created\": \"20220226134401887586\", \"caption\": \"{{||$:/plugins/oflg/fishing-cannedfish/北师大版高中英语选修模块7/Question}}\"}, \"北师大版高中英语选修模块7/20220226134401887589\": {\"title\": \"北师大版高中英语选修模块7/20220226134401887589\", \"tags\": \"[[Unit 19 Lesson 3]] ?\", \"word\": \"ambiguous\", \"created\": \"20220226134401887589\", \"caption\": \"{{||$:/plugins/oflg/fishing-cannedfish/北师大版高中英语选修模块7/Question}}\"}, \"北师大版高中英语选修模块7/20220226134401887592\": {\"title\": \"北师大版高中英语选修模块7/20220226134401887592\", \"tags\": \"[[Unit 19 Lesson 3]] ?\", \"word\": \"offence\", \"created\": \"20220226134401887592\", \"caption\": \"{{||$:/plugins/oflg/fishing-cannedfish/北师大版高中英语选修模块7/Question}}\"}, \"北师大版高中英语选修模块7/20220226134401887595\": {\"title\": \"北师大版高中英语选修模块7/20220226134401887595\", \"tags\": \"[[Unit 19 Lesson 3]] ?\", \"word\": \"approval\", \"created\": \"20220226134401887595\", \"caption\": \"{{||$:/plugins/oflg/fishing-cannedfish/北师大版高中英语选修模块7/Question}}\"}, \"北师大版高中英语选修模块7/20220226134401887598\": {\"title\": \"北师大版高中英语选修模块7/20220226134401887598\", \"tags\": \"[[Unit 19 Lesson 3]] ?\", \"word\": \"bent\", \"created\": \"20220226134401887598\", \"caption\": \"{{||$:/plugins/oflg/fishing-cannedfish/北师大版高中英语选修模块7/Question}}\"}, \"北师大版高中英语选修模块7/20220226134401887602\": {\"title\": \"北师大版高中英语选修模块7/20220226134401887602\", \"tags\": \"[[Unit 19 Communication Workshop]] ?\", \"word\": \"applicant\", \"created\": \"20220226134401887602\", \"caption\": \"{{||$:/plugins/oflg/fishing-cannedfish/北师大版高中英语选修模块7/Question}}\"}, \"北师大版高中英语选修模块7/20220226134401887605\": {\"title\": \"北师大版高中英语选修模块7/20220226134401887605\", \"tags\": \"[[Unit 19 Communication Workshop]] ?\", \"word\": \"certificate\", \"created\": \"20220226134401887605\", \"caption\": \"{{||$:/plugins/oflg/fishing-cannedfish/北师大版高中英语选修模块7/Question}}\"}, \"北师大版高中英语选修模块7/20220226134401887608\": {\"title\": \"北师大版高中英语选修模块7/20220226134401887608\", \"tags\": \"[[Unit 19 Communication Workshop]] ?\", \"word\": \"registration\", \"created\": \"20220226134401887608\", \"caption\": \"{{||$:/plugins/oflg/fishing-cannedfish/北师大版高中英语选修模块7/Question}}\"}, \"北师大版高中英语选修模块7/20220226134401887611\": {\"title\": \"北师大版高中英语选修模块7/20220226134401887611\", \"tags\": \"[[Unit 19 Communication Workshop]] ?\", \"word\": \"competence\", \"created\": \"20220226134401887611\", \"caption\": \"{{||$:/plugins/oflg/fishing-cannedfish/北师大版高中英语选修模块7/Question}}\"}, \"北师大版高中英语选修模块7/20220226134401887614\": {\"title\": \"北师大版高中英语选修模块7/20220226134401887614\", \"tags\": \"[[Unit 19 Communication Workshop]] ?\", \"word\": \"diploma\", \"created\": \"20220226134401887614\", \"caption\": \"{{||$:/plugins/oflg/fishing-cannedfish/北师大版高中英语选修模块7/Question}}\"}, \"北师大版高中英语选修模块7/20220226134401887617\": {\"title\": \"北师大版高中英语选修模块7/20220226134401887617\", \"tags\": \"[[Unit 19 Communication Workshop]] ?\", \"word\": \"marketing\", \"created\": \"20220226134401887617\", \"caption\": \"{{||$:/plugins/oflg/fishing-cannedfish/北师大版高中英语选修模块7/Question}}\"}, \"北师大版高中英语选修模块7/20220226134401887620\": {\"title\": \"北师大版高中英语选修模块7/20220226134401887620\", \"tags\": \"[[Unit 19 Communication Workshop]] ?\", \"word\": \"overview\", \"created\": \"20220226134401887620\", \"caption\": \"{{||$:/plugins/oflg/fishing-cannedfish/北师大版高中英语选修模块7/Question}}\"}, \"北师大版高中英语选修模块7/20220226134401887623\": {\"title\": \"北师大版高中英语选修模块7/20220226134401887623\", \"tags\": \"[[Unit 19 Communication Workshop]] ?\", \"word\": \"provided\", \"created\": \"20220226134401887623\", \"caption\": \"{{||$:/plugins/oflg/fishing-cannedfish/北师大版高中英语选修模块7/Question}}\"}, \"北师大版高中英语选修模块7/20220226134401887626\": {\"title\": \"北师大版高中英语选修模块7/20220226134401887626\", \"tags\": \"[[Unit 19 Communication Workshop]] ?\", \"word\": \"register\", \"created\": \"20220226134401887626\", \"caption\": \"{{||$:/plugins/oflg/fishing-cannedfish/北师大版高中英语选修模块7/Question}}\"}, \"北师大版高中英语选修模块7/20220226134401887629\": {\"title\": \"北师大版高中英语选修模块7/20220226134401887629\", \"tags\": \"[[Unit 19 Communication Workshop]] ?\", \"word\": \"candidate\", \"created\": \"20220226134401887629\", \"caption\": \"{{||$:/plugins/oflg/fishing-cannedfish/北师大版高中英语选修模块7/Question}}\"}, \"北师大版高中英语选修模块7/20220226134401887633\": {\"title\": \"北师大版高中英语选修模块7/20220226134401887633\", \"tags\": \"[[Unit 19 Communication Workshop]] ?\", \"word\": \"cheers\", \"created\": \"20220226134401887633\", \"caption\": \"{{||$:/plugins/oflg/fishing-cannedfish/北师大版高中英语选修模块7/Question}}\"}, \"北师大版高中英语选修模块7/20220226134401887636\": {\"title\": \"北师大版高中英语选修模块7/20220226134401887636\", \"tags\": \"[[Unit 19 Communication Workshop]] ?\", \"word\": \"diagram\", \"created\": \"20220226134401887636\", \"caption\": \"{{||$:/plugins/oflg/fishing-cannedfish/北师大版高中英语选修模块7/Question}}\"}, \"北师大版高中英语选修模块7/20220226134401887639\": {\"title\": \"北师大版高中英语选修模块7/20220226134401887639\", \"tags\": \"[[Unit 19 Communication Workshop]] ?\", \"word\": \"caption\", \"created\": \"20220226134401887639\", \"caption\": \"{{||$:/plugins/oflg/fishing-cannedfish/北师大版高中英语选修模块7/Question}}\"}, \"北师大版高中英语选修模块7/20220226134401887642\": {\"title\": \"北师大版高中英语选修模块7/20220226134401887642\", \"tags\": \"[[Unit 19 Communication Workshop]] ?\", \"word\": \"booth\", \"created\": \"20220226134401887642\", \"caption\": \"{{||$:/plugins/oflg/fishing-cannedfish/北师大版高中英语选修模块7/Question}}\"}, \"北师大版高中英语选修模块7/20220226134401887645\": {\"title\": \"北师大版高中英语选修模块7/20220226134401887645\", \"tags\": \"[[Unit 19 Communication Workshop]] ?\", \"word\": \"barbershop\", \"created\": \"20220226134401887645\", \"caption\": \"{{||$:/plugins/oflg/fishing-cannedfish/北师大版高中英语选修模块7/Question}}\"}, \"北师大版高中英语选修模块7/20220226134401887649\": {\"title\": \"北师大版高中英语选修模块7/20220226134401887649\", \"tags\": \"[[Unit 19 Communication Workshop]] ?\", \"word\": \"globe\", \"created\": \"20220226134401887649\", \"caption\": \"{{||$:/plugins/oflg/fishing-cannedfish/北师大版高中英语选修模块7/Question}}\"}, \"北师大版高中英语选修模块7/20220226134401887652\": {\"title\": \"北师大版高中英语选修模块7/20220226134401887652\", \"tags\": \"[[Unit 19 Communication Workshop]] ?\", \"word\": \"barber\", \"created\": \"20220226134401887652\", \"caption\": \"{{||$:/plugins/oflg/fishing-cannedfish/北师大版高中英语选修模块7/Question}}\"}, \"北师大版高中英语选修模块7/20220226134401887655\": {\"title\": \"北师大版高中英语选修模块7/20220226134401887655\", \"tags\": \"[[Unit 19 Communication Workshop]] ?\", \"word\": \"fasten\", \"created\": \"20220226134401887655\", \"caption\": \"{{||$:/plugins/oflg/fishing-cannedfish/北师大版高中英语选修模块7/Question}}\"}, \"北师大版高中英语选修模块7/20220226134401887658\": {\"title\": \"北师大版高中英语选修模块7/20220226134401887658\", \"tags\": \"[[Unit 19 Communication Workshop]] ?\", \"word\": \"stewardess\", \"created\": \"20220226134401887658\", \"caption\": \"{{||$:/plugins/oflg/fishing-cannedfish/北师大版高中英语选修模块7/Question}}\"}, \"北师大版高中英语选修模块7/20220226134401887661\": {\"title\": \"北师大版高中英语选修模块7/20220226134401887661\", \"tags\": \"[[Unit 19 Communication Workshop]] ?\", \"word\": \"steward\", \"created\": \"20220226134401887661\", \"caption\": \"{{||$:/plugins/oflg/fishing-cannedfish/北师大版高中英语选修模块7/Question}}\"}, \"北师大版高中英语选修模块7/20220226134401887664\": {\"title\": \"北师大版高中英语选修模块7/20220226134401887664\", \"tags\": \"[[Unit 19 Communication Workshop]] ?\", \"word\": \"regulation\", \"created\": \"20220226134401887664\", \"caption\": \"{{||$:/plugins/oflg/fishing-cannedfish/北师大版高中英语选修模块7/Question}}\"}, \"北师大版高中英语选修模块7/20220226134401887667\": {\"title\": \"北师大版高中英语选修模块7/20220226134401887667\", \"tags\": \"[[Unit 19 Communication Workshop]] ?\", \"word\": \"bingo\", \"created\": \"20220226134401887667\", \"caption\": \"{{||$:/plugins/oflg/fishing-cannedfish/北师大版高中英语选修模块7/Question}}\"}, \"北师大版高中英语选修模块7/20220226134401887670\": {\"title\": \"北师大版高中英语选修模块7/20220226134401887670\", \"tags\": \"[[Unit 19 Communication Workshop]] ?\", \"word\": \"haircut\", \"created\": \"20220226134401887670\", \"caption\": \"{{||$:/plugins/oflg/fishing-cannedfish/北师大版高中英语选修模块7/Question}}\"}, \"北师大版高中英语选修模块7/20220226134401887687\": {\"title\": \"北师大版高中英语选修模块7/20220226134401887687\", \"tags\": \"[[Unit 19 Communication Workshop]] ?\", \"word\": \"amateur\", \"created\": \"20220226134401887687\", \"caption\": \"{{||$:/plugins/oflg/fishing-cannedfish/北师大版高中英语选修模块7/Question}}\"}, \"北师大版高中英语选修模块7/20220226134401887696\": {\"title\": \"北师大版高中英语选修模块7/20220226134401887696\", \"tags\": \"[[Unit 19 Communication Workshop]] ?\", \"word\": \"sincerely\", \"created\": \"20220226134401887696\", \"caption\": \"{{||$:/plugins/oflg/fishing-cannedfish/北师大版高中英语选修模块7/Question}}\"}, \"北师大版高中英语选修模块7/20220226134401887700\": {\"title\": \"北师大版高中英语选修模块7/20220226134401887700\", \"tags\": \"[[Unit 19 Communication Workshop]] ?\", \"word\": \"embarrass\", \"created\": \"20220226134401887700\", \"caption\": \"{{||$:/plugins/oflg/fishing-cannedfish/北师大版高中英语选修模块7/Question}}\"}, \"北师大版高中英语选修模块7/20220226134401887704\": {\"title\": \"北师大版高中英语选修模块7/20220226134401887704\", \"tags\": \"[[Unit 19 Communication Workshop]] ?\", \"word\": \"punctual\", \"created\": \"20220226134401887704\", \"caption\": \"{{||$:/plugins/oflg/fishing-cannedfish/北师大版高中英语选修模块7/Question}}\"}, \"北师大版高中英语选修模块7/20220226134401887707\": {\"title\": \"北师大版高中英语选修模块7/20220226134401887707\", \"tags\": \"[[Unit 19 Communication Workshop]] ?\", \"word\": \"directory\", \"created\": \"20220226134401887707\", \"caption\": \"{{||$:/plugins/oflg/fishing-cannedfish/北师大版高中英语选修模块7/Question}}\"}, \"北师大版高中英语选修模块7/20220226134401887711\": {\"title\": \"北师大版高中英语选修模块7/20220226134401887711\", \"tags\": \"[[Unit 19 Communication Workshop]] ?\", \"word\": \"personnel\", \"created\": \"20220226134401887711\", \"caption\": \"{{||$:/plugins/oflg/fishing-cannedfish/北师大版高中英语选修模块7/Question}}\"}, \"北师大版高中英语选修模块7/20220226134401887714\": {\"title\": \"北师大版高中英语选修模块7/20220226134401887714\", \"tags\": \"[[Unit 19 Communication Workshop]] ?\", \"word\": \"bet\", \"created\": \"20220226134401887714\", \"caption\": \"{{||$:/plugins/oflg/fishing-cannedfish/北师大版高中英语选修模块7/Question}}\"}, \"北师大版高中英语选修模块7/20220226134401887718\": {\"title\": \"北师大版高中英语选修模块7/20220226134401887718\", \"tags\": \"[[Unit 19 Communication Workshop]] ?\", \"word\": \"I bet\", \"created\": \"20220226134401887718\", \"caption\": \"{{||$:/plugins/oflg/fishing-cannedfish/北师大版高中英语选修模块7/Question}}\"}, \"北师大版高中英语选修模块7/20220226134401887721\": {\"title\": \"北师大版高中英语选修模块7/20220226134401887721\", \"tags\": \"[[Unit 19 Communication Workshop]] ?\", \"word\": \"academy\", \"created\": \"20220226134401887721\", \"caption\": \"{{||$:/plugins/oflg/fishing-cannedfish/北师大版高中英语选修模块7/Question}}\"}, \"北师大版高中英语选修模块7/20220226134401887724\": {\"title\": \"北师大版高中英语选修模块7/20220226134401887724\", \"tags\": \"[[Unit 19 Communication Workshop]] ?\", \"word\": \"Academy of Arts\", \"created\": \"20220226134401887724\", \"caption\": \"{{||$:/plugins/oflg/fishing-cannedfish/北师大版高中英语选修模块7/Question}}\"}, \"北师大版高中英语选修模块7/20220226134401887729\": {\"title\": \"北师大版高中英语选修模块7/20220226134401887729\", \"tags\": \"[[Unit 20 Warm-up]] ?\", \"word\": \"algebra\", \"created\": \"20220226134401887729\", \"caption\": \"{{||$:/plugins/oflg/fishing-cannedfish/北师大版高中英语选修模块7/Question}}\"}, \"北师大版高中英语选修模块7/20220226134401887732\": {\"title\": \"北师大版高中英语选修模块7/20220226134401887732\", \"tags\": \"[[Unit 20 Warm-up]] ?\", \"word\": \"geometry\", \"created\": \"20220226134401887732\", \"caption\": \"{{||$:/plugins/oflg/fishing-cannedfish/北师大版高中英语选修模块7/Question}}\"}, \"北师大版高中英语选修模块7/20220226134401887735\": {\"title\": \"北师大版高中英语选修模块7/20220226134401887735\", \"tags\": \"[[Unit 20 Warm-up]] ?\", \"word\": \"bacteria\", \"created\": \"20220226134401887735\", \"caption\": \"{{||$:/plugins/oflg/fishing-cannedfish/北师大版高中英语选修模块7/Question}}\"}, \"北师大版高中英语选修模块7/20220226134401887739\": {\"title\": \"北师大版高中英语选修模块7/20220226134401887739\", \"tags\": \"[[Unit 20 Warm-up]] ?\", \"word\": \"software\", \"created\": \"20220226134401887739\", \"caption\": \"{{||$:/plugins/oflg/fishing-cannedfish/北师大版高中英语选修模块7/Question}}\"}, \"北师大版高中英语选修模块7/20220226134401887742\": {\"title\": \"北师大版高中英语选修模块7/20220226134401887742\", \"tags\": \"[[Unit 20 Warm-up]] ?\", \"word\": \"mass\", \"created\": \"20220226134401887742\", \"caption\": \"{{||$:/plugins/oflg/fishing-cannedfish/北师大版高中英语选修模块7/Question}}\"}, \"北师大版高中英语选修模块7/20220226134401887746\": {\"title\": \"北师大版高中英语选修模块7/20220226134401887746\", \"tags\": \"[[Unit 20 Warm-up]] ?\", \"word\": \"radiation\", \"created\": \"20220226134401887746\", \"caption\": \"{{||$:/plugins/oflg/fishing-cannedfish/北师大版高中英语选修模块7/Question}}\"}, \"北师大版高中英语选修模块7/20220226134401887749\": {\"title\": \"北师大版高中英语选修模块7/20220226134401887749\", \"tags\": \"[[Unit 20 Warm-up]] ?\", \"word\": \"radium\", \"created\": \"20220226134401887749\", \"caption\": \"{{||$:/plugins/oflg/fishing-cannedfish/北师大版高中英语选修模块7/Question}}\"}, \"北师大版高中英语选修模块7/20220226134401887766\": {\"title\": \"北师大版高中英语选修模块7/20220226134401887766\", \"tags\": \"[[Unit 20 Warm-up]] ?\", \"word\": \"radioactive\", \"created\": \"20220226134401887766\", \"caption\": \"{{||$:/plugins/oflg/fishing-cannedfish/北师大版高中英语选修模块7/Question}}\"}, \"北师大版高中英语选修模块7/20220226134401887770\": {\"title\": \"北师大版高中英语选修模块7/20220226134401887770\", \"tags\": \"[[Unit 20 Warm-up]] ?\", \"word\": \"shuttle\", \"created\": \"20220226134401887770\", \"caption\": \"{{||$:/plugins/oflg/fishing-cannedfish/北师大版高中英语选修模块7/Question}}\"}, \"北师大版高中英语选修模块7/20220226134401887774\": {\"title\": \"北师大版高中英语选修模块7/20220226134401887774\", \"tags\": \"[[Unit 20 Warm-up]] ?\", \"word\": \"crew\", \"created\": \"20220226134401887774\", \"caption\": \"{{||$:/plugins/oflg/fishing-cannedfish/北师大版高中英语选修模块7/Question}}\"}, \"北师大版高中英语选修模块7/20220226134401887777\": {\"title\": \"北师大版高中英语选修模块7/20220226134401887777\", \"tags\": \"[[Unit 20 Warm-up]] ?\", \"word\": \"assist\", \"created\": \"20220226134401887777\", \"caption\": \"{{||$:/plugins/oflg/fishing-cannedfish/北师大版高中英语选修模块7/Question}}\"}, \"北师大版高中英语选修模块7/20220226134401887780\": {\"title\": \"北师大版高中英语选修模块7/20220226134401887780\", \"tags\": \"[[Unit 20 Warm-up]] ?\", \"word\": \"emotional\", \"created\": \"20220226134401887780\", \"caption\": \"{{||$:/plugins/oflg/fishing-cannedfish/北师大版高中英语选修模块7/Question}}\"}, \"北师大版高中英语选修模块7/20220226134401887784\": {\"title\": \"北师大版高中英语选修模块7/20220226134401887784\", \"tags\": \"[[Unit 20 Warm-up]] ?\", \"word\": \"technical\", \"created\": \"20220226134401887784\", \"caption\": \"{{||$:/plugins/oflg/fishing-cannedfish/北师大版高中英语选修模块7/Question}}\"}, \"北师大版高中英语选修模块7/20220226134401887787\": {\"title\": \"北师大版高中英语选修模块7/20220226134401887787\", \"tags\": \"[[Unit 20 Warm-up]] ?\", \"word\": \"journal\", \"created\": \"20220226134401887787\", \"caption\": \"{{||$:/plugins/oflg/fishing-cannedfish/北师大版高中英语选修模块7/Question}}\"}, \"北师大版高中英语选修模块7/20220226134401887791\": {\"title\": \"北师大版高中英语选修模块7/20220226134401887791\", \"tags\": \"[[Unit 20 Warm-up]] ?\", \"word\": \"issue\", \"created\": \"20220226134401887791\", \"caption\": \"{{||$:/plugins/oflg/fishing-cannedfish/北师大版高中英语选修模块7/Question}}\"}, \"北师大版高中英语选修模块7/20220226134401887794\": {\"title\": \"北师大版高中英语选修模块7/20220226134401887794\", \"tags\": \"[[Unit 20 Warm-up]] ?\", \"word\": \"recreation\", \"created\": \"20220226134401887794\", \"caption\": \"{{||$:/plugins/oflg/fishing-cannedfish/北师大版高中英语选修模块7/Question}}\"}, \"北师大版高中英语选修模块7/20220226134401887798\": {\"title\": \"北师大版高中英语选修模块7/20220226134401887798\", \"tags\": \"[[Unit 20 Lesson 1]] ?\", \"word\": \"futurology\", \"created\": \"20220226134401887798\", \"caption\": \"{{||$:/plugins/oflg/fishing-cannedfish/北师大版高中英语选修模块7/Question}}\"}, \"北师大版高中英语选修模块7/20220226134401887801\": {\"title\": \"北师大版高中英语选修模块7/20220226134401887801\", \"tags\": \"[[Unit 20 Lesson 1]] ?\", \"word\": \"latter\", \"created\": \"20220226134401887801\", \"caption\": \"{{||$:/plugins/oflg/fishing-cannedfish/北师大版高中英语选修模块7/Question}}\"}, \"北师大版高中英语选修模块7/20220226134401887804\": {\"title\": \"北师大版高中英语选修模块7/20220226134401887804\", \"tags\": \"[[Unit 20 Lesson 1]] ?\", \"word\": \"futurologist\", \"created\": \"20220226134401887804\", \"caption\": \"{{||$:/plugins/oflg/fishing-cannedfish/北师大版高中英语选修模块7/Question}}\"}, \"北师大版高中英语选修模块7/20220226134401887808\": {\"title\": \"北师大版高中英语选修模块7/20220226134401887808\", \"tags\": \"[[Unit 20 Lesson 1]] ?\", \"word\": \"seminar\", \"created\": \"20220226134401887808\", \"caption\": \"{{||$:/plugins/oflg/fishing-cannedfish/北师大版高中英语选修模块7/Question}}\"}, \"北师大版高中英语选修模块7/20220226134401887811\": {\"title\": \"北师大版高中英语选修模块7/20220226134401887811\", \"tags\": \"[[Unit 20 Lesson 1]] ?\", \"word\": \"enterprise\", \"created\": \"20220226134401887811\", \"caption\": \"{{||$:/plugins/oflg/fishing-cannedfish/北师大版高中英语选修模块7/Question}}\"}, \"北师大版高中英语选修模块7/20220226134401887814\": {\"title\": \"北师大版高中英语选修模块7/20220226134401887814\", \"tags\": \"[[Unit 20 Lesson 1]] ?\", \"word\": \"click\", \"created\": \"20220226134401887814\", \"caption\": \"{{||$:/plugins/oflg/fishing-cannedfish/北师大版高中英语选修模块7/Question}}\"}, \"北师大版高中英语选修模块7/20220226134401887818\": {\"title\": \"北师大版高中英语选修模块7/20220226134401887818\", \"tags\": \"[[Unit 20 Lesson 1]] ?\", \"word\": \"handy\", \"created\": \"20220226134401887818\", \"caption\": \"{{||$:/plugins/oflg/fishing-cannedfish/北师大版高中英语选修模块7/Question}}\"}, \"北师大版高中英语选修模块7/20220226134401887821\": {\"title\": \"北师大版高中英语选修模块7/20220226134401887821\", \"tags\": \"[[Unit 20 Lesson 1]] ?\", \"word\": \"shortly\", \"created\": \"20220226134401887821\", \"caption\": \"{{||$:/plugins/oflg/fishing-cannedfish/北师大版高中英语选修模块7/Question}}\"}, \"北师大版高中英语选修模块7/20220226134401887825\": {\"title\": \"北师大版高中英语选修模块7/20220226134401887825\", \"tags\": \"[[Unit 20 Lesson 1]] ?\", \"word\": \"download\", \"created\": \"20220226134401887825\", \"caption\": \"{{||$:/plugins/oflg/fishing-cannedfish/北师大版高中英语选修模块7/Question}}\"}, \"北师大版高中英语选修模块7/20220226134401887828\": {\"title\": \"北师大版高中英语选修模块7/20220226134401887828\", \"tags\": \"[[Unit 20 Lesson 1]] ?\", \"word\": \"update\", \"created\": \"20220226134401887828\", \"caption\": \"{{||$:/plugins/oflg/fishing-cannedfish/北师大版高中英语选修模块7/Question}}\"}, \"北师大版高中英语选修模块7/20220226134401887831\": {\"title\": \"北师大版高中英语选修模块7/20220226134401887831\", \"tags\": \"[[Unit 20 Lesson 1]] ?\", \"word\": \"stainless\", \"created\": \"20220226134401887831\", \"caption\": \"{{||$:/plugins/oflg/fishing-cannedfish/北师大版高中英语选修模块7/Question}}\"}, \"北师大版高中英语选修模块7/20220226134401887834\": {\"title\": \"北师大版高中英语选修模块7/20220226134401887834\", \"tags\": \"[[Unit 20 Lesson 1]] ?\", \"word\": \"stain\", \"created\": \"20220226134401887834\", \"caption\": \"{{||$:/plugins/oflg/fishing-cannedfish/北师大版高中英语选修模块7/Question}}\"}, \"北师大版高中英语选修模块7/20220226134401887837\": {\"title\": \"北师大版高中英语选修模块7/20220226134401887837\", \"tags\": \"[[Unit 20 Lesson 1]] ?\", \"word\": \"garment\", \"created\": \"20220226134401887837\", \"caption\": \"{{||$:/plugins/oflg/fishing-cannedfish/北师大版高中英语选修模块7/Question}}\"}, \"北师大版高中英语选修模块7/20220226134401887841\": {\"title\": \"北师大版高中英语选修模块7/20220226134401887841\", \"tags\": \"[[Unit 20 Lesson 1]] ?\", \"word\": \"worn\", \"created\": \"20220226134401887841\", \"caption\": \"{{||$:/plugins/oflg/fishing-cannedfish/北师大版高中英语选修模块7/Question}}\"}, \"北师大版高中英语选修模块7/20220226134401887844\": {\"title\": \"北师大版高中英语选修模块7/20220226134401887844\", \"tags\": \"[[Unit 20 Lesson 1]] ?\", \"word\": \"starvation\", \"created\": \"20220226134401887844\", \"caption\": \"{{||$:/plugins/oflg/fishing-cannedfish/北师大版高中英语选修模块7/Question}}\"}, \"北师大版高中英语选修模块7/20220226134401887847\": {\"title\": \"北师大版高中英语选修模块7/20220226134401887847\", \"tags\": \"[[Unit 20 Lesson 1]] ?\", \"word\": \"welfare\", \"created\": \"20220226134401887847\", \"caption\": \"{{||$:/plugins/oflg/fishing-cannedfish/北师大版高中英语选修模块7/Question}}\"}, \"北师大版高中英语选修模块7/20220226134401887850\": {\"title\": \"北师大版高中英语选修模块7/20220226134401887850\", \"tags\": \"[[Unit 20 Lesson 1]] ?\", \"word\": \"discrimination\", \"created\": \"20220226134401887850\", \"caption\": \"{{||$:/plugins/oflg/fishing-cannedfish/北师大版高中英语选修模块7/Question}}\"}, \"北师大版高中英语选修模块7/20220226134401887854\": {\"title\": \"北师大版高中英语选修模块7/20220226134401887854\", \"tags\": \"[[Unit 20 Lesson 1]] ?\", \"word\": \"conflict\", \"created\": \"20220226134401887854\", \"caption\": \"{{||$:/plugins/oflg/fishing-cannedfish/北师大版高中英语选修模块7/Question}}\"}, \"北师大版高中英语选修模块7/20220226134401887857\": {\"title\": \"北师大版高中英语选修模块7/20220226134401887857\", \"tags\": \"[[Unit 20 Lesson 1]] ?\", \"word\": \"equality\", \"created\": \"20220226134401887857\", \"caption\": \"{{||$:/plugins/oflg/fishing-cannedfish/北师大版高中英语选修模块7/Question}}\"}, \"北师大版高中英语选修模块7/20220226134401887860\": {\"title\": \"北师大版高中英语选修模块7/20220226134401887860\", \"tags\": \"[[Unit 20 Lesson 1]] ?\", \"word\": \"cell\", \"created\": \"20220226134401887860\", \"caption\": \"{{||$:/plugins/oflg/fishing-cannedfish/北师大版高中英语选修模块7/Question}}\"}, \"北师大版高中英语选修模块7/20220226134401887863\": {\"title\": \"北师大版高中英语选修模块7/20220226134401887863\", \"tags\": \"[[Unit 20 Lesson 1]] ?\", \"word\": \"assess\", \"created\": \"20220226134401887863\", \"caption\": \"{{||$:/plugins/oflg/fishing-cannedfish/北师大版高中英语选修模块7/Question}}\"}, \"北师大版高中英语选修模块7/20220226134401887867\": {\"title\": \"北师大版高中英语选修模块7/20220226134401887867\", \"tags\": \"[[Unit 20 Lesson 1]] ?\", \"word\": \"database\", \"created\": \"20220226134401887867\", \"caption\": \"{{||$:/plugins/oflg/fishing-cannedfish/北师大版高中英语选修模块7/Question}}\"}, \"北师大版高中英语选修模块7/20220226134401887870\": {\"title\": \"北师大版高中英语选修模块7/20220226134401887870\", \"tags\": \"[[Unit 20 Lesson 1]] ?\", \"word\": \"electronic\", \"created\": \"20220226134401887870\", \"caption\": \"{{||$:/plugins/oflg/fishing-cannedfish/北师大版高中英语选修模块7/Question}}\"}, \"北师大版高中英语选修模块7/20220226134401887873\": {\"title\": \"北师大版高中英语选修模块7/20220226134401887873\", \"tags\": \"[[Unit 20 Lesson 1]] ?\", \"word\": \"dawn\", \"created\": \"20220226134401887873\", \"caption\": \"{{||$:/plugins/oflg/fishing-cannedfish/北师大版高中英语选修模块7/Question}}\"}, \"北师大版高中英语选修模块7/20220226134401887876\": {\"title\": \"北师大版高中英语选修模块7/20220226134401887876\", \"tags\": \"[[Unit 20 Lesson 1]] ?\", \"word\": \"digital\", \"created\": \"20220226134401887876\", \"caption\": \"{{||$:/plugins/oflg/fishing-cannedfish/北师大版高中英语选修模块7/Question}}\"}, \"北师大版高中英语选修模块7/20220226134401887880\": {\"title\": \"北师大版高中英语选修模块7/20220226134401887880\", \"tags\": \"[[Unit 20 Lesson 1]] ?\", \"word\": \"source\", \"created\": \"20220226134401887880\", \"caption\": \"{{||$:/plugins/oflg/fishing-cannedfish/北师大版高中英语选修模块7/Question}}\"}, \"北师大版高中英语选修模块7/20220226134401887883\": {\"title\": \"北师大版高中英语选修模块7/20220226134401887883\", \"tags\": \"[[Unit 20 Lesson 1]] ?\", \"word\": \"specialist\", \"created\": \"20220226134401887883\", \"caption\": \"{{||$:/plugins/oflg/fishing-cannedfish/北师大版高中英语选修模块7/Question}}\"}, \"北师大版高中英语选修模块7/20220226134401887886\": {\"title\": \"北师大版高中英语选修模块7/20220226134401887886\", \"tags\": \"[[Unit 20 Lesson 1]] ?\", \"word\": \"participant\", \"created\": \"20220226134401887886\", \"caption\": \"{{||$:/plugins/oflg/fishing-cannedfish/北师大版高中英语选修模块7/Question}}\"}, \"北师大版高中英语选修模块7/20220226134401887890\": {\"title\": \"北师大版高中英语选修模块7/20220226134401887890\", \"tags\": \"[[Unit 20 Lesson 2]] ?\", \"word\": \"present\", \"created\": \"20220226134401887890\", \"caption\": \"{{||$:/plugins/oflg/fishing-cannedfish/北师大版高中英语选修模块7/Question}}\"}, \"北师大版高中英语选修模块7/20220226134401887893\": {\"title\": \"北师大版高中英语选修模块7/20220226134401887893\", \"tags\": \"[[Unit 20 Lesson 2]] ?\", \"word\": \"category\", \"created\": \"20220226134401887893\", \"caption\": \"{{||$:/plugins/oflg/fishing-cannedfish/北师大版高中英语选修模块7/Question}}\"}, \"北师大版高中英语选修模块7/20220226134401887896\": {\"title\": \"北师大版高中英语选修模块7/20220226134401887896\", \"tags\": \"[[Unit 20 Lesson 2]] ?\", \"word\": \"autonomous\", \"created\": \"20220226134401887896\", \"caption\": \"{{||$:/plugins/oflg/fishing-cannedfish/北师大版高中英语选修模块7/Question}}\"}, \"北师大版高中英语选修模块7/20220226134401887900\": {\"title\": \"北师大版高中英语选修模块7/20220226134401887900\", \"tags\": \"[[Unit 20 Lesson 2]] ?\", \"word\": \"programmer\", \"created\": \"20220226134401887900\", \"caption\": \"{{||$:/plugins/oflg/fishing-cannedfish/北师大版高中英语选修模块7/Question}}\"}, \"北师大版高中英语选修模块7/20220226134401887904\": {\"title\": \"北师大版高中英语选修模块7/20220226134401887904\", \"tags\": \"[[Unit 20 Lesson 2]] ?\", \"word\": \"in advance\", \"created\": \"20220226134401887904\", \"caption\": \"{{||$:/plugins/oflg/fishing-cannedfish/北师大版高中英语选修模块7/Question}}\"}, \"北师大版高中英语选修模块7/20220226134401887907\": {\"title\": \"北师大版高中英语选修模块7/20220226134401887907\", \"tags\": \"[[Unit 20 Lesson 2]] ?\", \"word\": \"creator\", \"created\": \"20220226134401887907\", \"caption\": \"{{||$:/plugins/oflg/fishing-cannedfish/北师大版高中英语选修模块7/Question}}\"}, \"北师大版高中英语选修模块7/20220226134401887910\": {\"title\": \"北师大版高中英语选修模块7/20220226134401887910\", \"tags\": \"[[Unit 20 Lesson 2]] ?\", \"word\": \"premiere\", \"created\": \"20220226134401887910\", \"caption\": \"{{||$:/plugins/oflg/fishing-cannedfish/北师大版高中英语选修模块7/Question}}\"}, \"北师大版高中英语选修模块7/20220226134401887913\": {\"title\": \"北师大版高中英语选修模块7/20220226134401887913\", \"tags\": \"[[Unit 20 Lesson 2]] ?\", \"word\": \"caveman\", \"created\": \"20220226134401887913\", \"caption\": \"{{||$:/plugins/oflg/fishing-cannedfish/北师大版高中英语选修模块7/Question}}\"}, \"北师大版高中英语选修模块7/20220226134401887917\": {\"title\": \"北师大版高中英语选修模块7/20220226134401887917\", \"tags\": \"[[Unit 20 Lesson 2]] ?\", \"word\": \"give away\", \"created\": \"20220226134401887917\", \"caption\": \"{{||$:/plugins/oflg/fishing-cannedfish/北师大版高中英语选修模块7/Question}}\"}, \"北师大版高中英语选修模块7/20220226134401887920\": {\"title\": \"北师大版高中英语选修模块7/20220226134401887920\", \"tags\": \"[[Unit 20 Lesson 2]] ?\", \"word\": \"take over\", \"created\": \"20220226134401887920\", \"caption\": \"{{||$:/plugins/oflg/fishing-cannedfish/北师大版高中英语选修模块7/Question}}\"}, \"北师大版高中英语选修模块7/20220226134401887923\": {\"title\": \"北师大版高中英语选修模块7/20220226134401887923\", \"tags\": \"[[Unit 20 Lesson 2]] ?\", \"word\": \"official\", \"created\": \"20220226134401887923\", \"caption\": \"{{||$:/plugins/oflg/fishing-cannedfish/北师大版高中英语选修模块7/Question}}\"}, \"北师大版高中英语选修模块7/20220226134401887927\": {\"title\": \"北师大版高中英语选修模块7/20220226134401887927\", \"tags\": \"[[Unit 20 Lesson 2]] ?\", \"word\": \"invest\", \"created\": \"20220226134401887927\", \"caption\": \"{{||$:/plugins/oflg/fishing-cannedfish/北师大版高中英语选修模块7/Question}}\"}, \"北师大版高中英语选修模块7/20220226134401887930\": {\"title\": \"北师大版高中英语选修模块7/20220226134401887930\", \"tags\": \"[[Unit 20 Lesson 2]] ?\", \"word\": \"colleague\", \"created\": \"20220226134401887930\", \"caption\": \"{{||$:/plugins/oflg/fishing-cannedfish/北师大版高中英语选修模块7/Question}}\"}, \"北师大版高中英语选修模块7/20220226134401887933\": {\"title\": \"北师大版高中英语选修模块7/20220226134401887933\", \"tags\": \"[[Unit 20 Lesson 2]] ?\", \"word\": \"hibernation\", \"created\": \"20220226134401887933\", \"caption\": \"{{||$:/plugins/oflg/fishing-cannedfish/北师大版高中英语选修模块7/Question}}\"}, \"北师大版高中英语选修模块7/20220226134401887937\": {\"title\": \"北师大版高中英语选修模块7/20220226134401887937\", \"tags\": \"[[Unit 20 Lesson 2]] ?\", \"word\": \"rescue\", \"created\": \"20220226134401887937\", \"caption\": \"{{||$:/plugins/oflg/fishing-cannedfish/北师大版高中英语选修模块7/Question}}\"}, \"北师大版高中英语选修模块7/20220226134401887940\": {\"title\": \"北师大版高中英语选修模块7/20220226134401887940\", \"tags\": \"[[Unit 20 Lesson 2]] ?\", \"word\": \"exit\", \"created\": \"20220226134401887940\", \"caption\": \"{{||$:/plugins/oflg/fishing-cannedfish/北师大版高中英语选修模块7/Question}}\"}, \"北师大版高中英语选修模块7/20220226134401887943\": {\"title\": \"北师大版高中英语选修模块7/20220226134401887943\", \"tags\": \"[[Unit 20 Lesson 2]] ?\", \"word\": \"disconnect\", \"created\": \"20220226134401887943\", \"caption\": \"{{||$:/plugins/oflg/fishing-cannedfish/北师大版高中英语选修模块7/Question}}\"}, \"北师大版高中英语选修模块7/20220226134401887947\": {\"title\": \"北师大版高中英语选修模块7/20220226134401887947\", \"tags\": \"[[Unit 20 Lesson 2]] ?\", \"word\": \"original\", \"created\": \"20220226134401887947\", \"caption\": \"{{||$:/plugins/oflg/fishing-cannedfish/北师大版高中英语选修模块7/Question}}\"}, \"北师大版高中英语选修模块7/20220226134401887950\": {\"title\": \"北师大版高中英语选修模块7/20220226134401887950\", \"tags\": \"[[Unit 20 Lesson 2]] ?\", \"word\": \"operational\", \"created\": \"20220226134401887950\", \"caption\": \"{{||$:/plugins/oflg/fishing-cannedfish/北师大版高中英语选修模块7/Question}}\"}, \"北师大版高中英语选修模块7/20220226134401887953\": {\"title\": \"北师大版高中英语选修模块7/20220226134401887953\", \"tags\": \"[[Unit 20 Lesson 2]] ?\", \"word\": \"instructor\", \"created\": \"20220226134401887953\", \"caption\": \"{{||$:/plugins/oflg/fishing-cannedfish/北师大版高中英语选修模块7/Question}}\"}, \"北师大版高中英语选修模块7/20220226134401887957\": {\"title\": \"北师大版高中英语选修模块7/20220226134401887957\", \"tags\": \"[[Unit 20 Lesson 3]] ?\", \"word\": \"dilemma\", \"created\": \"20220226134401887957\", \"caption\": \"{{||$:/plugins/oflg/fishing-cannedfish/北师大版高中英语选修模块7/Question}}\"}, \"北师大版高中英语选修模块7/20220226134401887960\": {\"title\": \"北师大版高中英语选修模块7/20220226134401887960\", \"tags\": \"[[Unit 20 Lesson 3]] ?\", \"word\": \"microscope\", \"created\": \"20220226134401887960\", \"caption\": \"{{||$:/plugins/oflg/fishing-cannedfish/北师大版高中英语选修模块7/Question}}\"}, \"北师大版高中英语选修模块7/20220226134401887963\": {\"title\": \"北师大版高中英语选修模块7/20220226134401887963\", \"tags\": \"[[Unit 20 Lesson 3]] ?\", \"word\": \"procedure\", \"created\": \"20220226134401887963\", \"caption\": \"{{||$:/plugins/oflg/fishing-cannedfish/北师大版高中英语选修模块7/Question}}\"}, \"北师大版高中英语选修模块7/20220226134401887969\": {\"title\": \"北师大版高中英语选修模块7/20220226134401887969\", \"tags\": \"[[Unit 20 Lesson 3]] ?\", \"word\": \"organ\", \"created\": \"20220226134401887969\", \"caption\": \"{{||$:/plugins/oflg/fishing-cannedfish/北师大版高中英语选修模块7/Question}}\"}, \"北师大版高中英语选修模块7/20220226134401887972\": {\"title\": \"北师大版高中英语选修模块7/20220226134401887972\", \"tags\": \"[[Unit 20 Lesson 3]] ?\", \"word\": \"donate\", \"created\": \"20220226134401887972\", \"caption\": \"{{||$:/plugins/oflg/fishing-cannedfish/北师大版高中英语选修模块7/Question}}\"}, \"北师大版高中英语选修模块7/20220226134401887975\": {\"title\": \"北师大版高中英语选修模块7/20220226134401887975\", \"tags\": \"[[Unit 20 Lesson 3]] ?\", \"word\": \"correspond\", \"created\": \"20220226134401887975\", \"caption\": \"{{||$:/plugins/oflg/fishing-cannedfish/北师大版高中英语选修模块7/Question}}\"}, \"北师大版高中英语选修模块7/20220226134401887979\": {\"title\": \"北师大版高中英语选修模块7/20220226134401887979\", \"tags\": \"[[Unit 20 Lesson 3]] ?\", \"word\": \"meanwhile\", \"created\": \"20220226134401887979\", \"caption\": \"{{||$:/plugins/oflg/fishing-cannedfish/北师大版高中英语选修模块7/Question}}\"}, \"北师大版高中英语选修模块7/20220226134401887982\": {\"title\": \"北师大版高中英语选修模块7/20220226134401887982\", \"tags\": \"[[Unit 20 Lesson 3]] ?\", \"word\": \"split\", \"created\": \"20220226134401887982\", \"caption\": \"{{||$:/plugins/oflg/fishing-cannedfish/北师大版高中英语选修模块7/Question}}\"}, \"北师大版高中英语选修模块7/20220226134401887985\": {\"title\": \"北师大版高中英语选修模块7/20220226134401887985\", \"tags\": \"[[Unit 20 Lesson 3]] ?\", \"word\": \"premier\", \"created\": \"20220226134401887985\", \"caption\": \"{{||$:/plugins/oflg/fishing-cannedfish/北师大版高中英语选修模块7/Question}}\"}, \"北师大版高中英语选修模块7/20220226134401887988\": {\"title\": \"北师大版高中英语选修模块7/20220226134401887988\", \"tags\": \"[[Unit 20 Lesson 3]] ?\", \"word\": \"outspoken\", \"created\": \"20220226134401887988\", \"caption\": \"{{||$:/plugins/oflg/fishing-cannedfish/北师大版高中英语选修模块7/Question}}\"}, \"北师大版高中英语选修模块7/20220226134401887992\": {\"title\": \"北师大版高中英语选修模块7/20220226134401887992\", \"tags\": \"[[Unit 20 Lesson 3]] ?\", \"word\": \"telescope\", \"created\": \"20220226134401887992\", \"caption\": \"{{||$:/plugins/oflg/fishing-cannedfish/北师大版高中英语选修模块7/Question}}\"}, \"北师大版高中英语选修模块7/20220226134401887995\": {\"title\": \"北师大版高中英语选修模块7/20220226134401887995\", \"tags\": \"[[Unit 20 Lesson 3]] ?\", \"word\": \"galaxy\", \"created\": \"20220226134401887995\", \"caption\": \"{{||$:/plugins/oflg/fishing-cannedfish/北师大版高中英语选修模块7/Question}}\"}, \"北师大版高中英语选修模块7/20220226134401887998\": {\"title\": \"北师大版高中英语选修模块7/20220226134401887998\", \"tags\": \"[[Unit 20 Lesson 3]] ?\", \"word\": \"mist\", \"created\": \"20220226134401887998\", \"caption\": \"{{||$:/plugins/oflg/fishing-cannedfish/北师大版高中英语选修模块7/Question}}\"}, \"北师大版高中英语选修模块7/20220226134401888002\": {\"title\": \"北师大版高中英语选修模块7/20220226134401888002\", \"tags\": \"[[Unit 20 Lesson 3]] ?\", \"word\": \"mould\", \"created\": \"20220226134401888002\", \"caption\": \"{{||$:/plugins/oflg/fishing-cannedfish/北师大版高中英语选修模块7/Question}}\"}, \"北师大版高中英语选修模块7/20220226134401888005\": {\"title\": \"北师大版高中英语选修模块7/20220226134401888005\", \"tags\": \"[[Unit 20 Lesson 3]] ?\", \"word\": \"penicillin\", \"created\": \"20220226134401888005\", \"caption\": \"{{||$:/plugins/oflg/fishing-cannedfish/北师大版高中英语选修模块7/Question}}\"}, \"北师大版高中英语选修模块7/20220226134401888008\": {\"title\": \"北师大版高中英语选修模块7/20220226134401888008\", \"tags\": \"[[Unit 20 Lesson 3]] ?\", \"word\": \"outcome\", \"created\": \"20220226134401888008\", \"caption\": \"{{||$:/plugins/oflg/fishing-cannedfish/北师大版高中英语选修模块7/Question}}\"}, \"北师大版高中英语选修模块7/20220226134401888011\": {\"title\": \"北师大版高中英语选修模块7/20220226134401888011\", \"tags\": \"[[Unit 20 Lesson 3]] ?\", \"word\": \"cure\", \"created\": \"20220226134401888011\", \"caption\": \"{{||$:/plugins/oflg/fishing-cannedfish/北师大版高中英语选修模块7/Question}}\"}, \"北师大版高中英语选修模块7/20220226134401888015\": {\"title\": \"北师大版高中英语选修模块7/20220226134401888015\", \"tags\": \"[[Unit 20 Lesson 3]] ?\", \"word\": \"navy\", \"created\": \"20220226134401888015\", \"caption\": \"{{||$:/plugins/oflg/fishing-cannedfish/北师大版高中英语选修模块7/Question}}\"}, \"北师大版高中英语选修模块7/20220226134401888018\": {\"title\": \"北师大版高中英语选修模块7/20220226134401888018\", \"tags\": \"[[Unit 20 Lesson 3]] ?\", \"word\": \"wrestle\", \"created\": \"20220226134401888018\", \"caption\": \"{{||$:/plugins/oflg/fishing-cannedfish/北师大版高中英语选修模块7/Question}}\"}, \"北师大版高中英语选修模块7/20220226134401888022\": {\"title\": \"北师大版高中英语选修模块7/20220226134401888022\", \"tags\": \"[[Unit 20 Lesson 3]] ?\", \"word\": \"wrestle with something\", \"created\": \"20220226134401888022\", \"caption\": \"{{||$:/plugins/oflg/fishing-cannedfish/北师大版高中英语选修模块7/Question}}\"}, \"北师大版高中英语选修模块7/20220226134401888025\": {\"title\": \"北师大版高中英语选修模块7/20220226134401888025\", \"tags\": \"[[Unit 20 Lesson 3]] ?\", \"word\": \"circuit\", \"created\": \"20220226134401888025\", \"caption\": \"{{||$:/plugins/oflg/fishing-cannedfish/北师大版高中英语选修模块7/Question}}\"}, \"北师大版高中英语选修模块7/20220226134401888028\": {\"title\": \"北师大版高中英语选修模块7/20220226134401888028\", \"tags\": \"[[Unit 20 Lesson 3]] ?\", \"word\": \"microwave\", \"created\": \"20220226134401888028\", \"caption\": \"{{||$:/plugins/oflg/fishing-cannedfish/北师大版高中英语选修模块7/Question}}\"}, \"北师大版高中英语选修模块7/20220226134401888032\": {\"title\": \"北师大版高中英语选修模块7/20220226134401888032\", \"tags\": \"[[Unit 20 Lesson 3]] ?\", \"word\": \"patent\", \"created\": \"20220226134401888032\", \"caption\": \"{{||$:/plugins/oflg/fishing-cannedfish/北师大版高中英语选修模块7/Question}}\"}, \"北师大版高中英语选修模块7/20220226134401888035\": {\"title\": \"北师大版高中英语选修模块7/20220226134401888035\", \"tags\": \"[[Unit 20 Lesson 3]] ?\", \"word\": \"jet\", \"created\": \"20220226134401888035\", \"caption\": \"{{||$:/plugins/oflg/fishing-cannedfish/北师大版高中英语选修模块7/Question}}\"}, \"北师大版高中英语选修模块7/20220226134401888039\": {\"title\": \"北师大版高中英语选修模块7/20220226134401888039\", \"tags\": \"[[Unit 20 Communication Workshop]] ?\", \"word\": \"exploration\", \"created\": \"20220226134401888039\", \"caption\": \"{{||$:/plugins/oflg/fishing-cannedfish/北师大版高中英语选修模块7/Question}}\"}, \"北师大版高中英语选修模块7/20220226134401888042\": {\"title\": \"北师大版高中英语选修模块7/20220226134401888042\", \"tags\": \"[[Unit 20 Communication Workshop]] ?\", \"word\": \"dot\", \"created\": \"20220226134401888042\", \"caption\": \"{{||$:/plugins/oflg/fishing-cannedfish/北师大版高中英语选修模块7/Question}}\"}, \"北师大版高中英语选修模块7/20220226134401888046\": {\"title\": \"北师大版高中英语选修模块7/20220226134401888046\", \"tags\": \"[[Unit 20 Communication Workshop]] ?\", \"word\": \"ancestor\", \"created\": \"20220226134401888046\", \"caption\": \"{{||$:/plugins/oflg/fishing-cannedfish/北师大版高中英语选修模块7/Question}}\"}, \"北师大版高中英语选修模块7/20220226134401888049\": {\"title\": \"北师大版高中英语选修模块7/20220226134401888049\", \"tags\": \"[[Unit 20 Communication Workshop]] ?\", \"word\": \"outwards\", \"created\": \"20220226134401888049\", \"caption\": \"{{||$:/plugins/oflg/fishing-cannedfish/北师大版高中英语选修模块7/Question}}\"}, \"北师大版高中英语选修模块7/20220226134401888052\": {\"title\": \"北师大版高中英语选修模块7/20220226134401888052\", \"tags\": \"[[Unit 20 Communication Workshop]] ?\", \"word\": \"boundary\", \"created\": \"20220226134401888052\", \"caption\": \"{{||$:/plugins/oflg/fishing-cannedfish/北师大版高中英语选修模块7/Question}}\"}, \"北师大版高中英语选修模块7/20220226134401888055\": {\"title\": \"北师大版高中英语选修模块7/20220226134401888055\", \"tags\": \"[[Unit 20 Communication Workshop]] ?\", \"word\": \"fade\", \"created\": \"20220226134401888055\", \"caption\": \"{{||$:/plugins/oflg/fishing-cannedfish/北师大版高中英语选修模块7/Question}}\"}, \"北师大版高中英语选修模块7/20220226134401888058\": {\"title\": \"北师大版高中英语选修模块7/20220226134401888058\", \"tags\": \"[[Unit 20 Communication Workshop]] ?\", \"word\": \"barrier\", \"created\": \"20220226134401888058\", \"caption\": \"{{||$:/plugins/oflg/fishing-cannedfish/北师大版高中英语选修模块7/Question}}\"}, \"北师大版高中英语选修模块7/20220226134401888062\": {\"title\": \"北师大版高中英语选修模块7/20220226134401888062\", \"tags\": \"[[Unit 20 Communication Workshop]] ?\", \"word\": \"phenomenon\", \"created\": \"20220226134401888062\", \"caption\": \"{{||$:/plugins/oflg/fishing-cannedfish/北师大版高中英语选修模块7/Question}}\"}, \"北师大版高中英语选修模块7/20220226134401888065\": {\"title\": \"北师大版高中英语选修模块7/20220226134401888065\", \"tags\": \"[[Unit 20 Communication Workshop]] ?\", \"word\": \"primitive\", \"created\": \"20220226134401888065\", \"caption\": \"{{||$:/plugins/oflg/fishing-cannedfish/北师大版高中英语选修模块7/Question}}\"}, \"北师大版高中英语选修模块7/20220226134401888068\": {\"title\": \"北师大版高中英语选修模块7/20220226134401888068\", \"tags\": \"[[Unit 20 Communication Workshop]] ?\", \"word\": \"orbit\", \"created\": \"20220226134401888068\", \"caption\": \"{{||$:/plugins/oflg/fishing-cannedfish/北师大版高中英语选修模块7/Question}}\"}, \"北师大版高中英语选修模块7/20220226134401888071\": {\"title\": \"北师大版高中英语选修模块7/20220226134401888071\", \"tags\": \"[[Unit 20 Communication Workshop]] ?\", \"word\": \"permanent\", \"created\": \"20220226134401888071\", \"caption\": \"{{||$:/plugins/oflg/fishing-cannedfish/北师大版高中英语选修模块7/Question}}\"}, \"北师大版高中英语选修模块7/20220226134401888074\": {\"title\": \"北师大版高中英语选修模块7/20220226134401888074\", \"tags\": \"[[Unit 20 Communication Workshop]] ?\", \"word\": \"headline\", \"created\": \"20220226134401888074\", \"caption\": \"{{||$:/plugins/oflg/fishing-cannedfish/北师大版高中英语选修模块7/Question}}\"}, \"北师大版高中英语选修模块7/20220226134401888078\": {\"title\": \"北师大版高中英语选修模块7/20220226134401888078\", \"tags\": \"[[Unit 20 Communication Workshop]] ?\", \"word\": \"initial\", \"created\": \"20220226134401888078\", \"caption\": \"{{||$:/plugins/oflg/fishing-cannedfish/北师大版高中英语选修模块7/Question}}\"}, \"北师大版高中英语选修模块7/20220226134401888081\": {\"title\": \"北师大版高中英语选修模块7/20220226134401888081\", \"tags\": \"[[Unit 20 Communication Workshop]] ?\", \"word\": \"spin\", \"created\": \"20220226134401888081\", \"caption\": \"{{||$:/plugins/oflg/fishing-cannedfish/北师大版高中英语选修模块7/Question}}\"}, \"北师大版高中英语选修模块7/20220226134401888084\": {\"title\": \"北师大版高中英语选修模块7/20220226134401888084\", \"tags\": \"[[Unit 20 Communication Workshop]] ?\", \"word\": \"overhead\", \"created\": \"20220226134401888084\", \"caption\": \"{{||$:/plugins/oflg/fishing-cannedfish/北师大版高中英语选修模块7/Question}}\"}, \"北师大版高中英语选修模块7/20220226134401888087\": {\"title\": \"北师大版高中英语选修模块7/20220226134401888087\", \"tags\": \"[[Unit 20 Communication Workshop]] ?\", \"word\": \"permit\", \"created\": \"20220226134401888087\", \"caption\": \"{{||$:/plugins/oflg/fishing-cannedfish/北师大版高中英语选修模块7/Question}}\"}, \"北师大版高中英语选修模块7/20220226134401888091\": {\"title\": \"北师大版高中英语选修模块7/20220226134401888091\", \"tags\": \"[[Unit 20 Communication Workshop]] ?\", \"word\": \"sneeze\", \"created\": \"20220226134401888091\", \"caption\": \"{{||$:/plugins/oflg/fishing-cannedfish/北师大版高中英语选修模块7/Question}}\"}, \"北师大版高中英语选修模块7/20220226134401888094\": {\"title\": \"北师大版高中英语选修模块7/20220226134401888094\", \"tags\": \"[[Unit 20 Communication Workshop]] ?\", \"word\": \"sniff\", \"created\": \"20220226134401888094\", \"caption\": \"{{||$:/plugins/oflg/fishing-cannedfish/北师大版高中英语选修模块7/Question}}\"}, \"北师大版高中英语选修模块7/20220226134401888097\": {\"title\": \"北师大版高中英语选修模块7/20220226134401888097\", \"tags\": \"[[Unit 20 Communication Workshop]] ?\", \"word\": \"porridge\", \"created\": \"20220226134401888097\", \"caption\": \"{{||$:/plugins/oflg/fishing-cannedfish/北师大版高中英语选修模块7/Question}}\"}, \"北师大版高中英语选修模块7/20220226134401888100\": {\"title\": \"北师大版高中英语选修模块7/20220226134401888100\", \"tags\": \"[[Unit 20 Communication Workshop]] ?\", \"word\": \"ripe\", \"created\": \"20220226134401888100\", \"caption\": \"{{||$:/plugins/oflg/fishing-cannedfish/北师大版高中英语选修模块7/Question}}\"}, \"北师大版高中英语选修模块7/20220226134401888103\": {\"title\": \"北师大版高中英语选修模块7/20220226134401888103\", \"tags\": \"[[Unit 20 Communication Workshop]] ?\", \"word\": \"melon\", \"created\": \"20220226134401888103\", \"caption\": \"{{||$:/plugins/oflg/fishing-cannedfish/北师大版高中英语选修模块7/Question}}\"}, \"北师大版高中英语选修模块7/20220226134401888107\": {\"title\": \"北师大版高中英语选修模块7/20220226134401888107\", \"tags\": \"[[Unit 20 Communication Workshop]] ?\", \"word\": \"ripen\", \"created\": \"20220226134401888107\", \"caption\": \"{{||$:/plugins/oflg/fishing-cannedfish/北师大版高中英语选修模块7/Question}}\"}, \"北师大版高中英语选修模块7/20220226134401888110\": {\"title\": \"北师大版高中英语选修模块7/20220226134401888110\", \"tags\": \"[[Unit 20 Communication Workshop]] ?\", \"word\": \"walnut\", \"created\": \"20220226134401888110\", \"caption\": \"{{||$:/plugins/oflg/fishing-cannedfish/北师大版高中英语选修模块7/Question}}\"}, \"北师大版高中英语选修模块7/20220226134401888113\": {\"title\": \"北师大版高中英语选修模块7/20220226134401888113\", \"tags\": \"[[Unit 20 Communication Workshop]] ?\", \"word\": \"press\", \"created\": \"20220226134401888113\", \"caption\": \"{{||$:/plugins/oflg/fishing-cannedfish/北师大版高中英语选修模块7/Question}}\"}, \"北师大版高中英语选修模块7/20220226134401888116\": {\"title\": \"北师大版高中英语选修模块7/20220226134401888116\", \"tags\": \"[[Unit 20 Communication Workshop]] ?\", \"word\": \"socket\", \"created\": \"20220226134401888116\", \"caption\": \"{{||$:/plugins/oflg/fishing-cannedfish/北师大版高中英语选修模块7/Question}}\"}, \"北师大版高中英语选修模块7/20220226134401888119\": {\"title\": \"北师大版高中英语选修模块7/20220226134401888119\", \"tags\": \"[[Unit 20 Communication Workshop]] ?\", \"word\": \"shaver\", \"created\": \"20220226134401888119\", \"caption\": \"{{||$:/plugins/oflg/fishing-cannedfish/北师大版高中英语选修模块7/Question}}\"}, \"北师大版高中英语选修模块7/20220226134401888122\": {\"title\": \"北师大版高中英语选修模块7/20220226134401888122\", \"tags\": \"[[Unit 20 Communication Workshop]] ?\", \"word\": \"Mars\", \"created\": \"20220226134401888122\", \"caption\": \"{{||$:/plugins/oflg/fishing-cannedfish/北师大版高中英语选修模块7/Question}}\"}, \"北师大版高中英语选修模块7/20220226134401888125\": {\"title\": \"北师大版高中英语选修模块7/20220226134401888125\", \"tags\": \"[[Unit 20 Communication Workshop]] ?\", \"word\": \"Venus\", \"created\": \"20220226134401888125\", \"caption\": \"{{||$:/plugins/oflg/fishing-cannedfish/北师大版高中英语选修模块7/Question}}\"}, \"北师大版高中英语选修模块7/20220226134401888128\": {\"title\": \"北师大版高中英语选修模块7/20220226134401888128\", \"tags\": \"[[Unit 20 Communication Workshop]] ?\", \"word\": \"poisonous\", \"created\": \"20220226134401888128\", \"caption\": \"{{||$:/plugins/oflg/fishing-cannedfish/北师大版高中英语选修模块7/Question}}\"}, \"北师大版高中英语选修模块7/20220226134401888131\": {\"title\": \"北师大版高中英语选修模块7/20220226134401888131\", \"tags\": \"[[Unit 20 Communication Workshop]] ?\", \"word\": \"carbon dioxide\", \"created\": \"20220226134401888131\", \"caption\": \"{{||$:/plugins/oflg/fishing-cannedfish/北师大版高中英语选修模块7/Question}}\"}, \"北师大版高中英语选修模块7/20220226134401888135\": {\"title\": \"北师大版高中英语选修模块7/20220226134401888135\", \"tags\": \"[[Unit 20 Communication Workshop]] ?\", \"word\": \"poison\", \"created\": \"20220226134401888135\", \"caption\": \"{{||$:/plugins/oflg/fishing-cannedfish/北师大版高中英语选修模块7/Question}}\"}, \"北师大版高中英语选修模块7/20220226134401888138\": {\"title\": \"北师大版高中英语选修模块7/20220226134401888138\", \"tags\": \"[[Unit 20 Communication Workshop]] ?\", \"word\": \"canal\", \"created\": \"20220226134401888138\", \"caption\": \"{{||$:/plugins/oflg/fishing-cannedfish/北师大版高中英语选修模块7/Question}}\"}, \"北师大版高中英语选修模块7/20220226134401888141\": {\"title\": \"北师大版高中英语选修模块7/20220226134401888141\", \"tags\": \"[[Unit 20 Communication Workshop]] ?\", \"word\": \"declare\", \"created\": \"20220226134401888141\", \"caption\": \"{{||$:/plugins/oflg/fishing-cannedfish/北师大版高中英语选修模块7/Question}}\"}, \"北师大版高中英语选修模块7/20220226134401888144\": {\"title\": \"北师大版高中英语选修模块7/20220226134401888144\", \"tags\": \"[[Unit 20 Communication Workshop]] ?\", \"word\": \"souvenir\", \"created\": \"20220226134401888144\", \"caption\": \"{{||$:/plugins/oflg/fishing-cannedfish/北师大版高中英语选修模块7/Question}}\"}, \"北师大版高中英语选修模块7/20220226134401888147\": {\"title\": \"北师大版高中英语选修模块7/20220226134401888147\", \"tags\": \"[[Unit 20 Communication Workshop]] ?\", \"word\": \"settler\", \"created\": \"20220226134401888147\", \"caption\": \"{{||$:/plugins/oflg/fishing-cannedfish/北师大版高中英语选修模块7/Question}}\"}, \"北师大版高中英语选修模块7/20220226134401888151\": {\"title\": \"北师大版高中英语选修模块7/20220226134401888151\", \"tags\": \"[[Unit 21 Warm-up]] ?\", \"word\": \"kidney\", \"created\": \"20220226134401888151\", \"caption\": \"{{||$:/plugins/oflg/fishing-cannedfish/北师大版高中英语选修模块7/Question}}\"}, \"北师大版高中英语选修模块7/20220226134401888154\": {\"title\": \"北师大版高中英语选修模块7/20220226134401888154\", \"tags\": \"[[Unit 21 Warm-up]] ?\", \"word\": \"liver\", \"created\": \"20220226134401888154\", \"caption\": \"{{||$:/plugins/oflg/fishing-cannedfish/北师大版高中英语选修模块7/Question}}\"}, \"北师大版高中英语选修模块7/20220226134401888157\": {\"title\": \"北师大版高中英语选修模块7/20220226134401888157\", \"tags\": \"[[Unit 21 Warm-up]] ?\", \"word\": \"interval\", \"created\": \"20220226134401888157\", \"caption\": \"{{||$:/plugins/oflg/fishing-cannedfish/北师大版高中英语选修模块7/Question}}\"}, \"北师大版高中英语选修模块7/20220226134401888160\": {\"title\": \"北师大版高中英语选修模块7/20220226134401888160\", \"tags\": \"[[Unit 21 Warm-up]] ?\", \"word\": \"circulate\", \"created\": \"20220226134401888160\", \"caption\": \"{{||$:/plugins/oflg/fishing-cannedfish/北师大版高中英语选修模块7/Question}}\"}, \"北师大版高中英语选修模块7/20220226134401888163\": {\"title\": \"北师大版高中英语选修模块7/20220226134401888163\", \"tags\": \"[[Unit 21 Warm-up]] ?\", \"word\": \"pump\", \"created\": \"20220226134401888163\", \"caption\": \"{{||$:/plugins/oflg/fishing-cannedfish/北师大版高中英语选修模块7/Question}}\"}, \"北师大版高中英语选修模块7/20220226134401888167\": {\"title\": \"北师大版高中英语选修模块7/20220226134401888167\", \"tags\": \"[[Unit 21 Warm-up]] ?\", \"word\": \"digest\", \"created\": \"20220226134401888167\", \"caption\": \"{{||$:/plugins/oflg/fishing-cannedfish/北师大版高中英语选修模块7/Question}}\"}, \"北师大版高中英语选修模块7/20220226134401888170\": {\"title\": \"北师大版高中英语选修模块7/20220226134401888170\", \"tags\": \"[[Unit 21 Warm-up]] ?\", \"word\": \"mineral\", \"created\": \"20220226134401888170\", \"caption\": \"{{||$:/plugins/oflg/fishing-cannedfish/北师大版高中英语选修模块7/Question}}\"}, \"北师大版高中英语选修模块7/20220226134401888173\": {\"title\": \"北师大版高中英语选修模块7/20220226134401888173\", \"tags\": \"[[Unit 21 Warm-up]] ?\", \"word\": \"swap\", \"created\": \"20220226134401888173\", \"caption\": \"{{||$:/plugins/oflg/fishing-cannedfish/北师大版高中英语选修模块7/Question}}\"}, \"北师大版高中英语选修模块7/20220226134401888177\": {\"title\": \"北师大版高中英语选修模块7/20220226134401888177\", \"tags\": \"[[Unit 21 Warm-up]] ?\", \"word\": \"hearing\", \"created\": \"20220226134401888177\", \"caption\": \"{{||$:/plugins/oflg/fishing-cannedfish/北师大版高中英语选修模块7/Question}}\"}, \"北师大版高中英语选修模块7/20220226134401888180\": {\"title\": \"北师大版高中英语选修模块7/20220226134401888180\", \"tags\": \"[[Unit 21 Warm-up]] ?\", \"word\": \"pulse\", \"created\": \"20220226134401888180\", \"caption\": \"{{||$:/plugins/oflg/fishing-cannedfish/北师大版高中英语选修模块7/Question}}\"}, \"北师大版高中英语选修模块7/20220226134401888184\": {\"title\": \"北师大版高中英语选修模块7/20220226134401888184\", \"tags\": \"[[Unit 21 Lesson 1]] ?\", \"word\": \"track and field\", \"created\": \"20220226134401888184\", \"caption\": \"{{||$:/plugins/oflg/fishing-cannedfish/北师大版高中英语选修模块7/Question}}\"}, \"北师大版高中英语选修模块7/20220226134401888187\": {\"title\": \"北师大版高中英语选修模块7/20220226134401888187\", \"tags\": \"[[Unit 21 Lesson 1]] ?\", \"word\": \"enhance\", \"created\": \"20220226134401888187\", \"caption\": \"{{||$:/plugins/oflg/fishing-cannedfish/北师大版高中英语选修模块7/Question}}\"}, \"北师大版高中英语选修模块7/20220226134401888190\": {\"title\": \"北师大版高中英语选修模块7/20220226134401888190\", \"tags\": \"[[Unit 21 Lesson 1]] ?\", \"word\": \"performance-enhancing\", \"created\": \"20220226134401888190\", \"caption\": \"{{||$:/plugins/oflg/fishing-cannedfish/北师大版高中英语选修模块7/Question}}\"}, \"北师大版高中英语选修模块7/20220226134401888193\": {\"title\": \"北师大版高中英语选修模块7/20220226134401888193\", \"tags\": \"[[Unit 21 Lesson 1]] ?\", \"word\": \"supreme\", \"created\": \"20220226134401888193\", \"caption\": \"{{||$:/plugins/oflg/fishing-cannedfish/北师大版高中英语选修模块7/Question}}\"}, \"北师大版高中英语选修模块7/20220226134401888196\": {\"title\": \"北师大版高中英语选修模块7/20220226134401888196\", \"tags\": \"[[Unit 21 Lesson 1]] ?\", \"word\": \"doping\", \"created\": \"20220226134401888196\", \"caption\": \"{{||$:/plugins/oflg/fishing-cannedfish/北师大版高中英语选修模块7/Question}}\"}, \"北师大版高中英语选修模块7/20220226134401888200\": {\"title\": \"北师大版高中英语选修模块7/20220226134401888200\", \"tags\": \"[[Unit 21 Lesson 1]] ?\", \"word\": \"abuse\", \"created\": \"20220226134401888200\", \"caption\": \"{{||$:/plugins/oflg/fishing-cannedfish/北师大版高中英语选修模块7/Question}}\"}, \"北师大版高中英语选修模块7/20220226134401888203\": {\"title\": \"北师大版高中英语选修模块7/20220226134401888203\", \"tags\": \"[[Unit 21 Lesson 1]] ?\", \"word\": \"tolerate\", \"created\": \"20220226134401888203\", \"caption\": \"{{||$:/plugins/oflg/fishing-cannedfish/北师大版高中英语选修模块7/Question}}\"}, \"北师大版高中英语选修模块7/20220226134401888206\": {\"title\": \"北师大版高中英语选修模块7/20220226134401888206\", \"tags\": \"[[Unit 21 Lesson 1]] ?\", \"word\": \"fundamental\", \"created\": \"20220226134401888206\", \"caption\": \"{{||$:/plugins/oflg/fishing-cannedfish/北师大版高中英语选修模块7/Question}}\"}, \"北师大版高中英语选修模块7/20220226134401888209\": {\"title\": \"北师大版高中英语选修模块7/20220226134401888209\", \"tags\": \"[[Unit 21 Lesson 1]] ?\", \"word\": \"doubtful\", \"created\": \"20220226134401888209\", \"caption\": \"{{||$:/plugins/oflg/fishing-cannedfish/北师大版高中英语选修模块7/Question}}\"}, \"北师大版高中英语选修模块7/20220226134401888212\": {\"title\": \"北师大版高中英语选修模块7/20220226134401888212\", \"tags\": \"[[Unit 21 Lesson 1]] ?\", \"word\": \"seek\", \"created\": \"20220226134401888212\", \"caption\": \"{{||$:/plugins/oflg/fishing-cannedfish/北师大版高中英语选修模块7/Question}}\"}, \"北师大版高中英语选修模块7/20220226134401888216\": {\"title\": \"北师大版高中英语选修模块7/20220226134401888216\", \"tags\": \"[[Unit 21 Lesson 1]] ?\", \"word\": \"annual\", \"created\": \"20220226134401888216\", \"caption\": \"{{||$:/plugins/oflg/fishing-cannedfish/北师大版高中英语选修模块7/Question}}\"}, \"北师大版高中英语选修模块7/20220226134401888219\": {\"title\": \"北师大版高中英语选修模块7/20220226134401888219\", \"tags\": \"[[Unit 21 Lesson 1]] ?\", \"word\": \"lame\", \"created\": \"20220226134401888219\", \"caption\": \"{{||$:/plugins/oflg/fishing-cannedfish/北师大版高中英语选修模块7/Question}}\"}, \"北师大版高中英语选修模块7/20220226134401888222\": {\"title\": \"北师大版高中英语选修模块7/20220226134401888222\", \"tags\": \"[[Unit 21 Lesson 1]] ?\", \"word\": \"in vain\", \"created\": \"20220226134401888222\", \"caption\": \"{{||$:/plugins/oflg/fishing-cannedfish/北师大版高中英语选修模块7/Question}}\"}, \"北师大版高中英语选修模块7/20220226134401888225\": {\"title\": \"北师大版高中英语选修模块7/20220226134401888225\", \"tags\": \"[[Unit 21 Lesson 1]] ?\", \"word\": \"compulsory\", \"created\": \"20220226134401888225\", \"caption\": \"{{||$:/plugins/oflg/fishing-cannedfish/北师大版高中英语选修模块7/Question}}\"}, \"北师大版高中英语选修模块7/20220226134401888229\": {\"title\": \"北师大版高中英语选修模块7/20220226134401888229\", \"tags\": \"[[Unit 21 Lesson 1]] ?\", \"word\": \"at random\", \"created\": \"20220226134401888229\", \"caption\": \"{{||$:/plugins/oflg/fishing-cannedfish/北师大版高中英语选修模块7/Question}}\"}, \"北师大版高中英语选修模块7/20220226134401888232\": {\"title\": \"北师大版高中英语选修模块7/20220226134401888232\", \"tags\": \"[[Unit 21 Lesson 1]] ?\", \"word\": \"gene-therapy\", \"created\": \"20220226134401888232\", \"caption\": \"{{||$:/plugins/oflg/fishing-cannedfish/北师大版高中英语选修模块7/Question}}\"}, \"北师大版高中英语选修模块7/20220226134401888236\": {\"title\": \"北师大版高中英语选修模块7/20220226134401888236\", \"tags\": \"[[Unit 21 Lesson 1]] ?\", \"word\": \"threat\", \"created\": \"20220226134401888236\", \"caption\": \"{{||$:/plugins/oflg/fishing-cannedfish/北师大版高中英语选修模块7/Question}}\"}, \"北师大版高中英语选修模块7/20220226134401888239\": {\"title\": \"北师大版高中英语选修模块7/20220226134401888239\", \"tags\": \"[[Unit 21 Lesson 1]] ?\", \"word\": \"controversial\", \"created\": \"20220226134401888239\", \"caption\": \"{{||$:/plugins/oflg/fishing-cannedfish/北师大版高中英语选修模块7/Question}}\"}, \"北师大版高中英语选修模块7/20220226134401888242\": {\"title\": \"北师大版高中英语选修模块7/20220226134401888242\", \"tags\": \"[[Unit 21 Lesson 1]] ?\", \"word\": \"oppose\", \"created\": \"20220226134401888242\", \"caption\": \"{{||$:/plugins/oflg/fishing-cannedfish/北师大版高中英语选修模块7/Question}}\"}, \"北师大版高中英语选修模块7/20220226134401888245\": {\"title\": \"北师大版高中英语选修模块7/20220226134401888245\", \"tags\": \"[[Unit 21 Lesson 1]] ?\", \"word\": \"dash\", \"created\": \"20220226134401888245\", \"caption\": \"{{||$:/plugins/oflg/fishing-cannedfish/北师大版高中英语选修模块7/Question}}\"}, \"北师大版高中英语选修模块7/20220226134401888248\": {\"title\": \"北师大版高中英语选修模块7/20220226134401888248\", \"tags\": \"[[Unit 21 Lesson 1]] ?\", \"word\": \"marathon\", \"created\": \"20220226134401888248\", \"caption\": \"{{||$:/plugins/oflg/fishing-cannedfish/北师大版高中英语选修模块7/Question}}\"}, \"北师大版高中英语选修模块7/20220226134401888252\": {\"title\": \"北师大版高中英语选修模块7/20220226134401888252\", \"tags\": \"[[Unit 21 Lesson 1]] ?\", \"word\": \"contradict\", \"created\": \"20220226134401888252\", \"caption\": \"{{||$:/plugins/oflg/fishing-cannedfish/北师大版高中英语选修模块7/Question}}\"}, \"北师大版高中英语选修模块7/20220226134401888255\": {\"title\": \"北师大版高中英语选修模块7/20220226134401888255\", \"tags\": \"[[Unit 21 Lesson 1]] ?\", \"word\": \"violate\", \"created\": \"20220226134401888255\", \"caption\": \"{{||$:/plugins/oflg/fishing-cannedfish/北师大版高中英语选修模块7/Question}}\"}, \"北师大版高中英语选修模块7/20220226134401888258\": {\"title\": \"北师大版高中英语选修模块7/20220226134401888258\", \"tags\": \"[[Unit 21 Lesson 1]] ?\", \"word\": \"at all costs\", \"created\": \"20220226134401888258\", \"caption\": \"{{||$:/plugins/oflg/fishing-cannedfish/北师大版高中英语选修模块7/Question}}\"}, \"北师大版高中英语选修模块7/20220226134401888262\": {\"title\": \"北师大版高中英语选修模块7/20220226134401888262\", \"tags\": \"[[Unit 21 Lesson 2]] ?\", \"word\": \"impulse\", \"created\": \"20220226134401888262\", \"caption\": \"{{||$:/plugins/oflg/fishing-cannedfish/北师大版高中英语选修模块7/Question}}\"}, \"北师大版高中英语选修模块7/20220226134401888265\": {\"title\": \"北师大版高中英语选修模块7/20220226134401888265\", \"tags\": \"[[Unit 21 Lesson 2]] ?\", \"word\": \"complicated\", \"created\": \"20220226134401888265\", \"caption\": \"{{||$:/plugins/oflg/fishing-cannedfish/北师大版高中英语选修模块7/Question}}\"}, \"北师大版高中英语选修模块7/20220226134401888268\": {\"title\": \"北师大版高中英语选修模块7/20220226134401888268\", \"tags\": \"[[Unit 21 Lesson 2]] ?\", \"word\": \"miniature\", \"created\": \"20220226134401888268\", \"caption\": \"{{||$:/plugins/oflg/fishing-cannedfish/北师大版高中英语选修模块7/Question}}\"}, \"北师大版高中英语选修模块7/20220226134401888272\": {\"title\": \"北师大版高中英语选修模块7/20220226134401888272\", \"tags\": \"[[Unit 21 Lesson 2]] ?\", \"word\": \"soundtrack\", \"created\": \"20220226134401888272\", \"caption\": \"{{||$:/plugins/oflg/fishing-cannedfish/北师大版高中英语选修模块7/Question}}\"}, \"北师大版高中英语选修模块7/20220226134401888275\": {\"title\": \"北师大版高中英语选修模块7/20220226134401888275\", \"tags\": \"[[Unit 21 Lesson 2]] ?\", \"word\": \"interpret\", \"created\": \"20220226134401888275\", \"caption\": \"{{||$:/plugins/oflg/fishing-cannedfish/北师大版高中英语选修模块7/Question}}\"}, \"北师大版高中英语选修模块7/20220226134401888278\": {\"title\": \"北师大版高中英语选修模块7/20220226134401888278\", \"tags\": \"[[Unit 21 Lesson 2]] ?\", \"word\": \"identify\", \"created\": \"20220226134401888278\", \"caption\": \"{{||$:/plugins/oflg/fishing-cannedfish/北师大版高中英语选修模块7/Question}}\"}, \"北师大版高中英语选修模块7/20220226134401888281\": {\"title\": \"北师大版高中英语选修模块7/20220226134401888281\", \"tags\": \"[[Unit 21 Lesson 2]] ?\", \"word\": \"emotion\", \"created\": \"20220226134401888281\", \"caption\": \"{{||$:/plugins/oflg/fishing-cannedfish/北师大版高中英语选修模块7/Question}}\"}, \"北师大版高中英语选修模块7/20220226134401888284\": {\"title\": \"北师大版高中英语选修模块7/20220226134401888284\", \"tags\": \"[[Unit 21 Lesson 2]] ?\", \"word\": \"privileged\", \"created\": \"20220226134401888284\", \"caption\": \"{{||$:/plugins/oflg/fishing-cannedfish/北师大版高中英语选修模块7/Question}}\"}, \"北师大版高中英语选修模块7/20220226134401888288\": {\"title\": \"北师大版高中英语选修模块7/20220226134401888288\", \"tags\": \"[[Unit 21 Lesson 2]] ?\", \"word\": \"cater\", \"created\": \"20220226134401888288\", \"caption\": \"{{||$:/plugins/oflg/fishing-cannedfish/北师大版高中英语选修模块7/Question}}\"}, \"北师大版高中英语选修模块7/20220226134401888291\": {\"title\": \"北师大版高中英语选修模块7/20220226134401888291\", \"tags\": \"[[Unit 21 Lesson 2]] ?\", \"word\": \"entry\", \"created\": \"20220226134401888291\", \"caption\": \"{{||$:/plugins/oflg/fishing-cannedfish/北师大版高中英语选修模块7/Question}}\"}, \"北师大版高中英语选修模块7/20220226134401888294\": {\"title\": \"北师大版高中英语选修模块7/20220226134401888294\", \"tags\": \"[[Unit 21 Lesson 2]] ?\", \"word\": \"ample\", \"created\": \"20220226134401888294\", \"caption\": \"{{||$:/plugins/oflg/fishing-cannedfish/北师大版高中英语选修模块7/Question}}\"}, \"北师大版高中英语选修模块7/20220226134401888298\": {\"title\": \"北师大版高中英语选修模块7/20220226134401888298\", \"tags\": \"[[Unit 21 Lesson 2]] ?\", \"word\": \"herb\", \"created\": \"20220226134401888298\", \"caption\": \"{{||$:/plugins/oflg/fishing-cannedfish/北师大版高中英语选修模块7/Question}}\"}, \"北师大版高中英语选修模块7/20220226134401888301\": {\"title\": \"北师大版高中英语选修模块7/20220226134401888301\", \"tags\": \"[[Unit 21 Lesson 2]] ?\", \"word\": \"scan\", \"created\": \"20220226134401888301\", \"caption\": \"{{||$:/plugins/oflg/fishing-cannedfish/北师大版高中英语选修模块7/Question}}\"}, \"北师大版高中英语选修模块7/20220226134401888305\": {\"title\": \"北师大版高中英语选修模块7/20220226134401888305\", \"tags\": \"[[Unit 21 Lesson 2]] ?\", \"word\": \"treat\", \"created\": \"20220226134401888305\", \"caption\": \"{{||$:/plugins/oflg/fishing-cannedfish/北师大版高中英语选修模块7/Question}}\"}, \"北师大版高中英语选修模块7/20220226134401888308\": {\"title\": \"北师大版高中英语选修模块7/20220226134401888308\", \"tags\": \"[[Unit 21 Lesson 2]] ?\", \"word\": \"storage\", \"created\": \"20220226134401888308\", \"caption\": \"{{||$:/plugins/oflg/fishing-cannedfish/北师大版高中英语选修模块7/Question}}\"}, \"北师大版高中英语选修模块7/20220226134401888311\": {\"title\": \"北师大版高中英语选修模块7/20220226134401888311\", \"tags\": \"[[Unit 21 Lesson 2]] ?\", \"word\": \"postpone\", \"created\": \"20220226134401888311\", \"caption\": \"{{||$:/plugins/oflg/fishing-cannedfish/北师大版高中英语选修模块7/Question}}\"}, \"北师大版高中英语选修模块7/20220226134401888315\": {\"title\": \"北师大版高中英语选修模块7/20220226134401888315\", \"tags\": \"[[Unit 21 Lesson 2]] ?\", \"word\": \"straight away\", \"created\": \"20220226134401888315\", \"caption\": \"{{||$:/plugins/oflg/fishing-cannedfish/北师大版高中英语选修模块7/Question}}\"}, \"北师大版高中英语选修模块7/20220226134401888319\": {\"title\": \"北师大版高中英语选修模块7/20220226134401888319\", \"tags\": \"[[Unit 21 Lesson 3]] ?\", \"word\": \"epidemic\", \"created\": \"20220226134401888319\", \"caption\": \"{{||$:/plugins/oflg/fishing-cannedfish/北师大版高中英语选修模块7/Question}}\"}, \"北师大版高中英语选修模块7/20220226134401888322\": {\"title\": \"北师大版高中英语选修模块7/20220226134401888322\", \"tags\": \"[[Unit 21 Lesson 3]] ?\", \"word\": \"cancer\", \"created\": \"20220226134401888322\", \"caption\": \"{{||$:/plugins/oflg/fishing-cannedfish/北师大版高中英语选修模块7/Question}}\"}, \"北师大版高中英语选修模块7/20220226134401888325\": {\"title\": \"北师大版高中英语选修模块7/20220226134401888325\", \"tags\": \"[[Unit 21 Lesson 3]] ?\", \"word\": \"wipe\", \"created\": \"20220226134401888325\", \"caption\": \"{{||$:/plugins/oflg/fishing-cannedfish/北师大版高中英语选修模块7/Question}}\"}, \"北师大版高中英语选修模块7/20220226134401888328\": {\"title\": \"北师大版高中英语选修模块7/20220226134401888328\", \"tags\": \"[[Unit 21 Lesson 3]] ?\", \"word\": \"urban\", \"created\": \"20220226134401888328\", \"caption\": \"{{||$:/plugins/oflg/fishing-cannedfish/北师大版高中英语选修模块7/Question}}\"}, \"北师大版高中英语选修模块7/20220226134401888332\": {\"title\": \"北师大版高中英语选修模块7/20220226134401888332\", \"tags\": \"[[Unit 21 Lesson 3]] ?\", \"word\": \"rebuild\", \"created\": \"20220226134401888332\", \"caption\": \"{{||$:/plugins/oflg/fishing-cannedfish/北师大版高中英语选修模块7/Question}}\"}, \"北师大版高中英语选修模块7/20220226134401888335\": {\"title\": \"北师大版高中英语选修模块7/20220226134401888335\", \"tags\": \"[[Unit 21 Lesson 3]] ?\", \"word\": \"empire\", \"created\": \"20220226134401888335\", \"caption\": \"{{||$:/plugins/oflg/fishing-cannedfish/北师大版高中英语选修模块7/Question}}\"}, \"北师大版高中英语选修模块7/20220226134401888338\": {\"title\": \"北师大版高中英语选修模块7/20220226134401888338\", \"tags\": \"[[Unit 21 Lesson 3]] ?\", \"word\": \"trial\", \"created\": \"20220226134401888338\", \"caption\": \"{{||$:/plugins/oflg/fishing-cannedfish/北师大版高中英语选修模块7/Question}}\"}, \"北师大版高中英语选修模块7/20220226134401888341\": {\"title\": \"北师大版高中英语选修模块7/20220226134401888341\", \"tags\": \"[[Unit 21 Lesson 3]] ?\", \"word\": \"prohibit\", \"created\": \"20220226134401888341\", \"caption\": \"{{||$:/plugins/oflg/fishing-cannedfish/北师大版高中英语选修模块7/Question}}\"}, \"北师大版高中英语选修模块7/20220226134401888344\": {\"title\": \"北师大版高中英语选修模块7/20220226134401888344\", \"tags\": \"[[Unit 21 Lesson 3]] ?\", \"word\": \"unite\", \"created\": \"20220226134401888344\", \"caption\": \"{{||$:/plugins/oflg/fishing-cannedfish/北师大版高中英语选修模块7/Question}}\"}, \"北师大版高中英语选修模块7/20220226134401888347\": {\"title\": \"北师大版高中英语选修模块7/20220226134401888347\", \"tags\": \"[[Unit 21 Lesson 3]] ?\", \"word\": \"pause\", \"created\": \"20220226134401888347\", \"caption\": \"{{||$:/plugins/oflg/fishing-cannedfish/北师大版高中英语选修模块7/Question}}\"}, \"北师大版高中英语选修模块7/20220226134401888351\": {\"title\": \"北师大版高中英语选修模块7/20220226134401888351\", \"tags\": \"[[Unit 21 Lesson 3]] ?\", \"word\": \"acute\", \"created\": \"20220226134401888351\", \"caption\": \"{{||$:/plugins/oflg/fishing-cannedfish/北师大版高中英语选修模块7/Question}}\"}, \"北师大版高中英语选修模块7/20220226134401888354\": {\"title\": \"北师大版高中英语选修模块7/20220226134401888354\", \"tags\": \"[[Unit 21 Lesson 3]] ?\", \"word\": \"statistics\", \"created\": \"20220226134401888354\", \"caption\": \"{{||$:/plugins/oflg/fishing-cannedfish/北师大版高中英语选修模块7/Question}}\"}, \"北师大版高中英语选修模块7/20220226134401888357\": {\"title\": \"北师大版高中英语选修模块7/20220226134401888357\", \"tags\": \"[[Unit 21 Lesson 3]] ?\", \"word\": \"symptom\", \"created\": \"20220226134401888357\", \"caption\": \"{{||$:/plugins/oflg/fishing-cannedfish/北师大版高中英语选修模块7/Question}}\"}, \"北师大版高中英语选修模块7/20220226134401888360\": {\"title\": \"北师大版高中英语选修模块7/20220226134401888360\", \"tags\": \"[[Unit 21 Lesson 3]] ?\", \"word\": \"routine\", \"created\": \"20220226134401888360\", \"caption\": \"{{||$:/plugins/oflg/fishing-cannedfish/北师大版高中英语选修模块7/Question}}\"}, \"北师大版高中英语选修模块7/20220226134401888364\": {\"title\": \"北师大版高中英语选修模块7/20220226134401888364\", \"tags\": \"[[Unit 21 Lesson 3]] ?\", \"word\": \"press\", \"created\": \"20220226134401888364\", \"caption\": \"{{||$:/plugins/oflg/fishing-cannedfish/北师大版高中英语选修模块7/Question}}\"}, \"北师大版高中英语选修模块7/20220226134401888367\": {\"title\": \"北师大版高中英语选修模块7/20220226134401888367\", \"tags\": \"[[Unit 21 Lesson 3]] ?\", \"word\": \"parallel\", \"created\": \"20220226134401888367\", \"caption\": \"{{||$:/plugins/oflg/fishing-cannedfish/北师大版高中英语选修模块7/Question}}\"}, \"北师大版高中英语选修模块7/20220226134401888370\": {\"title\": \"北师大版高中英语选修模块7/20220226134401888370\", \"tags\": \"[[Unit 21 Lesson 3]] ?\", \"word\": \"tissue\", \"created\": \"20220226134401888370\", \"caption\": \"{{||$:/plugins/oflg/fishing-cannedfish/北师大版高中英语选修模块7/Question}}\"}, \"北师大版高中英语选修模块7/20220226134401888373\": {\"title\": \"北师大版高中英语选修模块7/20220226134401888373\", \"tags\": \"[[Unit 21 Lesson 3]] ?\", \"word\": \"adaptation\", \"created\": \"20220226134401888373\", \"caption\": \"{{||$:/plugins/oflg/fishing-cannedfish/北师大版高中英语选修模块7/Question}}\"}, \"北师大版高中英语选修模块7/20220226134401888377\": {\"title\": \"北师大版高中英语选修模块7/20220226134401888377\", \"tags\": \"[[Unit 21 Lesson 3]] ?\", \"word\": \"foresee\", \"created\": \"20220226134401888377\", \"caption\": \"{{||$:/plugins/oflg/fishing-cannedfish/北师大版高中英语选修模块7/Question}}\"}, \"北师大版高中英语选修模块7/20220226134401888380\": {\"title\": \"北师大版高中英语选修模块7/20220226134401888380\", \"tags\": \"[[Unit 21 Lesson 3]] ?\", \"word\": \"mourn\", \"created\": \"20220226134401888380\", \"caption\": \"{{||$:/plugins/oflg/fishing-cannedfish/北师大版高中英语选修模块7/Question}}\"}, \"北师大版高中英语选修模块7/20220226134401888383\": {\"title\": \"北师大版高中英语选修模块7/20220226134401888383\", \"tags\": \"[[Unit 21 Lesson 3]] ?\", \"word\": \"carrier\", \"created\": \"20220226134401888383\", \"caption\": \"{{||$:/plugins/oflg/fishing-cannedfish/北师大版高中英语选修模块7/Question}}\"}, \"北师大版高中英语选修模块7/20220226134401888387\": {\"title\": \"北师大版高中英语选修模块7/20220226134401888387\", \"tags\": \"[[Unit 21 Lesson 3]] ?\", \"word\": \"prescription\", \"created\": \"20220226134401888387\", \"caption\": \"{{||$:/plugins/oflg/fishing-cannedfish/北师大版高中英语选修模块7/Question}}\"}, \"北师大版高中英语选修模块7/20220226134401888390\": {\"title\": \"北师大版高中英语选修模块7/20220226134401888390\", \"tags\": \"[[Unit 21 Lesson 3]] ?\", \"word\": \"tablet\", \"created\": \"20220226134401888390\", \"caption\": \"{{||$:/plugins/oflg/fishing-cannedfish/北师大版高中英语选修模块7/Question}}\"}, \"北师大版高中英语选修模块7/20220226134401888393\": {\"title\": \"北师大版高中英语选修模块7/20220226134401888393\", \"tags\": \"[[Unit 21 Lesson 3]] ?\", \"word\": \"underline\", \"created\": \"20220226134401888393\", \"caption\": \"{{||$:/plugins/oflg/fishing-cannedfish/北师大版高中英语选修模块7/Question}}\"}, \"北师大版高中英语选修模块7/20220226134401888396\": {\"title\": \"北师大版高中英语选修模块7/20220226134401888396\", \"tags\": \"[[Unit 21 Lesson 3]] ?\", \"word\": \"thorough\", \"created\": \"20220226134401888396\", \"caption\": \"{{||$:/plugins/oflg/fishing-cannedfish/北师大版高中英语选修模块7/Question}}\"}, \"北师大版高中英语选修模块7/20220226134401888399\": {\"title\": \"北师大版高中英语选修模块7/20220226134401888399\", \"tags\": \"[[Unit 21 Lesson 3]] ?\", \"word\": \"systematic\", \"created\": \"20220226134401888399\", \"caption\": \"{{||$:/plugins/oflg/fishing-cannedfish/北师大版高中英语选修模块7/Question}}\"}, \"北师大版高中英语选修模块7/20220226134401888403\": {\"title\": \"北师大版高中英语选修模块7/20220226134401888403\", \"tags\": \"[[Unit 21 Lesson 3]] ?\", \"word\": \"teamwork\", \"created\": \"20220226134401888403\", \"caption\": \"{{||$:/plugins/oflg/fishing-cannedfish/北师大版高中英语选修模块7/Question}}\"}, \"北师大版高中英语选修模块7/20220226134401888406\": {\"title\": \"北师大版高中英语选修模块7/20220226134401888406\", \"tags\": \"[[Unit 21 Lesson 3]] ?\", \"word\": \"faith\", \"created\": \"20220226134401888406\", \"caption\": \"{{||$:/plugins/oflg/fishing-cannedfish/北师大版高中英语选修模块7/Question}}\"}, \"北师大版高中英语选修模块7/20220226134401888409\": {\"title\": \"北师大版高中英语选修模块7/20220226134401888409\", \"tags\": \"[[Unit 21 Lesson 3]] ?\", \"word\": \"stop sth. in its tracks\", \"created\": \"20220226134401888409\", \"caption\": \"{{||$:/plugins/oflg/fishing-cannedfish/北师大版高中英语选修模块7/Question}}\"}, \"北师大版高中英语选修模块7/20220226134401888412\": {\"title\": \"北师大版高中英语选修模块7/20220226134401888412\", \"tags\": \"[[Unit 21 Lesson 3]] ?\", \"word\": \"pill\", \"created\": \"20220226134401888412\", \"caption\": \"{{||$:/plugins/oflg/fishing-cannedfish/北师大版高中英语选修模块7/Question}}\"}, \"北师大版高中英语选修模块7/20220226134401888416\": {\"title\": \"北师大版高中英语选修模块7/20220226134401888416\", \"tags\": \"[[Unit 21 Communication Workshop]] ?\", \"word\": \"coma\", \"created\": \"20220226134401888416\", \"caption\": \"{{||$:/plugins/oflg/fishing-cannedfish/北师大版高中英语选修模块7/Question}}\"}, \"北师大版高中英语选修模块7/20220226134401888419\": {\"title\": \"北师大版高中英语选修模块7/20220226134401888419\", \"tags\": \"[[Unit 21 Communication Workshop]] ?\", \"word\": \"weekly\", \"created\": \"20220226134401888419\", \"caption\": \"{{||$:/plugins/oflg/fishing-cannedfish/北师大版高中英语选修模块7/Question}}\"}, \"北师大版高中英语选修模块7/20220226134401888422\": {\"title\": \"北师大版高中英语选修模块7/20220226134401888422\", \"tags\": \"[[Unit 21 Communication Workshop]] ?\", \"word\": \"temporary\", \"created\": \"20220226134401888422\", \"caption\": \"{{||$:/plugins/oflg/fishing-cannedfish/北师大版高中英语选修模块7/Question}}\"}, \"北师大版高中英语选修模块7/20220226134401888426\": {\"title\": \"北师大版高中英语选修模块7/20220226134401888426\", \"tags\": \"[[Unit 21 Communication Workshop]] ?\", \"word\": \"numb\", \"created\": \"20220226134401888426\", \"caption\": \"{{||$:/plugins/oflg/fishing-cannedfish/北师大版高中英语选修模块7/Question}}\"}, \"北师大版高中英语选修模块7/20220226134401888429\": {\"title\": \"北师大版高中英语选修模块7/20220226134401888429\", \"tags\": \"[[Unit 21 Communication Workshop]] ?\", \"word\": \"sacred\", \"created\": \"20220226134401888429\", \"caption\": \"{{||$:/plugins/oflg/fishing-cannedfish/北师大版高中英语选修模块7/Question}}\"}, \"北师大版高中英语选修模块7/20220226134401888432\": {\"title\": \"北师大版高中英语选修模块7/20220226134401888432\", \"tags\": \"[[Unit 21 Communication Workshop]] ?\", \"word\": \"rob\", \"created\": \"20220226134401888432\", \"caption\": \"{{||$:/plugins/oflg/fishing-cannedfish/北师大版高中英语选修模块7/Question}}\"}, \"北师大版高中英语选修模块7/20220226134401888435\": {\"title\": \"北师大版高中英语选修模块7/20220226134401888435\", \"tags\": \"[[Unit 21 Communication Workshop]] ?\", \"word\": \"terminal\", \"created\": \"20220226134401888435\", \"caption\": \"{{||$:/plugins/oflg/fishing-cannedfish/北师大版高中英语选修模块7/Question}}\"}, \"北师大版高中英语选修模块7/20220226134401888438\": {\"title\": \"北师大版高中英语选修模块7/20220226134401888438\", \"tags\": \"[[Unit 21 Communication Workshop]] ?\", \"word\": \"helmet\", \"created\": \"20220226134401888438\", \"caption\": \"{{||$:/plugins/oflg/fishing-cannedfish/北师大版高中英语选修模块7/Question}}\"}, \"北师大版高中英语选修模块7/20220226134401888442\": {\"title\": \"北师大版高中英语选修模块7/20220226134401888442\", \"tags\": \"[[Unit 21 Communication Workshop]] ?\", \"word\": \"decline\", \"created\": \"20220226134401888442\", \"caption\": \"{{||$:/plugins/oflg/fishing-cannedfish/北师大版高中英语选修模块7/Question}}\"}, \"北师大版高中英语选修模块7/20220226134401888445\": {\"title\": \"北师大版高中英语选修模块7/20220226134401888445\", \"tags\": \"[[Unit 21 Communication Workshop]] ?\", \"word\": \"minimum\", \"created\": \"20220226134401888445\", \"caption\": \"{{||$:/plugins/oflg/fishing-cannedfish/北师大版高中英语选修模块7/Question}}\"}, \"北师大版高中英语选修模块7/20220226134401888448\": {\"title\": \"北师大版高中英语选修模块7/20220226134401888448\", \"tags\": \"[[Unit 21 Communication Workshop]] ?\", \"word\": \"institution\", \"created\": \"20220226134401888448\", \"caption\": \"{{||$:/plugins/oflg/fishing-cannedfish/北师大版高中英语选修模块7/Question}}\"}, \"北师大版高中英语选修模块7/20220226134401888452\": {\"title\": \"北师大版高中英语选修模块7/20220226134401888452\", \"tags\": \"[[Unit 21 Communication Workshop]] ?\", \"word\": \"unconditionally\", \"created\": \"20220226134401888452\", \"caption\": \"{{||$:/plugins/oflg/fishing-cannedfish/北师大版高中英语选修模块7/Question}}\"}, \"北师大版高中英语选修模块7/20220226134401888455\": {\"title\": \"北师大版高中英语选修模块7/20220226134401888455\", \"tags\": \"[[Unit 21 Communication Workshop]] ?\", \"word\": \"tentatively\", \"created\": \"20220226134401888455\", \"caption\": \"{{||$:/plugins/oflg/fishing-cannedfish/北师大版高中英语选修模块7/Question}}\"}, \"北师大版高中英语选修模块7/20220226134401888458\": {\"title\": \"北师大版高中英语选修模块7/20220226134401888458\", \"tags\": \"[[Unit 21 Communication Workshop]] ?\", \"word\": \"equip\", \"created\": \"20220226134401888458\", \"caption\": \"{{||$:/plugins/oflg/fishing-cannedfish/北师大版高中英语选修模块7/Question}}\"}, \"北师大版高中英语选修模块7/20220226134401888462\": {\"title\": \"北师大版高中英语选修模块7/20220226134401888462\", \"tags\": \"[[Unit 21 Communication Workshop]] ?\", \"word\": \"firm\", \"created\": \"20220226134401888462\", \"caption\": \"{{||$:/plugins/oflg/fishing-cannedfish/北师大版高中英语选修模块7/Question}}\"}, \"北师大版高中英语选修模块7/20220226134401888465\": {\"title\": \"北师大版高中英语选修模块7/20220226134401888465\", \"tags\": \"[[Unit 21 Communication Workshop]] ?\", \"word\": \"fortune\", \"created\": \"20220226134401888465\", \"caption\": \"{{||$:/plugins/oflg/fishing-cannedfish/北师大版高中英语选修模块7/Question}}\"}, \"北师大版高中英语选修模块7/20220226134401888468\": {\"title\": \"北师大版高中英语选修模块7/20220226134401888468\", \"tags\": \"[[Unit 21 Communication Workshop]] ?\", \"word\": \"reverse\", \"created\": \"20220226134401888468\", \"caption\": \"{{||$:/plugins/oflg/fishing-cannedfish/北师大版高中英语选修模块7/Question}}\"}, \"北师大版高中英语选修模块7/20220226134401888471\": {\"title\": \"北师大版高中英语选修模块7/20220226134401888471\", \"tags\": \"[[Unit 21 Communication Workshop]] ?\", \"word\": \"rate\", \"created\": \"20220226134401888471\", \"caption\": \"{{||$:/plugins/oflg/fishing-cannedfish/北师大版高中英语选修模块7/Question}}\"}, \"北师大版高中英语选修模块7/20220226134401888475\": {\"title\": \"北师大版高中英语选修模块7/20220226134401888475\", \"tags\": \"[[Unit 21 Communication Workshop]] ?\", \"word\": \"at any rate\", \"created\": \"20220226134401888475\", \"caption\": \"{{||$:/plugins/oflg/fishing-cannedfish/北师大版高中英语选修模块7/Question}}\"}, \"北师大版高中英语选修模块7/20220226134401888478\": {\"title\": \"北师大版高中英语选修模块7/20220226134401888478\", \"tags\": \"[[Unit 21 Communication Workshop]] ?\", \"word\": \"enquiry\", \"created\": \"20220226134401888478\", \"caption\": \"{{||$:/plugins/oflg/fishing-cannedfish/北师大版高中英语选修模块7/Question}}\"}, \"北师大版高中英语选修模块7/20220226134401888481\": {\"title\": \"北师大版高中英语选修模块7/20220226134401888481\", \"tags\": \"[[Unit 21 Communication Workshop]] ?\", \"word\": \"deadline\", \"created\": \"20220226134401888481\", \"caption\": \"{{||$:/plugins/oflg/fishing-cannedfish/北师大版高中英语选修模块7/Question}}\"}, \"北师大版高中英语选修模块7/20220226134401888484\": {\"title\": \"北师大版高中英语选修模块7/20220226134401888484\", \"tags\": \"[[Unit 21 Communication Workshop]] ?\", \"word\": \"submit\", \"created\": \"20220226134401888484\", \"caption\": \"{{||$:/plugins/oflg/fishing-cannedfish/北师大版高中英语选修模块7/Question}}\"}, \"北师大版高中英语选修模块7/20220226134401888487\": {\"title\": \"北师大版高中英语选修模块7/20220226134401888487\", \"tags\": \"[[Unit 21 Communication Workshop]] ?\", \"word\": \"appendix\", \"created\": \"20220226134401888487\", \"caption\": \"{{||$:/plugins/oflg/fishing-cannedfish/北师大版高中英语选修模块7/Question}}\"}, \"北师大版高中英语选修模块7/20220226134401888491\": {\"title\": \"北师大版高中英语选修模块7/20220226134401888491\", \"tags\": \"[[Unit 21 Communication Workshop]] ?\", \"word\": \"extension\", \"created\": \"20220226134401888491\", \"caption\": \"{{||$:/plugins/oflg/fishing-cannedfish/北师大版高中英语选修模块7/Question}}\"}, \"北师大版高中英语选修模块7/20220226134401888494\": {\"title\": \"北师大版高中英语选修模块7/20220226134401888494\", \"tags\": \"[[Unit 21 Communication Workshop]] ?\", \"word\": \"tractor\", \"created\": \"20220226134401888494\", \"caption\": \"{{||$:/plugins/oflg/fishing-cannedfish/北师大版高中英语选修模块7/Question}}\"}, \"北师大版高中英语选修模块7/20220226134401888497\": {\"title\": \"北师大版高中英语选修模块7/20220226134401888497\", \"tags\": \"[[Unit 21 Communication Workshop]] ?\", \"word\": \"jealous\", \"created\": \"20220226134401888497\", \"caption\": \"{{||$:/plugins/oflg/fishing-cannedfish/北师大版高中英语选修模块7/Question}}\"}, \"北师大版高中英语选修模块7/20220226134401888500\": {\"title\": \"北师大版高中英语选修模块7/20220226134401888500\", \"tags\": \"[[Unit 21 Communication Workshop]] ?\", \"word\": \"spade\", \"created\": \"20220226134401888500\", \"caption\": \"{{||$:/plugins/oflg/fishing-cannedfish/北师大版高中英语选修模块7/Question}}\"}, \"北师大版高中英语选修模块7/20220226134401888503\": {\"title\": \"北师大版高中英语选修模块7/20220226134401888503\", \"tags\": \"[[Unit 21 Communication Workshop]] ?\", \"word\": \"aluminium\", \"created\": \"20220226134401888503\", \"caption\": \"{{||$:/plugins/oflg/fishing-cannedfish/北师大版高中英语选修模块7/Question}}\"}, \"北师大版高中英语选修模块7/20220226134401888507\": {\"title\": \"北师大版高中英语选修模块7/20220226134401888507\", \"tags\": \"[[Unit 21 Communication Workshop]] ?\", \"word\": \"tin\", \"created\": \"20220226134401888507\", \"caption\": \"{{||$:/plugins/oflg/fishing-cannedfish/北师大版高中英语选修模块7/Question}}\"}, \"北师大版高中英语选修模块7/20220226134401888510\": {\"title\": \"北师大版高中英语选修模块7/20220226134401888510\", \"tags\": \"[[Unit 21 Communication Workshop]] ?\", \"word\": \"concern\", \"created\": \"20220226134401888510\", \"caption\": \"{{||$:/plugins/oflg/fishing-cannedfish/北师大版高中英语选修模块7/Question}}\"}, \"北师大版高中英语选修模块7/20220226134401888513\": {\"title\": \"北师大版高中英语选修模块7/20220226134401888513\", \"tags\": \"[[Unit 21 Communication Workshop]] ?\", \"word\": \"vote\", \"created\": \"20220226134401888513\", \"caption\": \"{{||$:/plugins/oflg/fishing-cannedfish/北师大版高中英语选修模块7/Question}}\"}, \"北师大版高中英语选修模块7/20220226134401888516\": {\"title\": \"北师大版高中英语选修模块7/20220226134401888516\", \"tags\": \"[[Unit 21 Communication Workshop]] ?\", \"word\": \"sceptical\", \"created\": \"20220226134401888516\", \"caption\": \"{{||$:/plugins/oflg/fishing-cannedfish/北师大版高中英语选修模块7/Question}}\"}, \"北师大版高中英语选修模块7/20220226134401888519\": {\"title\": \"北师大版高中英语选修模块7/20220226134401888519\", \"tags\": \"[[Unit 21 Communication Workshop]] ?\", \"word\": \"belly\", \"created\": \"20220226134401888519\", \"caption\": \"{{||$:/plugins/oflg/fishing-cannedfish/北师大版高中英语选修模块7/Question}}\"}, \"北师大版高中英语选修模块7/20220226134401888523\": {\"title\": \"北师大版高中英语选修模块7/20220226134401888523\", \"tags\": \"[[Unit 21 Communication Workshop]] ?\", \"word\": \"absurd\", \"created\": \"20220226134401888523\", \"caption\": \"{{||$:/plugins/oflg/fishing-cannedfish/北师大版高中英语选修模块7/Question}}\"}, \"北师大版高中英语选修模块7/20220226134401888530\": {\"title\": \"北师大版高中英语选修模块7/20220226134401888530\", \"tags\": \"[[Unit 21 Communication Workshop]] ?\", \"word\": \"circumstance\", \"created\": \"20220226134401888530\", \"caption\": \"{{||$:/plugins/oflg/fishing-cannedfish/北师大版高中英语选修模块7/Question}}\"}}}"}]