[{"author": "oflg", "core-version": ">=5.2.1", "dependents": "$:/plugins/oflg/fishing-cannedfish", "description": "记忆包", "list": "readme", "name": "外研版初中英语八年级下册", "parent-plugin": "$:/plugins/oflg/fishing-cannedfish", "plugin-type": "plugin", "source": "https://github.com/oflg/fishing-cannedfish", "title": "$:/plugins/oflg/fishing-cannedfish/外研版初中英语八年级下册", "version": "0.0.1", "type": "application/json", "text": "{\"tiddlers\": {\"$:/plugins/oflg/fishing-cannedfish/外研版初中英语八年级下册/readme\": {\"title\": \"$:/plugins/oflg/fishing-cannedfish/外研版初中英语八年级下册/readme\", \"text\": \"Installation and usage tutorial is available at [[Fishing Manual|https://oflg.github.io/fishing/]].\\n\\n可在 [[钓鱼手册|https://oflg.github.io/fishing/]] 查看安装使用教程。\"}, \"$:/plugins/oflg/fishing/fishingrod/[all[shadows+tiddlers]tag[?]prefix[外研版初中英语八年级下册/]]\": {\"title\": \"$:/plugins/oflg/fishing/fishingrod/[all[shadows+tiddlers]tag[?]prefix[外研版初中英语八年级下册/]]\", \"caption\": \"外研版初中英语八年级下册\"}, \"$:/plugins/oflg/fishing-cannedfish/外研版初中英语八年级下册/SearchWord\": {\"title\": \"$:/plugins/oflg/fishing-cannedfish/外研版初中英语八年级下册/SearchWord\", \"tags\": \"$:/tags/QuestionTemplate\", \"word\": \"Canned fish\", \"text\": \"<$reveal\\n            state=<<folded-state>>\\n            type=\\\"match\\\"\\n            text=\\\"hide\\\"\\n            animate=\\\"yes\\\"\\n        >\\n            {{!!word}}\\n        </$reveal>\\n\\n    <span\\n        class=\\\"tc-fish-title\\\"\\n    >\\n        <$reveal\\n            state=<<folded-state>>\\n            type=\\\"nomatch\\\"\\n            text=\\\"hide\\\"\\n            animate=\\\"yes\\\"\\n        >\\n            <main style=\\\"width:100%;overflow:hidden;\\\"> \\n                <iframe id={{!!word}}\\n                    title={{!!word}}\\n                    height=\\\"700px\\\"\\n                    width=\\\"100%\\\"\\n                    src={{{[{!!word}encodeuricomponent[]addprefix[https://www.iciba.com/word?w=]]}}}\\n                    frameborder=0\\n                    seamless=\\\"seamless\\\"\\n                    style=\\\"margin:-130px 0 -60px 0;\\\"\\n                    marginheight=\\\"0\\\"\\n                    marginwidth=\\\"0\\\"\\n                />\\n            </main>\\n        </$reveal>\\n    </span>\"}, \"外研版初中英语八年级下册/20220118152142042862\": {\"title\": \"外研版初中英语八年级下册/20220118152142042862\", \"tags\": \"[[Module 1]] ?\", \"word\": \"smell\", \"created\": \"20220118152142042862\", \"caption\": \"{{||$:/plugins/oflg/fishing-cannedfish/外研版初中英语八年级下册/SearchWord}}\"}, \"外研版初中英语八年级下册/20220118152142042880\": {\"title\": \"外研版初中英语八年级下册/20220118152142042880\", \"tags\": \"[[Module 1]] ?\", \"word\": \"soft\", \"created\": \"20220118152142042880\", \"caption\": \"{{||$:/plugins/oflg/fishing-cannedfish/外研版初中英语八年级下册/SearchWord}}\"}, \"外研版初中英语八年级下册/20220118152142042885\": {\"title\": \"外研版初中英语八年级下册/20220118152142042885\", \"tags\": \"[[Module 1]] ?\", \"word\": \"sour\", \"created\": \"20220118152142042885\", \"caption\": \"{{||$:/plugins/oflg/fishing-cannedfish/外研版初中英语八年级下册/SearchWord}}\"}, \"外研版初中英语八年级下册/20220118152142042889\": {\"title\": \"外研版初中英语八年级下册/20220118152142042889\", \"tags\": \"[[Module 1]] ?\", \"word\": \"cookie\", \"created\": \"20220118152142042889\", \"caption\": \"{{||$:/plugins/oflg/fishing-cannedfish/外研版初中英语八年级下册/SearchWord}}\"}, \"外研版初中英语八年级下册/20220118152142042893\": {\"title\": \"外研版初中英语八年级下册/20220118152142042893\", \"tags\": \"[[Module 1]] ?\", \"word\": \"mm\", \"created\": \"20220118152142042893\", \"caption\": \"{{||$:/plugins/oflg/fishing-cannedfish/外研版初中英语八年级下册/SearchWord}}\"}, \"外研版初中英语八年级下册/20220118152142042896\": {\"title\": \"外研版初中英语八年级下册/20220118152142042896\", \"tags\": \"[[Module 1]] ?\", \"word\": \"pizza\", \"created\": \"20220118152142042896\", \"caption\": \"{{||$:/plugins/oflg/fishing-cannedfish/外研版初中英语八年级下册/SearchWord}}\"}, \"外研版初中英语八年级下册/20220118152142042900\": {\"title\": \"外研版初中英语八年级下册/20220118152142042900\", \"tags\": \"[[Module 1]] ?\", \"word\": \"lovely\", \"created\": \"20220118152142042900\", \"caption\": \"{{||$:/plugins/oflg/fishing-cannedfish/外研版初中英语八年级下册/SearchWord}}\"}, \"外研版初中英语八年级下册/20220118152142042904\": {\"title\": \"外研版初中英语八年级下册/20220118152142042904\", \"tags\": \"[[Module 1]] ?\", \"word\": \"done\", \"created\": \"20220118152142042904\", \"caption\": \"{{||$:/plugins/oflg/fishing-cannedfish/外研版初中英语八年级下册/SearchWord}}\"}, \"外研版初中英语八年级下册/20220118152142042908\": {\"title\": \"外研版初中英语八年级下册/20220118152142042908\", \"tags\": \"[[Module 1]] ?\", \"word\": \"try\", \"created\": \"20220118152142042908\", \"caption\": \"{{||$:/plugins/oflg/fishing-cannedfish/外研版初中英语八年级下册/SearchWord}}\"}, \"外研版初中英语八年级下册/20220118152142042912\": {\"title\": \"外研版初中英语八年级下册/20220118152142042912\", \"tags\": \"[[Module 1]] ?\", \"word\": \"have a try\", \"created\": \"20220118152142042912\", \"caption\": \"{{||$:/plugins/oflg/fishing-cannedfish/外研版初中英语八年级下册/SearchWord}}\"}, \"外研版初中英语八年级下册/20220118152142042915\": {\"title\": \"外研版初中英语八年级下册/20220118152142042915\", \"tags\": \"[[Module 1]] ?\", \"word\": \"pie\", \"created\": \"20220118152142042915\", \"caption\": \"{{||$:/plugins/oflg/fishing-cannedfish/外研版初中英语八年级下册/SearchWord}}\"}, \"外研版初中英语八年级下册/20220118152142042918\": {\"title\": \"外研版初中英语八年级下册/20220118152142042918\", \"tags\": \"[[Module 1]] ?\", \"word\": \"sound\", \"created\": \"20220118152142042918\", \"caption\": \"{{||$:/plugins/oflg/fishing-cannedfish/外研版初中英语八年级下册/SearchWord}}\"}, \"外研版初中英语八年级下册/20220118152142042922\": {\"title\": \"外研版初中英语八年级下册/20220118152142042922\", \"tags\": \"[[Module 1]] ?\", \"word\": \"sweet tooth\", \"created\": \"20220118152142042922\", \"caption\": \"{{||$:/plugins/oflg/fishing-cannedfish/外研版初中英语八年级下册/SearchWord}}\"}, \"外研版初中英语八年级下册/20220118152142042925\": {\"title\": \"外研版初中英语八年级下册/20220118152142042925\", \"tags\": \"[[Module 1]] ?\", \"word\": \"salt\", \"created\": \"20220118152142042925\", \"caption\": \"{{||$:/plugins/oflg/fishing-cannedfish/外研版初中英语八年级下册/SearchWord}}\"}, \"外研版初中英语八年级下册/20220118152142042928\": {\"title\": \"外研版初中英语八年级下册/20220118152142042928\", \"tags\": \"[[Module 1]] ?\", \"word\": \"jam\", \"created\": \"20220118152142042928\", \"caption\": \"{{||$:/plugins/oflg/fishing-cannedfish/外研版初中英语八年级下册/SearchWord}}\"}, \"外研版初中英语八年级下册/20220118152142042932\": {\"title\": \"外研版初中英语八年级下册/20220118152142042932\", \"tags\": \"[[Module 1]] ?\", \"word\": \"for\", \"created\": \"20220118152142042932\", \"caption\": \"{{||$:/plugins/oflg/fishing-cannedfish/外研版初中英语八年级下册/SearchWord}}\"}, \"外研版初中英语八年级下册/20220118152142042935\": {\"title\": \"外研版初中英语八年级下册/20220118152142042935\", \"tags\": \"[[Module 1]] ?\", \"word\": \"favourite\", \"created\": \"20220118152142042935\", \"caption\": \"{{||$:/plugins/oflg/fishing-cannedfish/外研版初中英语八年级下册/SearchWord}}\"}, \"外研版初中英语八年级下册/20220118152142042939\": {\"title\": \"外研版初中英语八年级下册/20220118152142042939\", \"tags\": \"[[Module 1]] ?\", \"word\": \"ear\", \"created\": \"20220118152142042939\", \"caption\": \"{{||$:/plugins/oflg/fishing-cannedfish/外研版初中英语八年级下册/SearchWord}}\"}, \"外研版初中英语八年级下册/20220118152142042942\": {\"title\": \"外研版初中英语八年级下册/20220118152142042942\", \"tags\": \"[[Module 1]] ?\", \"word\": \"glasses\", \"created\": \"20220118152142042942\", \"caption\": \"{{||$:/plugins/oflg/fishing-cannedfish/外研版初中英语八年级下册/SearchWord}}\"}, \"外研版初中英语八年级下册/20220118152142042947\": {\"title\": \"外研版初中英语八年级下册/20220118152142042947\", \"tags\": \"[[Module 1]] ?\", \"word\": \"jeans\", \"created\": \"20220118152142042947\", \"caption\": \"{{||$:/plugins/oflg/fishing-cannedfish/外研版初中英语八年级下册/SearchWord}}\"}, \"外研版初中英语八年级下册/20220118152142042950\": {\"title\": \"外研版初中英语八年级下册/20220118152142042950\", \"tags\": \"[[Module 1]] ?\", \"word\": \"nervous\", \"created\": \"20220118152142042950\", \"caption\": \"{{||$:/plugins/oflg/fishing-cannedfish/外研版初中英语八年级下册/SearchWord}}\"}, \"外研版初中英语八年级下册/20220118152142042954\": {\"title\": \"外研版初中英语八年级下册/20220118152142042954\", \"tags\": \"[[Module 1]] ?\", \"word\": \"fair\", \"created\": \"20220118152142042954\", \"caption\": \"{{||$:/plugins/oflg/fishing-cannedfish/外研版初中英语八年级下册/SearchWord}}\"}, \"外研版初中英语八年级下册/20220118152142042957\": {\"title\": \"外研版初中英语八年级下册/20220118152142042957\", \"tags\": \"[[Module 1]] ?\", \"word\": \"pretty\", \"created\": \"20220118152142042957\", \"caption\": \"{{||$:/plugins/oflg/fishing-cannedfish/外研版初中英语八年级下册/SearchWord}}\"}, \"外研版初中英语八年级下册/20220118152142042960\": {\"title\": \"外研版初中英语八年级下册/20220118152142042960\", \"tags\": \"[[Module 1]] ?\", \"word\": \"proud\", \"created\": \"20220118152142042960\", \"caption\": \"{{||$:/plugins/oflg/fishing-cannedfish/外研版初中英语八年级下册/SearchWord}}\"}, \"外研版初中英语八年级下册/20220118152142042964\": {\"title\": \"外研版初中英语八年级下册/20220118152142042964\", \"tags\": \"[[Module 1]] ?\", \"word\": \"be proud of ...\", \"created\": \"20220118152142042964\", \"caption\": \"{{||$:/plugins/oflg/fishing-cannedfish/外研版初中英语八年级下册/SearchWord}}\"}, \"外研版初中英语八年级下册/20220118152142042967\": {\"title\": \"外研版初中英语八年级下册/20220118152142042967\", \"tags\": \"[[Module 1]] ?\", \"word\": \"stranger\", \"created\": \"20220118152142042967\", \"caption\": \"{{||$:/plugins/oflg/fishing-cannedfish/外研版初中英语八年级下册/SearchWord}}\"}, \"外研版初中英语八年级下册/20220118152142042970\": {\"title\": \"外研版初中英语八年级下册/20220118152142042970\", \"tags\": \"[[Module 1]] ?\", \"word\": \"message\", \"created\": \"20220118152142042970\", \"caption\": \"{{||$:/plugins/oflg/fishing-cannedfish/外研版初中英语八年级下册/SearchWord}}\"}, \"外研版初中英语八年级下册/20220118152142042973\": {\"title\": \"外研版初中英语八年级下册/20220118152142042973\", \"tags\": \"[[Module 1]] ?\", \"word\": \"sb. can't wait\", \"created\": \"20220118152142042973\", \"caption\": \"{{||$:/plugins/oflg/fishing-cannedfish/外研版初中英语八年级下册/SearchWord}}\"}, \"外研版初中英语八年级下册/20220118152142042977\": {\"title\": \"外研版初中英语八年级下册/20220118152142042977\", \"tags\": \"[[Module 1]] ?\", \"word\": \"hobby\", \"created\": \"20220118152142042977\", \"caption\": \"{{||$:/plugins/oflg/fishing-cannedfish/外研版初中英语八年级下册/SearchWord}}\"}, \"外研版初中英语八年级下册/20220118152142042980\": {\"title\": \"外研版初中英语八年级下册/20220118152142042980\", \"tags\": \"[[Module 1]] ?\", \"word\": \"at school\", \"created\": \"20220118152142042980\", \"caption\": \"{{||$:/plugins/oflg/fishing-cannedfish/外研版初中英语八年级下册/SearchWord}}\"}, \"外研版初中英语八年级下册/20220118152142042983\": {\"title\": \"外研版初中英语八年级下册/20220118152142042983\", \"tags\": \"[[Module 1]] ?\", \"word\": \"in\", \"created\": \"20220118152142042983\", \"caption\": \"{{||$:/plugins/oflg/fishing-cannedfish/外研版初中英语八年级下册/SearchWord}}\"}, \"外研版初中英语八年级下册/20220118152142042987\": {\"title\": \"外研版初中英语八年级下册/20220118152142042987\", \"tags\": \"[[Module 1]] ?\", \"word\": \"mark\", \"created\": \"20220118152142042987\", \"caption\": \"{{||$:/plugins/oflg/fishing-cannedfish/外研版初中英语八年级下册/SearchWord}}\"}, \"外研版初中英语八年级下册/20220118152142042990\": {\"title\": \"外研版初中英语八年级下册/20220118152142042990\", \"tags\": \"[[Module 1]] ?\", \"word\": \"love\", \"created\": \"20220118152142042990\", \"caption\": \"{{||$:/plugins/oflg/fishing-cannedfish/外研版初中英语八年级下册/SearchWord}}\"}, \"外研版初中英语八年级下册/20220118152142042994\": {\"title\": \"外研版初中英语八年级下册/20220118152142042994\", \"tags\": \"[[Module 2]] ?\", \"word\": \"ever\", \"created\": \"20220118152142042994\", \"caption\": \"{{||$:/plugins/oflg/fishing-cannedfish/外研版初中英语八年级下册/SearchWord}}\"}, \"外研版初中英语八年级下册/20220118152142042997\": {\"title\": \"外研版初中英语八年级下册/20220118152142042997\", \"tags\": \"[[Module 2]] ?\", \"word\": \"enter\", \"created\": \"20220118152142042997\", \"caption\": \"{{||$:/plugins/oflg/fishing-cannedfish/外研版初中英语八年级下册/SearchWord}}\"}, \"外研版初中英语八年级下册/20220118152142043000\": {\"title\": \"外研版初中英语八年级下册/20220118152142043000\", \"tags\": \"[[Module 2]] ?\", \"word\": \"competition\", \"created\": \"20220118152142043000\", \"caption\": \"{{||$:/plugins/oflg/fishing-cannedfish/外研版初中英语八年级下册/SearchWord}}\"}, \"外研版初中英语八年级下册/20220118152142043004\": {\"title\": \"外研版初中英语八年级下册/20220118152142043004\", \"tags\": \"[[Module 2]] ?\", \"word\": \"prize\", \"created\": \"20220118152142043004\", \"caption\": \"{{||$:/plugins/oflg/fishing-cannedfish/外研版初中英语八年级下册/SearchWord}}\"}, \"外研版初中英语八年级下册/20220118152142043007\": {\"title\": \"外研版初中英语八年级下册/20220118152142043007\", \"tags\": \"[[Module 2]] ?\", \"word\": \"first prize\", \"created\": \"20220118152142043007\", \"caption\": \"{{||$:/plugins/oflg/fishing-cannedfish/外研版初中英语八年级下册/SearchWord}}\"}, \"外研版初中英语八年级下册/20220118152142043011\": {\"title\": \"外研版初中英语八年级下册/20220118152142043011\", \"tags\": \"[[Module 2]] ?\", \"word\": \"dream\", \"created\": \"20220118152142043011\", \"caption\": \"{{||$:/plugins/oflg/fishing-cannedfish/外研版初中英语八年级下册/SearchWord}}\"}, \"外研版初中英语八年级下册/20220118152142043014\": {\"title\": \"外研版初中英语八年级下册/20220118152142043014\", \"tags\": \"[[Module 2]] ?\", \"word\": \"afford\", \"created\": \"20220118152142043014\", \"caption\": \"{{||$:/plugins/oflg/fishing-cannedfish/外研版初中英语八年级下册/SearchWord}}\"}, \"外研版初中英语八年级下册/20220118152142043018\": {\"title\": \"外研版初中英语八年级下册/20220118152142043018\", \"tags\": \"[[Module 2]] ?\", \"word\": \"write about\", \"created\": \"20220118152142043018\", \"caption\": \"{{||$:/plugins/oflg/fishing-cannedfish/外研版初中英语八年级下册/SearchWord}}\"}, \"外研版初中英语八年级下册/20220118152142043022\": {\"title\": \"外研版初中英语八年级下册/20220118152142043022\", \"tags\": \"[[Module 2]] ?\", \"word\": \"make up\", \"created\": \"20220118152142043022\", \"caption\": \"{{||$:/plugins/oflg/fishing-cannedfish/外研版初中英语八年级下册/SearchWord}}\"}, \"外研版初中英语八年级下册/20220118152142043025\": {\"title\": \"外研版初中英语八年级下册/20220118152142043025\", \"tags\": \"[[Module 2]] ?\", \"word\": \"invite\", \"created\": \"20220118152142043025\", \"caption\": \"{{||$:/plugins/oflg/fishing-cannedfish/外研版初中英语八年级下册/SearchWord}}\"}, \"外研版初中英语八年级下册/20220118152142043029\": {\"title\": \"外研版初中英语八年级下册/20220118152142043029\", \"tags\": \"[[Module 2]] ?\", \"word\": \"move\", \"created\": \"20220118152142043029\", \"caption\": \"{{||$:/plugins/oflg/fishing-cannedfish/外研版初中英语八年级下册/SearchWord}}\"}, \"外研版初中英语八年级下册/20220118152142043032\": {\"title\": \"外研版初中英语八年级下册/20220118152142043032\", \"tags\": \"[[Module 2]] ?\", \"word\": \"send\", \"created\": \"20220118152142043032\", \"caption\": \"{{||$:/plugins/oflg/fishing-cannedfish/外研版初中英语八年级下册/SearchWord}}\"}, \"外研版初中英语八年级下册/20220118152142043035\": {\"title\": \"外研版初中英语八年级下册/20220118152142043035\", \"tags\": \"[[Module 2]] ?\", \"word\": \"Germany\", \"created\": \"20220118152142043035\", \"caption\": \"{{||$:/plugins/oflg/fishing-cannedfish/外研版初中英语八年级下册/SearchWord}}\"}, \"外研版初中英语八年级下册/20220118152142043039\": {\"title\": \"外研版初中英语八年级下册/20220118152142043039\", \"tags\": \"[[Module 2]] ?\", \"word\": \"France\", \"created\": \"20220118152142043039\", \"caption\": \"{{||$:/plugins/oflg/fishing-cannedfish/外研版初中英语八年级下册/SearchWord}}\"}, \"外研版初中英语八年级下册/20220118152142043042\": {\"title\": \"外研版初中英语八年级下册/20220118152142043042\", \"tags\": \"[[Module 2]] ?\", \"word\": \"tower\", \"created\": \"20220118152142043042\", \"caption\": \"{{||$:/plugins/oflg/fishing-cannedfish/外研版初中英语八年级下册/SearchWord}}\"}, \"外研版初中英语八年级下册/20220118152142043045\": {\"title\": \"外研版初中英语八年级下册/20220118152142043045\", \"tags\": \"[[Module 2]] ?\", \"word\": \"ancient\", \"created\": \"20220118152142043045\", \"caption\": \"{{||$:/plugins/oflg/fishing-cannedfish/外研版初中英语八年级下册/SearchWord}}\"}, \"外研版初中英语八年级下册/20220118152142043049\": {\"title\": \"外研版初中英语八年级下册/20220118152142043049\", \"tags\": \"[[Module 2]] ?\", \"word\": \"king\", \"created\": \"20220118152142043049\", \"caption\": \"{{||$:/plugins/oflg/fishing-cannedfish/外研版初中英语八年级下册/SearchWord}}\"}, \"外研版初中英语八年级下册/20220118152142043052\": {\"title\": \"外研版初中英语八年级下册/20220118152142043052\", \"tags\": \"[[Module 2]] ?\", \"word\": \"queen\", \"created\": \"20220118152142043052\", \"caption\": \"{{||$:/plugins/oflg/fishing-cannedfish/外研版初中英语八年级下册/SearchWord}}\"}, \"外研版初中英语八年级下册/20220118152142043055\": {\"title\": \"外研版初中英语八年级下册/20220118152142043055\", \"tags\": \"[[Module 2]] ?\", \"word\": \"Arabic\", \"created\": \"20220118152142043055\", \"caption\": \"{{||$:/plugins/oflg/fishing-cannedfish/外研版初中英语八年级下册/SearchWord}}\"}, \"外研版初中英语八年级下册/20220118152142043059\": {\"title\": \"外研版初中英语八年级下册/20220118152142043059\", \"tags\": \"[[Module 2]] ?\", \"word\": \"way\", \"created\": \"20220118152142043059\", \"caption\": \"{{||$:/plugins/oflg/fishing-cannedfish/外研版初中英语八年级下册/SearchWord}}\"}, \"外研版初中英语八年级下册/20220118152142043062\": {\"title\": \"外研版初中英语八年级下册/20220118152142043062\", \"tags\": \"[[Module 2]] ?\", \"word\": \"mix\", \"created\": \"20220118152142043062\", \"caption\": \"{{||$:/plugins/oflg/fishing-cannedfish/外研版初中英语八年级下册/SearchWord}}\"}, \"外研版初中英语八年级下册/20220118152142043065\": {\"title\": \"外研版初中英语八年级下册/20220118152142043065\", \"tags\": \"[[Module 2]] ?\", \"word\": \"miss\", \"created\": \"20220118152142043065\", \"caption\": \"{{||$:/plugins/oflg/fishing-cannedfish/外研版初中英语八年级下册/SearchWord}}\"}, \"外研版初中英语八年级下册/20220118152142043069\": {\"title\": \"外研版初中英语八年级下册/20220118152142043069\", \"tags\": \"[[Module 2]] ?\", \"word\": \"count\", \"created\": \"20220118152142043069\", \"caption\": \"{{||$:/plugins/oflg/fishing-cannedfish/外研版初中英语八年级下册/SearchWord}}\"}, \"外研版初中英语八年级下册/20220118152142043072\": {\"title\": \"外研版初中英语八年级下册/20220118152142043072\", \"tags\": \"[[Module 2]] ?\", \"word\": \"count down\", \"created\": \"20220118152142043072\", \"caption\": \"{{||$:/plugins/oflg/fishing-cannedfish/外研版初中英语八年级下册/SearchWord}}\"}, \"外研版初中英语八年级下册/20220118152142043076\": {\"title\": \"外研版初中英语八年级下册/20220118152142043076\", \"tags\": \"[[Module 3]] ?\", \"word\": \"earth\", \"created\": \"20220118152142043076\", \"caption\": \"{{||$:/plugins/oflg/fishing-cannedfish/外研版初中英语八年级下册/SearchWord}}\"}, \"外研版初中英语八年级下册/20220118152142043079\": {\"title\": \"外研版初中英语八年级下册/20220118152142043079\", \"tags\": \"[[Module 3]] ?\", \"word\": \"moon\", \"created\": \"20220118152142043079\", \"caption\": \"{{||$:/plugins/oflg/fishing-cannedfish/外研版初中英语八年级下册/SearchWord}}\"}, \"外研版初中英语八年级下册/20220118152142043083\": {\"title\": \"外研版初中英语八年级下册/20220118152142043083\", \"tags\": \"[[Module 3]] ?\", \"word\": \"news\", \"created\": \"20220118152142043083\", \"caption\": \"{{||$:/plugins/oflg/fishing-cannedfish/外研版初中英语八年级下册/SearchWord}}\"}, \"外研版初中英语八年级下册/20220118152142043087\": {\"title\": \"外研版初中英语八年级下册/20220118152142043087\", \"tags\": \"[[Module 3]] ?\", \"word\": \"planet\", \"created\": \"20220118152142043087\", \"caption\": \"{{||$:/plugins/oflg/fishing-cannedfish/外研版初中英语八年级下册/SearchWord}}\"}, \"外研版初中英语八年级下册/20220118152142043090\": {\"title\": \"外研版初中英语八年级下册/20220118152142043090\", \"tags\": \"[[Module 3]] ?\", \"word\": \"reach\", \"created\": \"20220118152142043090\", \"caption\": \"{{||$:/plugins/oflg/fishing-cannedfish/外研版初中英语八年级下册/SearchWord}}\"}, \"外研版初中英语八年级下册/20220118152142043093\": {\"title\": \"外研版初中英语八年级下册/20220118152142043093\", \"tags\": \"[[Module 3]] ?\", \"word\": \"yet\", \"created\": \"20220118152142043093\", \"caption\": \"{{||$:/plugins/oflg/fishing-cannedfish/外研版初中英语八年级下册/SearchWord}}\"}, \"外研版初中英语八年级下册/20220118152142043096\": {\"title\": \"外研版初中英语八年级下册/20220118152142043096\", \"tags\": \"[[Module 3]] ?\", \"word\": \"just\", \"created\": \"20220118152142043096\", \"caption\": \"{{||$:/plugins/oflg/fishing-cannedfish/外研版初中英语八年级下册/SearchWord}}\"}, \"外研版初中英语八年级下册/20220118152142043100\": {\"title\": \"外研版初中英语八年级下册/20220118152142043100\", \"tags\": \"[[Module 3]] ?\", \"word\": \"model\", \"created\": \"20220118152142043100\", \"caption\": \"{{||$:/plugins/oflg/fishing-cannedfish/外研版初中英语八年级下册/SearchWord}}\"}, \"外研版初中英语八年级下册/20220118152142043103\": {\"title\": \"外研版初中英语八年级下册/20220118152142043103\", \"tags\": \"[[Module 3]] ?\", \"word\": \"spaceship\", \"created\": \"20220118152142043103\", \"caption\": \"{{||$:/plugins/oflg/fishing-cannedfish/外研版初中英语八年级下册/SearchWord}}\"}, \"外研版初中英语八年级下册/20220118152142043107\": {\"title\": \"外研版初中英语八年级下册/20220118152142043107\", \"tags\": \"[[Module 3]] ?\", \"word\": \"project\", \"created\": \"20220118152142043107\", \"caption\": \"{{||$:/plugins/oflg/fishing-cannedfish/外研版初中英语八年级下册/SearchWord}}\"}, \"外研版初中英语八年级下册/20220118152142043110\": {\"title\": \"外研版初中英语八年级下册/20220118152142043110\", \"tags\": \"[[Module 3]] ?\", \"word\": \"no problem\", \"created\": \"20220118152142043110\", \"caption\": \"{{||$:/plugins/oflg/fishing-cannedfish/外研版初中英语八年级下册/SearchWord}}\"}, \"外研版初中英语八年级下册/20220118152142043113\": {\"title\": \"外研版初中英语八年级下册/20220118152142043113\", \"tags\": \"[[Module 3]] ?\", \"word\": \"latest\", \"created\": \"20220118152142043113\", \"caption\": \"{{||$:/plugins/oflg/fishing-cannedfish/外研版初中英语八年级下册/SearchWord}}\"}, \"外研版初中英语八年级下册/20220118152142043116\": {\"title\": \"外研版初中英语八年级下册/20220118152142043116\", \"tags\": \"[[Module 3]] ?\", \"word\": \"on\", \"created\": \"20220118152142043116\", \"caption\": \"{{||$:/plugins/oflg/fishing-cannedfish/外研版初中英语八年级下册/SearchWord}}\"}, \"外研版初中英语八年级下册/20220118152142043120\": {\"title\": \"外研版初中英语八年级下册/20220118152142043120\", \"tags\": \"[[Module 3]] ?\", \"word\": \"discover\", \"created\": \"20220118152142043120\", \"caption\": \"{{||$:/plugins/oflg/fishing-cannedfish/外研版初中英语八年级下册/SearchWord}}\"}, \"外研版初中英语八年级下册/20220118152142043123\": {\"title\": \"外研版初中英语八年级下册/20220118152142043123\", \"tags\": \"[[Module 3]] ?\", \"word\": \"astronaut\", \"created\": \"20220118152142043123\", \"caption\": \"{{||$:/plugins/oflg/fishing-cannedfish/外研版初中英语八年级下册/SearchWord}}\"}, \"外研版初中英语八年级下册/20220118152142043126\": {\"title\": \"外研版初中英语八年级下册/20220118152142043126\", \"tags\": \"[[Module 3]] ?\", \"word\": \"space travel\", \"created\": \"20220118152142043126\", \"caption\": \"{{||$:/plugins/oflg/fishing-cannedfish/外研版初中英语八年级下册/SearchWord}}\"}, \"外研版初中英语八年级下册/20220118152142043130\": {\"title\": \"外研版初中英语八年级下册/20220118152142043130\", \"tags\": \"[[Module 3]] ?\", \"word\": \"none\", \"created\": \"20220118152142043130\", \"caption\": \"{{||$:/plugins/oflg/fishing-cannedfish/外研版初中英语八年级下册/SearchWord}}\"}, \"外研版初中英语八年级下册/20220118152142043133\": {\"title\": \"外研版初中英语八年级下册/20220118152142043133\", \"tags\": \"[[Module 3]] ?\", \"word\": \"environment\", \"created\": \"20220118152142043133\", \"caption\": \"{{||$:/plugins/oflg/fishing-cannedfish/外研版初中英语八年级下册/SearchWord}}\"}, \"外研版初中英语八年级下册/20220118152142043136\": {\"title\": \"外研版初中英语八年级下册/20220118152142043136\", \"tags\": \"[[Module 3]] ?\", \"word\": \"that\", \"created\": \"20220118152142043136\", \"caption\": \"{{||$:/plugins/oflg/fishing-cannedfish/外研版初中英语八年级下册/SearchWord}}\"}, \"外研版初中英语八年级下册/20220118152142043140\": {\"title\": \"外研版初中英语八年级下册/20220118152142043140\", \"tags\": \"[[Module 3]] ?\", \"word\": \"solar\", \"created\": \"20220118152142043140\", \"caption\": \"{{||$:/plugins/oflg/fishing-cannedfish/外研版初中英语八年级下册/SearchWord}}\"}, \"外研版初中英语八年级下册/20220118152142043143\": {\"title\": \"外研版初中英语八年级下册/20220118152142043143\", \"tags\": \"[[Module 3]] ?\", \"word\": \"system\", \"created\": \"20220118152142043143\", \"caption\": \"{{||$:/plugins/oflg/fishing-cannedfish/外研版初中英语八年级下册/SearchWord}}\"}, \"外研版初中英语八年级下册/20220118152142043146\": {\"title\": \"外研版初中英语八年级下册/20220118152142043146\", \"tags\": \"[[Module 3]] ?\", \"word\": \"solar system\", \"created\": \"20220118152142043146\", \"caption\": \"{{||$:/plugins/oflg/fishing-cannedfish/外研版初中英语八年级下册/SearchWord}}\"}, \"外研版初中英语八年级下册/20220118152142043150\": {\"title\": \"外研版初中英语八年级下册/20220118152142043150\", \"tags\": \"[[Module 3]] ?\", \"word\": \"group\", \"created\": \"20220118152142043150\", \"caption\": \"{{||$:/plugins/oflg/fishing-cannedfish/外研版初中英语八年级下册/SearchWord}}\"}, \"外研版初中英语八年级下册/20220118152142043153\": {\"title\": \"外研版初中英语八年级下册/20220118152142043153\", \"tags\": \"[[Module 3]] ?\", \"word\": \"galaxy\", \"created\": \"20220118152142043153\", \"caption\": \"{{||$:/plugins/oflg/fishing-cannedfish/外研版初中英语八年级下册/SearchWord}}\"}, \"外研版初中英语八年级下册/20220118152142043156\": {\"title\": \"外研版初中英语八年级下册/20220118152142043156\", \"tags\": \"[[Module 3]] ?\", \"word\": \"universe\", \"created\": \"20220118152142043156\", \"caption\": \"{{||$:/plugins/oflg/fishing-cannedfish/外研版初中英语八年级下册/SearchWord}}\"}, \"外研版初中英语八年级下册/20220118152142043159\": {\"title\": \"外研版初中英语八年级下册/20220118152142043159\", \"tags\": \"[[Module 3]] ?\", \"word\": \"light\", \"created\": \"20220118152142043159\", \"caption\": \"{{||$:/plugins/oflg/fishing-cannedfish/外研版初中英语八年级下册/SearchWord}}\"}, \"外研版初中英语八年级下册/20220118152142043164\": {\"title\": \"外研版初中英语八年级下册/20220118152142043164\", \"tags\": \"[[Module 3]] ?\", \"word\": \"impossible\", \"created\": \"20220118152142043164\", \"caption\": \"{{||$:/plugins/oflg/fishing-cannedfish/外研版初中英语八年级下册/SearchWord}}\"}, \"外研版初中英语八年级下册/20220118152142043168\": {\"title\": \"外研版初中英语八年级下册/20220118152142043168\", \"tags\": \"[[Module 3]] ?\", \"word\": \"out\", \"created\": \"20220118152142043168\", \"caption\": \"{{||$:/plugins/oflg/fishing-cannedfish/外研版初中英语八年级下册/SearchWord}}\"}, \"外研版初中英语八年级下册/20220118152142043171\": {\"title\": \"外研版初中英语八年级下册/20220118152142043171\", \"tags\": \"[[Module 3]] ?\", \"word\": \"communicate\", \"created\": \"20220118152142043171\", \"caption\": \"{{||$:/plugins/oflg/fishing-cannedfish/外研版初中英语八年级下册/SearchWord}}\"}, \"外研版初中英语八年级下册/20220118152142043175\": {\"title\": \"外研版初中英语八年级下册/20220118152142043175\", \"tags\": \"[[Module 4]] ?\", \"word\": \"cough\", \"created\": \"20220118152142043175\", \"caption\": \"{{||$:/plugins/oflg/fishing-cannedfish/外研版初中英语八年级下册/SearchWord}}\"}, \"外研版初中英语八年级下册/20220118152142043178\": {\"title\": \"外研版初中英语八年级下册/20220118152142043178\", \"tags\": \"[[Module 4]] ?\", \"word\": \"fever\", \"created\": \"20220118152142043178\", \"caption\": \"{{||$:/plugins/oflg/fishing-cannedfish/外研版初中英语八年级下册/SearchWord}}\"}, \"外研版初中英语八年级下册/20220118152142043181\": {\"title\": \"外研版初中英语八年级下册/20220118152142043181\", \"tags\": \"[[Module 4]] ?\", \"word\": \"headache\", \"created\": \"20220118152142043181\", \"caption\": \"{{||$:/plugins/oflg/fishing-cannedfish/外研版初中英语八年级下册/SearchWord}}\"}, \"外研版初中英语八年级下册/20220118152142043185\": {\"title\": \"外研版初中英语八年级下册/20220118152142043185\", \"tags\": \"[[Module 4]] ?\", \"word\": \"stomach\", \"created\": \"20220118152142043185\", \"caption\": \"{{||$:/plugins/oflg/fishing-cannedfish/外研版初中英语八年级下册/SearchWord}}\"}, \"外研版初中英语八年级下册/20220118152142043188\": {\"title\": \"外研版初中英语八年级下册/20220118152142043188\", \"tags\": \"[[Module 4]] ?\", \"word\": \"ache\", \"created\": \"20220118152142043188\", \"caption\": \"{{||$:/plugins/oflg/fishing-cannedfish/外研版初中英语八年级下册/SearchWord}}\"}, \"外研版初中英语八年级下册/20220118152142043191\": {\"title\": \"外研版初中英语八年级下册/20220118152142043191\", \"tags\": \"[[Module 4]] ?\", \"word\": \"stomach ache\", \"created\": \"20220118152142043191\", \"caption\": \"{{||$:/plugins/oflg/fishing-cannedfish/外研版初中英语八年级下册/SearchWord}}\"}, \"外研版初中英语八年级下册/20220118152142043195\": {\"title\": \"外研版初中英语八年级下册/20220118152142043195\", \"tags\": \"[[Module 4]] ?\", \"word\": \"toothache\", \"created\": \"20220118152142043195\", \"caption\": \"{{||$:/plugins/oflg/fishing-cannedfish/外研版初中英语八年级下册/SearchWord}}\"}, \"外研版初中英语八年级下册/20220118152142043198\": {\"title\": \"外研版初中英语八年级下册/20220118152142043198\", \"tags\": \"[[Module 4]] ?\", \"word\": \"ill\", \"created\": \"20220118152142043198\", \"caption\": \"{{||$:/plugins/oflg/fishing-cannedfish/外研版初中英语八年级下册/SearchWord}}\"}, \"外研版初中英语八年级下册/20220118152142043201\": {\"title\": \"外研版初中英语八年级下册/20220118152142043201\", \"tags\": \"[[Module 4]] ?\", \"word\": \"this\", \"created\": \"20220118152142043201\", \"caption\": \"{{||$:/plugins/oflg/fishing-cannedfish/外研版初中英语八年级下册/SearchWord}}\"}, \"外研版初中英语八年级下册/20220118152142043204\": {\"title\": \"外研版初中英语八年级下册/20220118152142043204\", \"tags\": \"[[Module 4]] ?\", \"word\": \"since\", \"created\": \"20220118152142043204\", \"caption\": \"{{||$:/plugins/oflg/fishing-cannedfish/外研版初中英语八年级下册/SearchWord}}\"}, \"外研版初中英语八年级下册/20220118152142043208\": {\"title\": \"外研版初中英语八年级下册/20220118152142043208\", \"tags\": \"[[Module 4]] ?\", \"word\": \"cold\", \"created\": \"20220118152142043208\", \"caption\": \"{{||$:/plugins/oflg/fishing-cannedfish/外研版初中英语八年级下册/SearchWord}}\"}, \"外研版初中英语八年级下册/20220118152142043211\": {\"title\": \"外研版初中英语八年级下册/20220118152142043211\", \"tags\": \"[[Module 4]] ?\", \"word\": \"catch a cold\", \"created\": \"20220118152142043211\", \"caption\": \"{{||$:/plugins/oflg/fishing-cannedfish/外研版初中英语八年级下册/SearchWord}}\"}, \"外研版初中英语八年级下册/20220118152142043214\": {\"title\": \"外研版初中英语八年级下册/20220118152142043214\", \"tags\": \"[[Module 4]] ?\", \"word\": \"take\", \"created\": \"20220118152142043214\", \"caption\": \"{{||$:/plugins/oflg/fishing-cannedfish/外研版初中英语八年级下册/SearchWord}}\"}, \"外研版初中英语八年级下册/20220118152142043217\": {\"title\": \"外研版初中英语八年级下册/20220118152142043217\", \"tags\": \"[[Module 4]] ?\", \"word\": \"take sb.'s temperature\", \"created\": \"20220118152142043217\", \"caption\": \"{{||$:/plugins/oflg/fishing-cannedfish/外研版初中英语八年级下册/SearchWord}}\"}, \"外研版初中英语八年级下册/20220118152142043220\": {\"title\": \"外研版初中英语八年级下册/20220118152142043220\", \"tags\": \"[[Module 4]] ?\", \"word\": \"fast food\", \"created\": \"20220118152142043220\", \"caption\": \"{{||$:/plugins/oflg/fishing-cannedfish/外研版初中英语八年级下册/SearchWord}}\"}, \"外研版初中英语八年级下册/20220118152142043224\": {\"title\": \"外研版初中英语八年级下册/20220118152142043224\", \"tags\": \"[[Module 4]] ?\", \"word\": \"health\", \"created\": \"20220118152142043224\", \"caption\": \"{{||$:/plugins/oflg/fishing-cannedfish/外研版初中英语八年级下册/SearchWord}}\"}, \"外研版初中英语八年级下册/20220118152142043227\": {\"title\": \"外研版初中英语八年级下册/20220118152142043227\", \"tags\": \"[[Module 4]] ?\", \"word\": \"well\", \"created\": \"20220118152142043227\", \"caption\": \"{{||$:/plugins/oflg/fishing-cannedfish/外研版初中英语八年级下册/SearchWord}}\"}, \"外研版初中英语八年级下册/20220118152142043231\": {\"title\": \"外研版初中英语八年级下册/20220118152142043231\", \"tags\": \"[[Module 4]] ?\", \"word\": \"heart\", \"created\": \"20220118152142043231\", \"caption\": \"{{||$:/plugins/oflg/fishing-cannedfish/外研版初中英语八年级下册/SearchWord}}\"}, \"外研版初中英语八年级下册/20220118152142043234\": {\"title\": \"外研版初中英语八年级下册/20220118152142043234\", \"tags\": \"[[Module 4]] ?\", \"word\": \"active\", \"created\": \"20220118152142043234\", \"caption\": \"{{||$:/plugins/oflg/fishing-cannedfish/外研版初中英语八年级下册/SearchWord}}\"}, \"外研版初中英语八年级下册/20220118152142043237\": {\"title\": \"外研版初中英语八年级下册/20220118152142043237\", \"tags\": \"[[Module 4]] ?\", \"word\": \"pet\", \"created\": \"20220118152142043237\", \"caption\": \"{{||$:/plugins/oflg/fishing-cannedfish/外研版初中英语八年级下册/SearchWord}}\"}, \"外研版初中英语八年级下册/20220118152142043240\": {\"title\": \"外研版初中英语八年级下册/20220118152142043240\", \"tags\": \"[[Module 4]] ?\", \"word\": \"member\", \"created\": \"20220118152142043240\", \"caption\": \"{{||$:/plugins/oflg/fishing-cannedfish/外研版初中英语八年级下册/SearchWord}}\"}, \"外研版初中英语八年级下册/20220118152142043243\": {\"title\": \"外研版初中英语八年级下册/20220118152142043243\", \"tags\": \"[[Module 4]] ?\", \"word\": \"take part\", \"created\": \"20220118152142043243\", \"caption\": \"{{||$:/plugins/oflg/fishing-cannedfish/外研版初中英语八年级下册/SearchWord}}\"}, \"外研版初中英语八年级下册/20220118152142043247\": {\"title\": \"外研版初中英语八年级下册/20220118152142043247\", \"tags\": \"[[Module 4]] ?\", \"word\": \"take part in sth.\", \"created\": \"20220118152142043247\", \"caption\": \"{{||$:/plugins/oflg/fishing-cannedfish/外研版初中英语八年级下册/SearchWord}}\"}, \"外研版初中英语八年级下册/20220118152142043250\": {\"title\": \"外研版初中英语八年级下册/20220118152142043250\", \"tags\": \"[[Module 4]] ?\", \"word\": \"condition\", \"created\": \"20220118152142043250\", \"caption\": \"{{||$:/plugins/oflg/fishing-cannedfish/外研版初中英语八年级下册/SearchWord}}\"}, \"外研版初中英语八年级下册/20220118152142043253\": {\"title\": \"外研版初中英语八年级下册/20220118152142043253\", \"tags\": \"[[Module 4]] ?\", \"word\": \"in excellent condition\", \"created\": \"20220118152142043253\", \"caption\": \"{{||$:/plugins/oflg/fishing-cannedfish/外研版初中英语八年级下册/SearchWord}}\"}, \"外研版初中英语八年级下册/20220118152142043256\": {\"title\": \"外研版初中英语八年级下册/20220118152142043256\", \"tags\": \"[[Module 4]] ?\", \"word\": \"sleepy\", \"created\": \"20220118152142043256\", \"caption\": \"{{||$:/plugins/oflg/fishing-cannedfish/外研版初中英语八年级下册/SearchWord}}\"}, \"外研版初中英语八年级下册/20220118152142043259\": {\"title\": \"外研版初中英语八年级下册/20220118152142043259\", \"tags\": \"[[Module 4]] ?\", \"word\": \"then\", \"created\": \"20220118152142043259\", \"caption\": \"{{||$:/plugins/oflg/fishing-cannedfish/外研版初中英语八年级下册/SearchWord}}\"}, \"外研版初中英语八年级下册/20220118152142043262\": {\"title\": \"外研版初中英语八年级下册/20220118152142043262\", \"tags\": \"[[Module 4]] ?\", \"word\": \"daily\", \"created\": \"20220118152142043262\", \"caption\": \"{{||$:/plugins/oflg/fishing-cannedfish/外研版初中英语八年级下册/SearchWord}}\"}, \"外研版初中英语八年级下册/20220118152142043265\": {\"title\": \"外研版初中英语八年级下册/20220118152142043265\", \"tags\": \"[[Module 4]] ?\", \"word\": \"weak\", \"created\": \"20220118152142043265\", \"caption\": \"{{||$:/plugins/oflg/fishing-cannedfish/外研版初中英语八年级下册/SearchWord}}\"}, \"外研版初中英语八年级下册/20220118152142043269\": {\"title\": \"外研版初中英语八年级下册/20220118152142043269\", \"tags\": \"[[Module 4]] ?\", \"word\": \"illness\", \"created\": \"20220118152142043269\", \"caption\": \"{{||$:/plugins/oflg/fishing-cannedfish/外研版初中英语八年级下册/SearchWord}}\"}, \"外研版初中英语八年级下册/20220118152142043272\": {\"title\": \"外研版初中英语八年级下册/20220118152142043272\", \"tags\": \"[[Module 4]] ?\", \"word\": \"exercise\", \"created\": \"20220118152142043272\", \"caption\": \"{{||$:/plugins/oflg/fishing-cannedfish/外研版初中英语八年级下册/SearchWord}}\"}, \"外研版初中英语八年级下册/20220118152142043275\": {\"title\": \"外研版初中英语八年级下册/20220118152142043275\", \"tags\": \"[[Module 4]] ?\", \"word\": \"awful\", \"created\": \"20220118152142043275\", \"caption\": \"{{||$:/plugins/oflg/fishing-cannedfish/外研版初中英语八年级下册/SearchWord}}\"}, \"外研版初中英语八年级下册/20220118152142043278\": {\"title\": \"外研版初中英语八年级下册/20220118152142043278\", \"tags\": \"[[Module 4]] ?\", \"word\": \"feel awful\", \"created\": \"20220118152142043278\", \"caption\": \"{{||$:/plugins/oflg/fishing-cannedfish/外研版初中英语八年级下册/SearchWord}}\"}, \"外研版初中英语八年级下册/20220118152142043281\": {\"title\": \"外研版初中英语八年级下册/20220118152142043281\", \"tags\": \"[[Module 4]] ?\", \"word\": \"all over\", \"created\": \"20220118152142043281\", \"caption\": \"{{||$:/plugins/oflg/fishing-cannedfish/外研版初中英语八年级下册/SearchWord}}\"}, \"外研版初中英语八年级下册/20220118152142043285\": {\"title\": \"外研版初中英语八年级下册/20220118152142043285\", \"tags\": \"[[Module 4]] ?\", \"word\": \"perhaps\", \"created\": \"20220118152142043285\", \"caption\": \"{{||$:/plugins/oflg/fishing-cannedfish/外研版初中英语八年级下册/SearchWord}}\"}, \"外研版初中英语八年级下册/20220118152142043288\": {\"title\": \"外研版初中英语八年级下册/20220118152142043288\", \"tags\": \"[[Module 5]] ?\", \"word\": \"cartoon\", \"created\": \"20220118152142043288\", \"caption\": \"{{||$:/plugins/oflg/fishing-cannedfish/外研版初中英语八年级下册/SearchWord}}\"}, \"外研版初中英语八年级下册/20220118152142043292\": {\"title\": \"外研版初中英语八年级下册/20220118152142043292\", \"tags\": \"[[Module 5]] ?\", \"word\": \"handsome\", \"created\": \"20220118152142043292\", \"caption\": \"{{||$:/plugins/oflg/fishing-cannedfish/外研版初中英语八年级下册/SearchWord}}\"}, \"外研版初中英语八年级下册/20220118152142043295\": {\"title\": \"外研版初中英语八年级下册/20220118152142043295\", \"tags\": \"[[Module 5]] ?\", \"word\": \"smart\", \"created\": \"20220118152142043295\", \"caption\": \"{{||$:/plugins/oflg/fishing-cannedfish/外研版初中英语八年级下册/SearchWord}}\"}, \"外研版初中英语八年级下册/20220118152142043298\": {\"title\": \"外研版初中英语八年级下册/20220118152142043298\", \"tags\": \"[[Module 5]] ?\", \"word\": \"sky\", \"created\": \"20220118152142043298\", \"caption\": \"{{||$:/plugins/oflg/fishing-cannedfish/外研版初中英语八年级下册/SearchWord}}\"}, \"外研版初中英语八年级下册/20220118152142043301\": {\"title\": \"外研版初中英语八年级下册/20220118152142043301\", \"tags\": \"[[Module 5]] ?\", \"word\": \"fight\", \"created\": \"20220118152142043301\", \"caption\": \"{{||$:/plugins/oflg/fishing-cannedfish/外研版初中英语八年级下册/SearchWord}}\"}, \"外研版初中英语八年级下册/20220118152142043304\": {\"title\": \"外研版初中英语八年级下册/20220118152142043304\", \"tags\": \"[[Module 5]] ?\", \"word\": \"cool\", \"created\": \"20220118152142043304\", \"caption\": \"{{||$:/plugins/oflg/fishing-cannedfish/外研版初中英语八年级下册/SearchWord}}\"}, \"外研版初中英语八年级下册/20220118152142043307\": {\"title\": \"外研版初中英语八年级下册/20220118152142043307\", \"tags\": \"[[Module 5]] ?\", \"word\": \"hero\", \"created\": \"20220118152142043307\", \"caption\": \"{{||$:/plugins/oflg/fishing-cannedfish/外研版初中英语八年级下册/SearchWord}}\"}, \"外研版初中英语八年级下册/20220118152142043310\": {\"title\": \"外研版初中英语八年级下册/20220118152142043310\", \"tags\": \"[[Module 5]] ?\", \"word\": \"humorous\", \"created\": \"20220118152142043310\", \"caption\": \"{{||$:/plugins/oflg/fishing-cannedfish/外研版初中英语八年级下册/SearchWord}}\"}, \"外研版初中英语八年级下册/20220118152142043313\": {\"title\": \"外研版初中英语八年级下册/20220118152142043313\", \"tags\": \"[[Module 5]] ?\", \"word\": \"can't help doing sth.\", \"created\": \"20220118152142043313\", \"caption\": \"{{||$:/plugins/oflg/fishing-cannedfish/外研版初中英语八年级下册/SearchWord}}\"}, \"外研版初中英语八年级下册/20220118152142043316\": {\"title\": \"外研版初中英语八年级下册/20220118152142043316\", \"tags\": \"[[Module 5]] ?\", \"word\": \"laugh\", \"created\": \"20220118152142043316\", \"caption\": \"{{||$:/plugins/oflg/fishing-cannedfish/外研版初中英语八年级下册/SearchWord}}\"}, \"外研版初中英语八年级下册/20220118152142043319\": {\"title\": \"外研版初中英语八年级下册/20220118152142043319\", \"tags\": \"[[Module 5]] ?\", \"word\": \"lesson\", \"created\": \"20220118152142043319\", \"caption\": \"{{||$:/plugins/oflg/fishing-cannedfish/外研版初中英语八年级下册/SearchWord}}\"}, \"外研版初中英语八年级下册/20220118152142043323\": {\"title\": \"外研版初中英语八年级下册/20220118152142043323\", \"tags\": \"[[Module 5]] ?\", \"word\": \"orange-and-white\", \"created\": \"20220118152142043323\", \"caption\": \"{{||$:/plugins/oflg/fishing-cannedfish/外研版初中英语八年级下册/SearchWord}}\"}, \"外研版初中英语八年级下册/20220118152142043326\": {\"title\": \"外研版初中英语八年级下册/20220118152142043326\", \"tags\": \"[[Module 5]] ?\", \"word\": \"ugly\", \"created\": \"20220118152142043326\", \"caption\": \"{{||$:/plugins/oflg/fishing-cannedfish/外研版初中英语八年级下册/SearchWord}}\"}, \"外研版初中英语八年级下册/20220118152142043329\": {\"title\": \"外研版初中英语八年级下册/20220118152142043329\", \"tags\": \"[[Module 5]] ?\", \"word\": \"win the heart of sb.\", \"created\": \"20220118152142043329\", \"caption\": \"{{||$:/plugins/oflg/fishing-cannedfish/外研版初中英语八年级下册/SearchWord}}\"}, \"外研版初中英语八年级下册/20220118152142043332\": {\"title\": \"外研版初中英语八年级下册/20220118152142043332\", \"tags\": \"[[Module 5]] ?\", \"word\": \"schoolbag\", \"created\": \"20220118152142043332\", \"caption\": \"{{||$:/plugins/oflg/fishing-cannedfish/外研版初中英语八年级下册/SearchWord}}\"}, \"外研版初中英语八年级下册/20220118152142043336\": {\"title\": \"外研版初中英语八年级下册/20220118152142043336\", \"tags\": \"[[Module 5]] ?\", \"word\": \"lead\", \"created\": \"20220118152142043336\", \"caption\": \"{{||$:/plugins/oflg/fishing-cannedfish/外研版初中英语八年级下册/SearchWord}}\"}, \"外研版初中英语八年级下册/20220118152142043339\": {\"title\": \"外研版初中英语八年级下册/20220118152142043339\", \"tags\": \"[[Module 5]] ?\", \"word\": \"clever\", \"created\": \"20220118152142043339\", \"caption\": \"{{||$:/plugins/oflg/fishing-cannedfish/外研版初中英语八年级下册/SearchWord}}\"}, \"外研版初中英语八年级下册/20220118152142043342\": {\"title\": \"外研版初中英语八年级下册/20220118152142043342\", \"tags\": \"[[Module 5]] ?\", \"word\": \"as\", \"created\": \"20220118152142043342\", \"caption\": \"{{||$:/plugins/oflg/fishing-cannedfish/外研版初中英语八年级下册/SearchWord}}\"}, \"外研版初中英语八年级下册/20220118152142043345\": {\"title\": \"外研版初中英语八年级下册/20220118152142043345\", \"tags\": \"[[Module 5]] ?\", \"word\": \"mess\", \"created\": \"20220118152142043345\", \"caption\": \"{{||$:/plugins/oflg/fishing-cannedfish/外研版初中英语八年级下册/SearchWord}}\"}, \"外研版初中英语八年级下册/20220118152142043348\": {\"title\": \"外研版初中英语八年级下册/20220118152142043348\", \"tags\": \"[[Module 5]] ?\", \"word\": \"heaven\", \"created\": \"20220118152142043348\", \"caption\": \"{{||$:/plugins/oflg/fishing-cannedfish/外研版初中英语八年级下册/SearchWord}}\"}, \"外研版初中英语八年级下册/20220118152142043352\": {\"title\": \"外研版初中英语八年级下册/20220118152142043352\", \"tags\": \"[[Module 5]] ?\", \"word\": \"expect\", \"created\": \"20220118152142043352\", \"caption\": \"{{||$:/plugins/oflg/fishing-cannedfish/外研版初中英语八年级下册/SearchWord}}\"}, \"外研版初中英语八年级下册/20220118152142043355\": {\"title\": \"外研版初中英语八年级下册/20220118152142043355\", \"tags\": \"[[Module 5]] ?\", \"word\": \"artist\", \"created\": \"20220118152142043355\", \"caption\": \"{{||$:/plugins/oflg/fishing-cannedfish/外研版初中英语八年级下册/SearchWord}}\"}, \"外研版初中英语八年级下册/20220118152142043358\": {\"title\": \"外研版初中英语八年级下册/20220118152142043358\", \"tags\": \"[[Module 5]] ?\", \"word\": \"invent\", \"created\": \"20220118152142043358\", \"caption\": \"{{||$:/plugins/oflg/fishing-cannedfish/外研版初中英语八年级下册/SearchWord}}\"}, \"外研版初中英语八年级下册/20220118152142043361\": {\"title\": \"外研版初中英语八年级下册/20220118152142043361\", \"tags\": \"[[Module 5]] ?\", \"word\": \"copy\", \"created\": \"20220118152142043361\", \"caption\": \"{{||$:/plugins/oflg/fishing-cannedfish/外研版初中英语八年级下册/SearchWord}}\"}, \"外研版初中英语八年级下册/20220118152142043364\": {\"title\": \"外研版初中英语八年级下册/20220118152142043364\", \"tags\": \"[[Module 5]] ?\", \"word\": \"black-and-white\", \"created\": \"20220118152142043364\", \"caption\": \"{{||$:/plugins/oflg/fishing-cannedfish/外研版初中英语八年级下册/SearchWord}}\"}, \"外研版初中英语八年级下册/20220118152142043368\": {\"title\": \"外研版初中英语八年级下册/20220118152142043368\", \"tags\": \"[[Module 5]] ?\", \"word\": \"own\", \"created\": \"20220118152142043368\", \"caption\": \"{{||$:/plugins/oflg/fishing-cannedfish/外研版初中英语八年级下册/SearchWord}}\"}, \"外研版初中英语八年级下册/20220118152142043371\": {\"title\": \"外研版初中英语八年级下册/20220118152142043371\", \"tags\": \"[[Module 5]] ?\", \"word\": \"private\", \"created\": \"20220118152142043371\", \"caption\": \"{{||$:/plugins/oflg/fishing-cannedfish/外研版初中英语八年级下册/SearchWord}}\"}, \"外研版初中英语八年级下册/20220118152142043374\": {\"title\": \"外研版初中英语八年级下册/20220118152142043374\", \"tags\": \"[[Module 5]] ?\", \"word\": \"create\", \"created\": \"20220118152142043374\", \"caption\": \"{{||$:/plugins/oflg/fishing-cannedfish/外研版初中英语八年级下册/SearchWord}}\"}, \"外研版初中英语八年级下册/20220118152142043377\": {\"title\": \"外研版初中英语八年级下册/20220118152142043377\", \"tags\": \"[[Module 5]] ?\", \"word\": \"satisfy\", \"created\": \"20220118152142043377\", \"caption\": \"{{||$:/plugins/oflg/fishing-cannedfish/外研版初中英语八年级下册/SearchWord}}\"}, \"外研版初中英语八年级下册/20220118152142043381\": {\"title\": \"外研版初中英语八年级下册/20220118152142043381\", \"tags\": \"[[Module 6]] ?\", \"word\": \"fan\", \"created\": \"20220118152142043381\", \"caption\": \"{{||$:/plugins/oflg/fishing-cannedfish/外研版初中英语八年级下册/SearchWord}}\"}, \"外研版初中英语八年级下册/20220118152142043384\": {\"title\": \"外研版初中英语八年级下册/20220118152142043384\", \"tags\": \"[[Module 6]] ?\", \"word\": \"stamp\", \"created\": \"20220118152142043384\", \"caption\": \"{{||$:/plugins/oflg/fishing-cannedfish/外研版初中英语八年级下册/SearchWord}}\"}, \"外研版初中英语八年级下册/20220118152142043387\": {\"title\": \"外研版初中英语八年级下册/20220118152142043387\", \"tags\": \"[[Module 6]] ?\", \"word\": \"tidy up\", \"created\": \"20220118152142043387\", \"caption\": \"{{||$:/plugins/oflg/fishing-cannedfish/外研版初中英语八年级下册/SearchWord}}\"}, \"外研版初中英语八年级下册/20220118152142043391\": {\"title\": \"外研版初中英语八年级下册/20220118152142043391\", \"tags\": \"[[Module 6]] ?\", \"word\": \"shelf\", \"created\": \"20220118152142043391\", \"caption\": \"{{||$:/plugins/oflg/fishing-cannedfish/外研版初中英语八年级下册/SearchWord}}\"}, \"外研版初中英语八年级下册/20220118152142043394\": {\"title\": \"外研版初中英语八年级下册/20220118152142043394\", \"tags\": \"[[Module 6]] ?\", \"word\": \"have a look\", \"created\": \"20220118152142043394\", \"caption\": \"{{||$:/plugins/oflg/fishing-cannedfish/外研版初中英语八年级下册/SearchWord}}\"}, \"外研版初中英语八年级下册/20220118152142043397\": {\"title\": \"外研版初中英语八年级下册/20220118152142043397\", \"tags\": \"[[Module 6]] ?\", \"word\": \"as\", \"created\": \"20220118152142043397\", \"caption\": \"{{||$:/plugins/oflg/fishing-cannedfish/外研版初中英语八年级下册/SearchWord}}\"}, \"外研版初中英语八年级下册/20220118152142043401\": {\"title\": \"外研版初中英语八年级下册/20220118152142043401\", \"tags\": \"[[Module 6]] ?\", \"word\": \"coin\", \"created\": \"20220118152142043401\", \"caption\": \"{{||$:/plugins/oflg/fishing-cannedfish/外研版初中英语八年级下册/SearchWord}}\"}, \"外研版初中英语八年级下册/20220118152142043404\": {\"title\": \"外研版初中英语八年级下册/20220118152142043404\", \"tags\": \"[[Module 6]] ?\", \"word\": \"note\", \"created\": \"20220118152142043404\", \"caption\": \"{{||$:/plugins/oflg/fishing-cannedfish/外研版初中英语八年级下册/SearchWord}}\"}, \"外研版初中英语八年级下册/20220118152142043407\": {\"title\": \"外研版初中英语八年级下册/20220118152142043407\", \"tags\": \"[[Module 6]] ?\", \"word\": \"pound\", \"created\": \"20220118152142043407\", \"caption\": \"{{||$:/plugins/oflg/fishing-cannedfish/外研版初中英语八年级下册/SearchWord}}\"}, \"外研版初中英语八年级下册/20220118152142043410\": {\"title\": \"外研版初中英语八年级下册/20220118152142043410\", \"tags\": \"[[Module 6]] ?\", \"word\": \"dollar\", \"created\": \"20220118152142043410\", \"caption\": \"{{||$:/plugins/oflg/fishing-cannedfish/外研版初中英语八年级下册/SearchWord}}\"}, \"外研版初中英语八年级下册/20220118152142043413\": {\"title\": \"外研版初中英语八年级下册/20220118152142043413\", \"tags\": \"[[Module 6]] ?\", \"word\": \"must\", \"created\": \"20220118152142043413\", \"caption\": \"{{||$:/plugins/oflg/fishing-cannedfish/外研版初中英语八年级下册/SearchWord}}\"}, \"外研版初中英语八年级下册/20220118152142043417\": {\"title\": \"外研版初中英语八年级下册/20220118152142043417\", \"tags\": \"[[Module 6]] ?\", \"word\": \"valuable\", \"created\": \"20220118152142043417\", \"caption\": \"{{||$:/plugins/oflg/fishing-cannedfish/外研版初中英语八年级下册/SearchWord}}\"}, \"外研版初中英语八年级下册/20220118152142043420\": {\"title\": \"外研版初中英语八年级下册/20220118152142043420\", \"tags\": \"[[Module 6]] ?\", \"word\": \"with\", \"created\": \"20220118152142043420\", \"caption\": \"{{||$:/plugins/oflg/fishing-cannedfish/外研版初中英语八年级下册/SearchWord}}\"}, \"外研版初中英语八年级下册/20220118152142043423\": {\"title\": \"外研版初中英语八年级下册/20220118152142043423\", \"tags\": \"[[Module 6]] ?\", \"word\": \"value\", \"created\": \"20220118152142043423\", \"caption\": \"{{||$:/plugins/oflg/fishing-cannedfish/外研版初中英语八年级下册/SearchWord}}\"}, \"外研版初中英语八年级下册/20220118152142043427\": {\"title\": \"外研版初中英语八年级下册/20220118152142043427\", \"tags\": \"[[Module 6]] ?\", \"word\": \"just\", \"created\": \"20220118152142043427\", \"caption\": \"{{||$:/plugins/oflg/fishing-cannedfish/外研版初中英语八年级下册/SearchWord}}\"}, \"外研版初中英语八年级下册/20220118152142043430\": {\"title\": \"外研版初中英语八年级下册/20220118152142043430\", \"tags\": \"[[Module 6]] ?\", \"word\": \"person\", \"created\": \"20220118152142043430\", \"caption\": \"{{||$:/plugins/oflg/fishing-cannedfish/外研版初中英语八年级下册/SearchWord}}\"}, \"外研版初中英语八年级下册/20220118152142043433\": {\"title\": \"外研版初中英语八年级下册/20220118152142043433\", \"tags\": \"[[Module 6]] ?\", \"word\": \"interest\", \"created\": \"20220118152142043433\", \"caption\": \"{{||$:/plugins/oflg/fishing-cannedfish/外研版初中英语八年级下册/SearchWord}}\"}, \"外研版初中英语八年级下册/20220118152142043436\": {\"title\": \"外研版初中英语八年级下册/20220118152142043436\", \"tags\": \"[[Module 6]] ?\", \"word\": \"skill\", \"created\": \"20220118152142043436\", \"caption\": \"{{||$:/plugins/oflg/fishing-cannedfish/外研版初中英语八年级下册/SearchWord}}\"}, \"外研版初中英语八年级下册/20220118152142043441\": {\"title\": \"外研版初中英语八年级下册/20220118152142043441\", \"tags\": \"[[Module 6]] ?\", \"word\": \"activity\", \"created\": \"20220118152142043441\", \"caption\": \"{{||$:/plugins/oflg/fishing-cannedfish/外研版初中英语八年级下册/SearchWord}}\"}, \"外研版初中英语八年级下册/20220118152142043445\": {\"title\": \"外研版初中英语八年级下册/20220118152142043445\", \"tags\": \"[[Module 6]] ?\", \"word\": \"sailing\", \"created\": \"20220118152142043445\", \"caption\": \"{{||$:/plugins/oflg/fishing-cannedfish/外研版初中英语八年级下册/SearchWord}}\"}, \"外研版初中英语八年级下册/20220118152142043448\": {\"title\": \"外研版初中英语八年级下册/20220118152142043448\", \"tags\": \"[[Module 6]] ?\", \"word\": \"come out\", \"created\": \"20220118152142043448\", \"caption\": \"{{||$:/plugins/oflg/fishing-cannedfish/外研版初中英语八年级下册/SearchWord}}\"}, \"外研版初中英语八年级下册/20220118152142043451\": {\"title\": \"外研版初中英语八年级下册/20220118152142043451\", \"tags\": \"[[Module 6]] ?\", \"word\": \"result\", \"created\": \"20220118152142043451\", \"caption\": \"{{||$:/plugins/oflg/fishing-cannedfish/外研版初中英语八年级下册/SearchWord}}\"}, \"外研版初中英语八年级下册/20220118152142043454\": {\"title\": \"外研版初中英语八年级下册/20220118152142043454\", \"tags\": \"[[Module 6]] ?\", \"word\": \"as a result\", \"created\": \"20220118152142043454\", \"caption\": \"{{||$:/plugins/oflg/fishing-cannedfish/外研版初中英语八年级下册/SearchWord}}\"}, \"外研版初中英语八年级下册/20220118152142043458\": {\"title\": \"外研版初中英语八年级下册/20220118152142043458\", \"tags\": \"[[Module 6]] ?\", \"word\": \"pleasure\", \"created\": \"20220118152142043458\", \"caption\": \"{{||$:/plugins/oflg/fishing-cannedfish/外研版初中英语八年级下册/SearchWord}}\"}, \"外研版初中英语八年级下册/20220118152142043461\": {\"title\": \"外研版初中英语八年级下册/20220118152142043461\", \"tags\": \"[[Module 6]] ?\", \"word\": \"success\", \"created\": \"20220118152142043461\", \"caption\": \"{{||$:/plugins/oflg/fishing-cannedfish/外研版初中英语八年级下册/SearchWord}}\"}, \"外研版初中英语八年级下册/20220118152142043465\": {\"title\": \"外研版初中英语八年级下册/20220118152142043465\", \"tags\": \"[[Module 7]] ?\", \"word\": \"list\", \"created\": \"20220118152142043465\", \"caption\": \"{{||$:/plugins/oflg/fishing-cannedfish/外研版初中英语八年级下册/SearchWord}}\"}, \"外研版初中英语八年级下册/20220118152142043468\": {\"title\": \"外研版初中英语八年级下册/20220118152142043468\", \"tags\": \"[[Module 7]] ?\", \"word\": \"make a list\", \"created\": \"20220118152142043468\", \"caption\": \"{{||$:/plugins/oflg/fishing-cannedfish/外研版初中英语八年级下册/SearchWord}}\"}, \"外研版初中英语八年级下册/20220118152142043472\": {\"title\": \"外研版初中英语八年级下册/20220118152142043472\", \"tags\": \"[[Module 7]] ?\", \"word\": \"crazy\", \"created\": \"20220118152142043472\", \"caption\": \"{{||$:/plugins/oflg/fishing-cannedfish/外研版初中英语八年级下册/SearchWord}}\"}, \"外研版初中英语八年级下册/20220118152142043475\": {\"title\": \"外研版初中英语八年级下册/20220118152142043475\", \"tags\": \"[[Module 7]] ?\", \"word\": \"at the end of ...\", \"created\": \"20220118152142043475\", \"caption\": \"{{||$:/plugins/oflg/fishing-cannedfish/外研版初中英语八年级下册/SearchWord}}\"}, \"外研版初中英语八年级下册/20220118152142043478\": {\"title\": \"外研版初中英语八年级下册/20220118152142043478\", \"tags\": \"[[Module 7]] ?\", \"word\": \"shorts\", \"created\": \"20220118152142043478\", \"caption\": \"{{||$:/plugins/oflg/fishing-cannedfish/外研版初中英语八年级下册/SearchWord}}\"}, \"外研版初中英语八年级下册/20220118152142043481\": {\"title\": \"外研版初中英语八年级下册/20220118152142043481\", \"tags\": \"[[Module 7]] ?\", \"word\": \"trousers\", \"created\": \"20220118152142043481\", \"caption\": \"{{||$:/plugins/oflg/fishing-cannedfish/外研版初中英语八年级下册/SearchWord}}\"}, \"外研版初中英语八年级下册/20220118152142043484\": {\"title\": \"外研版初中英语八年级下册/20220118152142043484\", \"tags\": \"[[Module 7]] ?\", \"word\": \"sunglasses\", \"created\": \"20220118152142043484\", \"caption\": \"{{||$:/plugins/oflg/fishing-cannedfish/外研版初中英语八年级下册/SearchWord}}\"}, \"外研版初中英语八年级下册/20220118152142043488\": {\"title\": \"外研版初中英语八年级下册/20220118152142043488\", \"tags\": \"[[Module 7]] ?\", \"word\": \"homestay\", \"created\": \"20220118152142043488\", \"caption\": \"{{||$:/plugins/oflg/fishing-cannedfish/外研版初中英语八年级下册/SearchWord}}\"}, \"外研版初中英语八年级下册/20220118152142043491\": {\"title\": \"外研版初中英语八年级下册/20220118152142043491\", \"tags\": \"[[Module 7]] ?\", \"word\": \"weigh\", \"created\": \"20220118152142043491\", \"caption\": \"{{||$:/plugins/oflg/fishing-cannedfish/外研版初中英语八年级下册/SearchWord}}\"}, \"外研版初中英语八年级下册/20220118152142043494\": {\"title\": \"外研版初中英语八年级下册/20220118152142043494\", \"tags\": \"[[Module 7]] ?\", \"word\": \"total\", \"created\": \"20220118152142043494\", \"caption\": \"{{||$:/plugins/oflg/fishing-cannedfish/外研版初中英语八年级下册/SearchWord}}\"}, \"外研版初中英语八年级下册/20220118152142043497\": {\"title\": \"外研版初中英语八年级下册/20220118152142043497\", \"tags\": \"[[Module 7]] ?\", \"word\": \"weight\", \"created\": \"20220118152142043497\", \"caption\": \"{{||$:/plugins/oflg/fishing-cannedfish/外研版初中英语八年级下册/SearchWord}}\"}, \"外研版初中英语八年级下册/20220118152142043500\": {\"title\": \"外研版初中英语八年级下册/20220118152142043500\", \"tags\": \"[[Module 7]] ?\", \"word\": \"passport\", \"created\": \"20220118152142043500\", \"caption\": \"{{||$:/plugins/oflg/fishing-cannedfish/外研版初中英语八年级下册/SearchWord}}\"}, \"外研版初中英语八年级下册/20220118152142043503\": {\"title\": \"外研版初中英语八年级下册/20220118152142043503\", \"tags\": \"[[Module 7]] ?\", \"word\": \"culture\", \"created\": \"20220118152142043503\", \"caption\": \"{{||$:/plugins/oflg/fishing-cannedfish/外研版初中英语八年级下册/SearchWord}}\"}, \"外研版初中英语八年级下册/20220118152142043506\": {\"title\": \"外研版初中英语八年级下册/20220118152142043506\", \"tags\": \"[[Module 7]] ?\", \"word\": \"at the same time\", \"created\": \"20220118152142043506\", \"caption\": \"{{||$:/plugins/oflg/fishing-cannedfish/外研版初中英语八年级下册/SearchWord}}\"}, \"外研版初中英语八年级下册/20220118152142043510\": {\"title\": \"外研版初中英语八年级下册/20220118152142043510\", \"tags\": \"[[Module 7]] ?\", \"word\": \"last\", \"created\": \"20220118152142043510\", \"caption\": \"{{||$:/plugins/oflg/fishing-cannedfish/外研版初中英语八年级下册/SearchWord}}\"}, \"外研版初中英语八年级下册/20220118152142043513\": {\"title\": \"外研版初中英语八年级下册/20220118152142043513\", \"tags\": \"[[Module 7]] ?\", \"word\": \"depend\", \"created\": \"20220118152142043513\", \"caption\": \"{{||$:/plugins/oflg/fishing-cannedfish/外研版初中英语八年级下册/SearchWord}}\"}, \"外研版初中英语八年级下册/20220118152142043516\": {\"title\": \"外研版初中英语八年级下册/20220118152142043516\", \"tags\": \"[[Module 7]] ?\", \"word\": \"depend on\", \"created\": \"20220118152142043516\", \"caption\": \"{{||$:/plugins/oflg/fishing-cannedfish/外研版初中英语八年级下册/SearchWord}}\"}, \"外研版初中英语八年级下册/20220118152142043519\": {\"title\": \"外研版初中英语八年级下册/20220118152142043519\", \"tags\": \"[[Module 7]] ?\", \"word\": \"provide\", \"created\": \"20220118152142043519\", \"caption\": \"{{||$:/plugins/oflg/fishing-cannedfish/外研版初中英语八年级下册/SearchWord}}\"}, \"外研版初中英语八年级下册/20220118152142043522\": {\"title\": \"外研版初中英语八年级下册/20220118152142043522\", \"tags\": \"[[Module 7]] ?\", \"word\": \"test\", \"created\": \"20220118152142043522\", \"caption\": \"{{||$:/plugins/oflg/fishing-cannedfish/外研版初中英语八年级下册/SearchWord}}\"}, \"外研版初中英语八年级下册/20220118152142043526\": {\"title\": \"外研版初中英语八年级下册/20220118152142043526\", \"tags\": \"[[Module 7]] ?\", \"word\": \"progress\", \"created\": \"20220118152142043526\", \"caption\": \"{{||$:/plugins/oflg/fishing-cannedfish/外研版初中英语八年级下册/SearchWord}}\"}, \"外研版初中英语八年级下册/20220118152142043529\": {\"title\": \"外研版初中英语八年级下册/20220118152142043529\", \"tags\": \"[[Module 7]] ?\", \"word\": \"guest\", \"created\": \"20220118152142043529\", \"caption\": \"{{||$:/plugins/oflg/fishing-cannedfish/外研版初中英语八年级下册/SearchWord}}\"}, \"外研版初中英语八年级下册/20220118152142043533\": {\"title\": \"外研版初中英语八年级下册/20220118152142043533\", \"tags\": \"[[Module 7]] ?\", \"word\": \"daily life\", \"created\": \"20220118152142043533\", \"caption\": \"{{||$:/plugins/oflg/fishing-cannedfish/外研版初中英语八年级下册/SearchWord}}\"}, \"外研版初中英语八年级下册/20220118152142043536\": {\"title\": \"外研版初中英语八年级下册/20220118152142043536\", \"tags\": \"[[Module 7]] ?\", \"word\": \"form\", \"created\": \"20220118152142043536\", \"caption\": \"{{||$:/plugins/oflg/fishing-cannedfish/外研版初中英语八年级下册/SearchWord}}\"}, \"外研版初中英语八年级下册/20220118152142043540\": {\"title\": \"外研版初中英语八年级下册/20220118152142043540\", \"tags\": \"[[Module 7]] ?\", \"word\": \"friendship\", \"created\": \"20220118152142043540\", \"caption\": \"{{||$:/plugins/oflg/fishing-cannedfish/外研版初中英语八年级下册/SearchWord}}\"}, \"外研版初中英语八年级下册/20220118152142043559\": {\"title\": \"外研版初中英语八年级下册/20220118152142043559\", \"tags\": \"[[Module 7]] ?\", \"word\": \"stay in touch\", \"created\": \"20220118152142043559\", \"caption\": \"{{||$:/plugins/oflg/fishing-cannedfish/外研版初中英语八年级下册/SearchWord}}\"}, \"外研版初中英语八年级下册/20220118152142043564\": {\"title\": \"外研版初中英语八年级下册/20220118152142043564\", \"tags\": \"[[Module 7]] ?\", \"word\": \"stay in touch with sb.\", \"created\": \"20220118152142043564\", \"caption\": \"{{||$:/plugins/oflg/fishing-cannedfish/外研版初中英语八年级下册/SearchWord}}\"}, \"外研版初中英语八年级下册/20220118152142043567\": {\"title\": \"外研版初中英语八年级下册/20220118152142043567\", \"tags\": \"[[Module 7]] ?\", \"word\": \"prefer\", \"created\": \"20220118152142043567\", \"caption\": \"{{||$:/plugins/oflg/fishing-cannedfish/外研版初中英语八年级下册/SearchWord}}\"}, \"外研版初中英语八年级下册/20220118152142043570\": {\"title\": \"外研版初中英语八年级下册/20220118152142043570\", \"tags\": \"[[Module 7]] ?\", \"word\": \"certain\", \"created\": \"20220118152142043570\", \"caption\": \"{{||$:/plugins/oflg/fishing-cannedfish/外研版初中英语八年级下册/SearchWord}}\"}, \"外研版初中英语八年级下册/20220118152142043574\": {\"title\": \"外研版初中英语八年级下册/20220118152142043574\", \"tags\": \"[[Module 7]] ?\", \"word\": \"fill\", \"created\": \"20220118152142043574\", \"caption\": \"{{||$:/plugins/oflg/fishing-cannedfish/外研版初中英语八年级下册/SearchWord}}\"}, \"外研版初中英语八年级下册/20220118152142043578\": {\"title\": \"外研版初中英语八年级下册/20220118152142043578\", \"tags\": \"[[Module 7]] ?\", \"word\": \"fill out\", \"created\": \"20220118152142043578\", \"caption\": \"{{||$:/plugins/oflg/fishing-cannedfish/外研版初中英语八年级下册/SearchWord}}\"}, \"外研版初中英语八年级下册/20220118152142043582\": {\"title\": \"外研版初中英语八年级下册/20220118152142043582\", \"tags\": \"[[Module 8]] ?\", \"word\": \"hardly\", \"created\": \"20220118152142043582\", \"caption\": \"{{||$:/plugins/oflg/fishing-cannedfish/外研版初中英语八年级下册/SearchWord}}\"}, \"外研版初中英语八年级下册/20220118152142043586\": {\"title\": \"外研版初中英语八年级下册/20220118152142043586\", \"tags\": \"[[Module 8]] ?\", \"word\": \"take up\", \"created\": \"20220118152142043586\", \"caption\": \"{{||$:/plugins/oflg/fishing-cannedfish/外研版初中英语八年级下册/SearchWord}}\"}, \"外研版初中英语八年级下册/20220118152142043589\": {\"title\": \"外研版初中英语八年级下册/20220118152142043589\", \"tags\": \"[[Module 8]] ?\", \"word\": \"point out\", \"created\": \"20220118152142043589\", \"caption\": \"{{||$:/plugins/oflg/fishing-cannedfish/外研版初中英语八年级下册/SearchWord}}\"}, \"外研版初中英语八年级下册/20220118152142043592\": {\"title\": \"外研版初中英语八年级下册/20220118152142043592\", \"tags\": \"[[Module 8]] ?\", \"word\": \"sights\", \"created\": \"20220118152142043592\", \"caption\": \"{{||$:/plugins/oflg/fishing-cannedfish/外研版初中英语八年级下册/SearchWord}}\"}, \"外研版初中英语八年级下册/20220118152142043595\": {\"title\": \"外研版初中英语八年级下册/20220118152142043595\", \"tags\": \"[[Module 8]] ?\", \"word\": \"thirsty\", \"created\": \"20220118152142043595\", \"caption\": \"{{||$:/plugins/oflg/fishing-cannedfish/外研版初中英语八年级下册/SearchWord}}\"}, \"外研版初中英语八年级下册/20220118152142043599\": {\"title\": \"外研版初中英语八年级下册/20220118152142043599\", \"tags\": \"[[Module 8]] ?\", \"word\": \"at the top of ...\", \"created\": \"20220118152142043599\", \"caption\": \"{{||$:/plugins/oflg/fishing-cannedfish/外研版初中英语八年级下册/SearchWord}}\"}, \"外研版初中英语八年级下册/20220118152142043602\": {\"title\": \"外研版初中英语八年级下册/20220118152142043602\", \"tags\": \"[[Module 8]] ?\", \"word\": \"waste\", \"created\": \"20220118152142043602\", \"caption\": \"{{||$:/plugins/oflg/fishing-cannedfish/外研版初中英语八年级下册/SearchWord}}\"}, \"外研版初中英语八年级下册/20220118152142043605\": {\"title\": \"外研版初中英语八年级下册/20220118152142043605\", \"tags\": \"[[Module 8]] ?\", \"word\": \"square\", \"created\": \"20220118152142043605\", \"caption\": \"{{||$:/plugins/oflg/fishing-cannedfish/外研版初中英语八年级下册/SearchWord}}\"}, \"外研版初中英语八年级下册/20220118152142043609\": {\"title\": \"外研版初中英语八年级下册/20220118152142043609\", \"tags\": \"[[Module 8]] ?\", \"word\": \"kilometre\", \"created\": \"20220118152142043609\", \"caption\": \"{{||$:/plugins/oflg/fishing-cannedfish/外研版初中英语八年级下册/SearchWord}}\"}, \"外研版初中英语八年级下册/20220118152142043612\": {\"title\": \"外研版初中英语八年级下册/20220118152142043612\", \"tags\": \"[[Module 8]] ?\", \"word\": \"shape\", \"created\": \"20220118152142043612\", \"caption\": \"{{||$:/plugins/oflg/fishing-cannedfish/外研版初中英语八年级下册/SearchWord}}\"}, \"外研版初中英语八年级下册/20220118152142043615\": {\"title\": \"外研版初中英语八年级下册/20220118152142043615\", \"tags\": \"[[Module 8]] ?\", \"word\": \"human\", \"created\": \"20220118152142043615\", \"caption\": \"{{||$:/plugins/oflg/fishing-cannedfish/外研版初中英语八年级下册/SearchWord}}\"}, \"外研版初中英语八年级下册/20220118152142043618\": {\"title\": \"外研版初中英语八年级下册/20220118152142043618\", \"tags\": \"[[Module 8]] ?\", \"word\": \"wake\", \"created\": \"20220118152142043618\", \"caption\": \"{{||$:/plugins/oflg/fishing-cannedfish/外研版初中英语八年级下册/SearchWord}}\"}, \"外研版初中英语八年级下册/20220118152142043621\": {\"title\": \"外研版初中英语八年级下册/20220118152142043621\", \"tags\": \"[[Module 8]] ?\", \"word\": \"wake sb. up\", \"created\": \"20220118152142043621\", \"caption\": \"{{||$:/plugins/oflg/fishing-cannedfish/外研版初中英语八年级下册/SearchWord}}\"}, \"外研版初中英语八年级下册/20220118152142043624\": {\"title\": \"外研版初中英语八年级下册/20220118152142043624\", \"tags\": \"[[Module 8]] ?\", \"word\": \"somebody\", \"created\": \"20220118152142043624\", \"caption\": \"{{||$:/plugins/oflg/fishing-cannedfish/外研版初中英语八年级下册/SearchWord}}\"}, \"外研版初中英语八年级下册/20220118152142043627\": {\"title\": \"外研版初中英语八年级下册/20220118152142043627\", \"tags\": \"[[Module 8]] ?\", \"word\": \"about\", \"created\": \"20220118152142043627\", \"caption\": \"{{||$:/plugins/oflg/fishing-cannedfish/外研版初中英语八年级下册/SearchWord}}\"}, \"外研版初中英语八年级下册/20220118152142043630\": {\"title\": \"外研版初中英语八年级下册/20220118152142043630\", \"tags\": \"[[Module 8]] ?\", \"word\": \"path\", \"created\": \"20220118152142043630\", \"caption\": \"{{||$:/plugins/oflg/fishing-cannedfish/外研版初中英语八年级下册/SearchWord}}\"}, \"外研版初中英语八年级下册/20220118152142043633\": {\"title\": \"外研版初中英语八年级下册/20220118152142043633\", \"tags\": \"[[Module 8]] ?\", \"word\": \"pull\", \"created\": \"20220118152142043633\", \"caption\": \"{{||$:/plugins/oflg/fishing-cannedfish/外研版初中英语八年级下册/SearchWord}}\"}, \"外研版初中英语八年级下册/20220118152142043636\": {\"title\": \"外研版初中英语八年级下册/20220118152142043636\", \"tags\": \"[[Module 8]] ?\", \"word\": \"freshwater\", \"created\": \"20220118152142043636\", \"caption\": \"{{||$:/plugins/oflg/fishing-cannedfish/外研版初中英语八年级下册/SearchWord}}\"}, \"外研版初中英语八年级下册/20220118152142043639\": {\"title\": \"外研版初中英语八年级下册/20220118152142043639\", \"tags\": \"[[Module 9]] ?\", \"word\": \"helpline\", \"created\": \"20220118152142043639\", \"caption\": \"{{||$:/plugins/oflg/fishing-cannedfish/外研版初中英语八年级下册/SearchWord}}\"}, \"外研版初中英语八年级下册/20220118152142043642\": {\"title\": \"外研版初中英语八年级下册/20220118152142043642\", \"tags\": \"[[Module 9]] ?\", \"word\": \"separate\", \"created\": \"20220118152142043642\", \"caption\": \"{{||$:/plugins/oflg/fishing-cannedfish/外研版初中英语八年级下册/SearchWord}}\"}, \"外研版初中英语八年级下册/20220118152142043645\": {\"title\": \"外研版初中英语八年级下册/20220118152142043645\", \"tags\": \"[[Module 9]] ?\", \"word\": \"explain\", \"created\": \"20220118152142043645\", \"caption\": \"{{||$:/plugins/oflg/fishing-cannedfish/外研版初中英语八年级下册/SearchWord}}\"}, \"外研版初中英语八年级下册/20220118152142043648\": {\"title\": \"外研版初中英语八年级下册/20220118152142043648\", \"tags\": \"[[Module 9]] ?\", \"word\": \"mention\", \"created\": \"20220118152142043648\", \"caption\": \"{{||$:/plugins/oflg/fishing-cannedfish/外研版初中英语八年级下册/SearchWord}}\"}, \"外研版初中英语八年级下册/20220118152142043651\": {\"title\": \"外研版初中英语八年级下册/20220118152142043651\", \"tags\": \"[[Module 9]] ?\", \"word\": \"refuse\", \"created\": \"20220118152142043651\", \"caption\": \"{{||$:/plugins/oflg/fishing-cannedfish/外研版初中英语八年级下册/SearchWord}}\"}, \"外研版初中英语八年级下册/20220118152142043655\": {\"title\": \"外研版初中英语八年级下册/20220118152142043655\", \"tags\": \"[[Module 9]] ?\", \"word\": \"treat\", \"created\": \"20220118152142043655\", \"caption\": \"{{||$:/plugins/oflg/fishing-cannedfish/外研版初中英语八年级下册/SearchWord}}\"}, \"外研版初中英语八年级下册/20220118152142043657\": {\"title\": \"外研版初中英语八年级下册/20220118152142043657\", \"tags\": \"[[Module 9]] ?\", \"word\": \"herself\", \"created\": \"20220118152142043657\", \"caption\": \"{{||$:/plugins/oflg/fishing-cannedfish/外研版初中英语八年级下册/SearchWord}}\"}, \"外研版初中英语八年级下册/20220118152142043660\": {\"title\": \"外研版初中英语八年级下册/20220118152142043660\", \"tags\": \"[[Module 9]] ?\", \"word\": \"whether\", \"created\": \"20220118152142043660\", \"caption\": \"{{||$:/plugins/oflg/fishing-cannedfish/外研版初中英语八年级下册/SearchWord}}\"}, \"外研版初中英语八年级下册/20220118152142043663\": {\"title\": \"外研版初中英语八年级下册/20220118152142043663\", \"tags\": \"[[Module 9]] ?\", \"word\": \"lonely\", \"created\": \"20220118152142043663\", \"caption\": \"{{||$:/plugins/oflg/fishing-cannedfish/外研版初中英语八年级下册/SearchWord}}\"}, \"外研版初中英语八年级下册/20220118152142043666\": {\"title\": \"外研版初中英语八年级下册/20220118152142043666\", \"tags\": \"[[Module 9]] ?\", \"word\": \"regret\", \"created\": \"20220118152142043666\", \"caption\": \"{{||$:/plugins/oflg/fishing-cannedfish/外研版初中英语八年级下册/SearchWord}}\"}, \"外研版初中英语八年级下册/20220118152142043669\": {\"title\": \"外研版初中英语八年级下册/20220118152142043669\", \"tags\": \"[[Module 9]] ?\", \"word\": \"patient\", \"created\": \"20220118152142043669\", \"caption\": \"{{||$:/plugins/oflg/fishing-cannedfish/外研版初中英语八年级下册/SearchWord}}\"}, \"外研版初中英语八年级下册/20220118152142043672\": {\"title\": \"外研版初中英语八年级下册/20220118152142043672\", \"tags\": \"[[Module 9]] ?\", \"word\": \"introduce\", \"created\": \"20220118152142043672\", \"caption\": \"{{||$:/plugins/oflg/fishing-cannedfish/外研版初中英语八年级下册/SearchWord}}\"}, \"外研版初中英语八年级下册/20220118152142043675\": {\"title\": \"外研版初中英语八年级下册/20220118152142043675\", \"tags\": \"[[Module 9]] ?\", \"word\": \"encourage\", \"created\": \"20220118152142043675\", \"caption\": \"{{||$:/plugins/oflg/fishing-cannedfish/外研版初中英语八年级下册/SearchWord}}\"}, \"外研版初中英语八年级下册/20220118152142043679\": {\"title\": \"外研版初中英语八年级下册/20220118152142043679\", \"tags\": \"[[Module 9]] ?\", \"word\": \"join in\", \"created\": \"20220118152142043679\", \"caption\": \"{{||$:/plugins/oflg/fishing-cannedfish/外研版初中英语八年级下册/SearchWord}}\"}, \"外研版初中英语八年级下册/20220118152142043682\": {\"title\": \"外研版初中英语八年级下册/20220118152142043682\", \"tags\": \"[[Module 9]] ?\", \"word\": \"no problem\", \"created\": \"20220118152142043682\", \"caption\": \"{{||$:/plugins/oflg/fishing-cannedfish/外研版初中英语八年级下册/SearchWord}}\"}, \"外研版初中英语八年级下册/20220118152142043685\": {\"title\": \"外研版初中英语八年级下册/20220118152142043685\", \"tags\": \"[[Module 9]] ?\", \"word\": \"silence\", \"created\": \"20220118152142043685\", \"caption\": \"{{||$:/plugins/oflg/fishing-cannedfish/外研版初中英语八年级下册/SearchWord}}\"}, \"外研版初中英语八年级下册/20220118152142043688\": {\"title\": \"外研版初中英语八年级下册/20220118152142043688\", \"tags\": \"[[Module 9]] ?\", \"word\": \"in silence\", \"created\": \"20220118152142043688\", \"caption\": \"{{||$:/plugins/oflg/fishing-cannedfish/外研版初中英语八年级下册/SearchWord}}\"}, \"外研版初中英语八年级下册/20220118152142043691\": {\"title\": \"外研版初中英语八年级下册/20220118152142043691\", \"tags\": \"[[Module 9]] ?\", \"word\": \"pass\", \"created\": \"20220118152142043691\", \"caption\": \"{{||$:/plugins/oflg/fishing-cannedfish/外研版初中英语八年级下册/SearchWord}}\"}, \"外研版初中英语八年级下册/20220118152142043694\": {\"title\": \"外研版初中英语八年级下册/20220118152142043694\", \"tags\": \"[[Module 9]] ?\", \"word\": \"bright\", \"created\": \"20220118152142043694\", \"caption\": \"{{||$:/plugins/oflg/fishing-cannedfish/外研版初中英语八年级下册/SearchWord}}\"}, \"外研版初中英语八年级下册/20220118152142043697\": {\"title\": \"外研版初中英语八年级下册/20220118152142043697\", \"tags\": \"[[Module 9]] ?\", \"word\": \"treasure\", \"created\": \"20220118152142043697\", \"caption\": \"{{||$:/plugins/oflg/fishing-cannedfish/外研版初中英语八年级下册/SearchWord}}\"}, \"外研版初中英语八年级下册/20220118152142043700\": {\"title\": \"外研版初中英语八年级下册/20220118152142043700\", \"tags\": \"[[Module 9]] ?\", \"word\": \"day by day\", \"created\": \"20220118152142043700\", \"caption\": \"{{||$:/plugins/oflg/fishing-cannedfish/外研版初中英语八年级下册/SearchWord}}\"}, \"外研版初中英语八年级下册/20220118152142043703\": {\"title\": \"外研版初中英语八年级下册/20220118152142043703\", \"tags\": \"[[Module 9]] ?\", \"word\": \"trust\", \"created\": \"20220118152142043703\", \"caption\": \"{{||$:/plugins/oflg/fishing-cannedfish/外研版初中英语八年级下册/SearchWord}}\"}, \"外研版初中英语八年级下册/20220118152142043706\": {\"title\": \"外研版初中英语八年级下册/20220118152142043706\", \"tags\": \"[[Module 9]] ?\", \"word\": \"include\", \"created\": \"20220118152142043706\", \"caption\": \"{{||$:/plugins/oflg/fishing-cannedfish/外研版初中英语八年级下册/SearchWord}}\"}, \"外研版初中英语八年级下册/20220118152142043709\": {\"title\": \"外研版初中英语八年级下册/20220118152142043709\", \"tags\": \"[[Module 9]] ?\", \"word\": \"circle\", \"created\": \"20220118152142043709\", \"caption\": \"{{||$:/plugins/oflg/fishing-cannedfish/外研版初中英语八年级下册/SearchWord}}\"}, \"外研版初中英语八年级下册/20220118152142043712\": {\"title\": \"外研版初中英语八年级下册/20220118152142043712\", \"tags\": \"[[Module 9]] ?\", \"word\": \"stick\", \"created\": \"20220118152142043712\", \"caption\": \"{{||$:/plugins/oflg/fishing-cannedfish/外研版初中英语八年级下册/SearchWord}}\"}, \"外研版初中英语八年级下册/20220118152142043715\": {\"title\": \"外研版初中英语八年级下册/20220118152142043715\", \"tags\": \"[[Module 9]] ?\", \"word\": \"glue\", \"created\": \"20220118152142043715\", \"caption\": \"{{||$:/plugins/oflg/fishing-cannedfish/外研版初中英语八年级下册/SearchWord}}\"}, \"外研版初中英语八年级下册/20220118152142043718\": {\"title\": \"外研版初中英语八年级下册/20220118152142043718\", \"tags\": \"[[Module 9]] ?\", \"word\": \"suggestion\", \"created\": \"20220118152142043718\", \"caption\": \"{{||$:/plugins/oflg/fishing-cannedfish/外研版初中英语八年级下册/SearchWord}}\"}, \"外研版初中英语八年级下册/20220118152142043721\": {\"title\": \"外研版初中英语八年级下册/20220118152142043721\", \"tags\": \"[[Module 10]] ?\", \"word\": \"director\", \"created\": \"20220118152142043721\", \"caption\": \"{{||$:/plugins/oflg/fishing-cannedfish/外研版初中英语八年级下册/SearchWord}}\"}, \"外研版初中英语八年级下册/20220118152142043724\": {\"title\": \"外研版初中英语八年级下册/20220118152142043724\", \"tags\": \"[[Module 10]] ?\", \"word\": \"show\", \"created\": \"20220118152142043724\", \"caption\": \"{{||$:/plugins/oflg/fishing-cannedfish/外研版初中英语八年级下册/SearchWord}}\"}, \"外研版初中英语八年级下册/20220118152142043727\": {\"title\": \"外研版初中英语八年级下册/20220118152142043727\", \"tags\": \"[[Module 10]] ?\", \"word\": \"around\", \"created\": \"20220118152142043727\", \"caption\": \"{{||$:/plugins/oflg/fishing-cannedfish/外研版初中英语八年级下册/SearchWord}}\"}, \"外研版初中英语八年级下册/20220118152142043730\": {\"title\": \"外研版初中英语八年级下册/20220118152142043730\", \"tags\": \"[[Module 10]] ?\", \"word\": \"show sb. around\", \"created\": \"20220118152142043730\", \"caption\": \"{{||$:/plugins/oflg/fishing-cannedfish/外研版初中英语八年级下册/SearchWord}}\"}, \"外研版初中英语八年级下册/20220118152142043733\": {\"title\": \"外研版初中英语八年级下册/20220118152142043733\", \"tags\": \"[[Module 10]] ?\", \"word\": \"on air\", \"created\": \"20220118152142043733\", \"caption\": \"{{||$:/plugins/oflg/fishing-cannedfish/外研版初中英语八年级下册/SearchWord}}\"}, \"外研版初中英语八年级下册/20220118152142043737\": {\"title\": \"外研版初中英语八年级下册/20220118152142043737\", \"tags\": \"[[Module 10]] ?\", \"word\": \"avoid\", \"created\": \"20220118152142043737\", \"caption\": \"{{||$:/plugins/oflg/fishing-cannedfish/外研版初中英语八年级下册/SearchWord}}\"}, \"外研版初中英语八年级下册/20220118152142043740\": {\"title\": \"外研版初中英语八年级下册/20220118152142043740\", \"tags\": \"[[Module 10]] ?\", \"word\": \"background\", \"created\": \"20220118152142043740\", \"caption\": \"{{||$:/plugins/oflg/fishing-cannedfish/外研版初中英语八年级下册/SearchWord}}\"}, \"外研版初中英语八年级下册/20220118152142043743\": {\"title\": \"外研版初中英语八年级下册/20220118152142043743\", \"tags\": \"[[Module 10]] ?\", \"word\": \"national\", \"created\": \"20220118152142043743\", \"caption\": \"{{||$:/plugins/oflg/fishing-cannedfish/外研版初中英语八年级下册/SearchWord}}\"}, \"外研版初中英语八年级下册/20220118152142043746\": {\"title\": \"外研版初中英语八年级下册/20220118152142043746\", \"tags\": \"[[Module 10]] ?\", \"word\": \"international\", \"created\": \"20220118152142043746\", \"caption\": \"{{||$:/plugins/oflg/fishing-cannedfish/外研版初中英语八年级下册/SearchWord}}\"}, \"外研版初中英语八年级下册/20220118152142043749\": {\"title\": \"外研版初中英语八年级下册/20220118152142043749\", \"tags\": \"[[Module 10]] ?\", \"word\": \"presenter\", \"created\": \"20220118152142043749\", \"caption\": \"{{||$:/plugins/oflg/fishing-cannedfish/外研版初中英语八年级下册/SearchWord}}\"}, \"外研版初中英语八年级下册/20220118152142043752\": {\"title\": \"外研版初中英语八年级下册/20220118152142043752\", \"tags\": \"[[Module 10]] ?\", \"word\": \"interview\", \"created\": \"20220118152142043752\", \"caption\": \"{{||$:/plugins/oflg/fishing-cannedfish/外研版初中英语八年级下册/SearchWord}}\"}, \"外研版初中英语八年级下册/20220118152142043755\": {\"title\": \"外研版初中英语八年级下册/20220118152142043755\", \"tags\": \"[[Module 10]] ?\", \"word\": \"seem\", \"created\": \"20220118152142043755\", \"caption\": \"{{||$:/plugins/oflg/fishing-cannedfish/外研版初中英语八年级下册/SearchWord}}\"}, \"外研版初中英语八年级下册/20220118152142043758\": {\"title\": \"外研版初中英语八年级下册/20220118152142043758\", \"tags\": \"[[Module 10]] ?\", \"word\": \"listener\", \"created\": \"20220118152142043758\", \"caption\": \"{{||$:/plugins/oflg/fishing-cannedfish/外研版初中英语八年级下册/SearchWord}}\"}, \"外研版初中英语八年级下册/20220118152142043761\": {\"title\": \"外研版初中英语八年级下册/20220118152142043761\", \"tags\": \"[[Module 10]] ?\", \"word\": \"in person\", \"created\": \"20220118152142043761\", \"caption\": \"{{||$:/plugins/oflg/fishing-cannedfish/外研版初中英语八年级下册/SearchWord}}\"}, \"外研版初中英语八年级下册/20220118152142043763\": {\"title\": \"外研版初中英语八年级下册/20220118152142043763\", \"tags\": \"[[Module 10]] ?\", \"word\": \"part-time\", \"created\": \"20220118152142043763\", \"caption\": \"{{||$:/plugins/oflg/fishing-cannedfish/外研版初中英语八年级下册/SearchWord}}\"}, \"外研版初中英语八年级下册/20220118152142043767\": {\"title\": \"外研版初中英语八年级下册/20220118152142043767\", \"tags\": \"[[Module 10]] ?\", \"word\": \"article\", \"created\": \"20220118152142043767\", \"caption\": \"{{||$:/plugins/oflg/fishing-cannedfish/外研版初中英语八年级下册/SearchWord}}\"}, \"外研版初中英语八年级下册/20220118152142043770\": {\"title\": \"外研版初中英语八年级下册/20220118152142043770\", \"tags\": \"[[Module 10]] ?\", \"word\": \"studio\", \"created\": \"20220118152142043770\", \"caption\": \"{{||$:/plugins/oflg/fishing-cannedfish/外研版初中英语八年级下册/SearchWord}}\"}, \"外研版初中英语八年级下册/20220118152142043796\": {\"title\": \"外研版初中英语八年级下册/20220118152142043796\", \"tags\": \"[[Module 10]] ?\", \"word\": \"purpose\", \"created\": \"20220118152142043796\", \"caption\": \"{{||$:/plugins/oflg/fishing-cannedfish/外研版初中英语八年级下册/SearchWord}}\"}}}"}]